{"time": 0.0, "velocity": 0.0, "altitude": 0.0, "velocity_y": 0.065, "velocity_x": 0.0, "acceleration": 10.487, "downrange_distance": 0.0, "angle": 90.0, "q": 0.0}
{"time": 1.0, "velocity": 1.944, "altitude": 0.001, "velocity_y": 1.968, "velocity_x": 0.0, "acceleration": 11.068, "downrange_distance": 0.0, "angle": 90.0, "q": 2.314503215418331}
{"time": 2.0, "velocity": 2.877, "altitude": 0.003, "velocity_y": 3.871, "velocity_x": 0.0, "acceleration": 11.669, "downrange_distance": 0.0, "angle": 90.0, "q": 5.068053533903064}
{"time": 3.0, "velocity": 5.352, "altitude": 0.007, "velocity_y": 5.992, "velocity_x": 0.0, "acceleration": 12.158, "downrange_distance": 0.0, "angle": 90.0, "q": 17.53265649934283}
{"time": 4.0, "velocity": 8.23, "altitude": 0.014, "velocity_y": 8.549, "velocity_x": 0.0, "acceleration": 12.561, "downrange_distance": 0.0, "angle": 90.0, "q": 41.430904917476404}
{"time": 5.0, "velocity": 11.09, "altitude": 0.024, "velocity_y": 11.412, "velocity_x": 0.0, "acceleration": 12.803, "downrange_distance": 0.0, "angle": 90.0, "q": 75.16055825570412}
{"time": 6.0, "velocity": 14.427, "altitude": 0.037, "velocity_y": 14.54, "velocity_x": 0.0, "acceleration": 12.992, "downrange_distance": 0.0, "angle": 90.0, "q": 127.04453223462534}
{"time": 7.0, "velocity": 17.666, "altitude": 0.053, "velocity_y": 17.812, "velocity_x": 0.0, "acceleration": 13.11, "downrange_distance": 0.0, "angle": 90.0, "q": 190.19157198383536}
{"time": 8.0, "velocity": 21.026, "altitude": 0.072, "velocity_y": 21.179, "velocity_x": 0.0, "acceleration": 13.195, "downrange_distance": 0.0, "angle": 90.0, "q": 268.9107066982518}
{"time": 9.0, "velocity": 24.688, "altitude": 0.095, "velocity_y": 24.628, "velocity_x": 0.0, "acceleration": 13.263, "downrange_distance": 0.0, "angle": 90.0, "q": 369.9345782072391}
{"time": 10.0, "velocity": 28.03, "altitude": 0.121, "velocity_y": 28.148, "velocity_x": 0.0, "acceleration": 13.356, "downrange_distance": 0.0, "angle": 90.0, "q": 475.6487204313603}
{"time": 11.0, "velocity": 31.544, "altitude": 0.151, "velocity_y": 31.73, "velocity_x": 0.0, "acceleration": 13.45, "downrange_distance": 0.0, "angle": 90.0, "q": 600.6475772968262}
{"time": 12.0, "velocity": 35.338, "altitude": 0.185, "velocity_y": 35.384, "velocity_x": 0.0, "acceleration": 13.524, "downrange_distance": 0.0, "angle": 90.0, "q": 751.4209724412914}
{"time": 13.0, "velocity": 39.038, "altitude": 0.222, "velocity_y": 39.134, "velocity_x": 0.0, "acceleration": 13.595, "downrange_distance": 0.0, "angle": 90.0, "q": 913.7251857710714}
{"time": 14.0, "velocity": 42.741, "altitude": 0.263, "velocity_y": 43.004, "velocity_x": 0.0, "acceleration": 13.682, "downrange_distance": 0.0, "angle": 90.0, "q": 1090.969901835273}
{"time": 15.0, "velocity": 46.775, "altitude": 0.307, "velocity_y": 46.971, "velocity_x": 0.0, "acceleration": 13.801, "downrange_distance": 0.0, "angle": 90.0, "q": 1300.970047319544}
{"time": 16.0, "velocity": 50.985, "altitude": 0.356, "velocity_y": 51.038, "velocity_x": 0.0, "acceleration": 13.906, "downrange_distance": 0.0, "angle": 90.0, "q": 1538.4052378050587}
{"time": 17.0, "velocity": 55.21, "altitude": 0.409, "velocity_y": 55.195, "velocity_x": 0.0, "acceleration": 13.996, "downrange_distance": 0.0, "angle": 90.0, "q": 1794.7010477988797}
{"time": 18.0, "velocity": 59.232, "altitude": 0.467, "velocity_y": 59.425, "velocity_x": 0.0, "acceleration": 14.047, "downrange_distance": 0.0, "angle": 90.0, "q": 2054.3192609801094}
{"time": 19.0, "velocity": 63.673, "altitude": 0.528, "velocity_y": 63.678, "velocity_x": 0.0, "acceleration": 14.087, "downrange_distance": 0.0, "angle": 90.0, "q": 2359.766527386728}
{"time": 20.0, "velocity": 68.002, "altitude": 0.594, "velocity_y": 67.987, "velocity_x": 0.0, "acceleration": 14.129, "downrange_distance": 0.0, "angle": 90.0, "q": 2674.3836038647532}
{"time": 21.0, "velocity": 72.276, "altitude": 0.664, "velocity_y": 72.347, "velocity_x": 0.0, "acceleration": 14.183, "downrange_distance": 0.0, "angle": 90.0, "q": 3000.53781159126}
{"time": 22.0, "velocity": 76.489, "altitude": 0.738, "velocity_y": 76.776, "velocity_x": 0.0, "acceleration": 14.237, "downrange_distance": 0.0, "angle": 90.0, "q": 3336.256963859034}
{"time": 23.0, "velocity": 81.296, "altitude": 0.817, "velocity_y": 81.233, "velocity_x": 0.0, "acceleration": 14.283, "downrange_distance": 0.0, "angle": 90.0, "q": 3739.790252629657}
{"time": 24.0, "velocity": 85.736, "altitude": 0.901, "velocity_y": 85.77, "velocity_x": 0.0, "acceleration": 14.326, "downrange_distance": 0.0, "angle": 90.0, "q": 4125.620134824153}
{"time": 25.0, "velocity": 90.314, "altitude": 0.989, "velocity_y": 90.355, "velocity_x": 0.0, "acceleration": 14.372, "downrange_distance": 0.0, "angle": 90.0, "q": 4538.6326171457085}
{"time": 26.0, "velocity": 94.755, "altitude": 1.081, "velocity_y": 95.014, "velocity_x": 0.0, "acceleration": 14.449, "downrange_distance": 0.0, "angle": 90.0, "q": 4950.707746114071}
{"time": 27.0, "velocity": 99.751, "altitude": 1.179, "velocity_y": 99.723, "velocity_x": 0.0, "acceleration": 14.557, "downrange_distance": 0.0, "angle": 90.0, "q": 5434.195561813121}
{"time": 28.0, "velocity": 104.33, "altitude": 1.281, "velocity_y": 104.543, "velocity_x": 0.0, "acceleration": 14.695, "downrange_distance": 0.0, "angle": 90.0, "q": 5884.983330726395}
{"time": 29.0, "velocity": 109.326, "altitude": 1.387, "velocity_y": 109.446, "velocity_x": 0.0, "acceleration": 14.803, "downrange_distance": 0.0, "angle": 90.0, "q": 6394.104282775115}
{"time": 30.0, "velocity": 114.322, "altitude": 1.499, "velocity_y": 114.452, "velocity_x": 0.0, "acceleration": 14.88, "downrange_distance": 0.0, "angle": 90.0, "q": 6914.671438303392}
{"time": 31.0, "velocity": 119.456, "altitude": 1.616, "velocity_y": 119.558, "velocity_x": 0.0, "acceleration": 14.941, "downrange_distance": 0.0, "angle": 90.0, "q": 7462.446998871901}
{"time": 32.0, "velocity": 124.591, "altitude": 1.738, "velocity_y": 124.777, "velocity_x": 0.0, "acceleration": 15.003, "downrange_distance": 0.0, "angle": 90.0, "q": 8019.563140468841}
{"time": 33.0, "velocity": 129.865, "altitude": 1.865, "velocity_y": 130.078, "velocity_x": 0.0, "acceleration": 15.079, "downrange_distance": 0.0, "angle": 90.0, "q": 8602.619898204759}
{"time": 34.0, "velocity": 135.555, "altitude": 1.998, "velocity_y": 135.471, "velocity_x": 0.0, "acceleration": 15.172, "downrange_distance": 0.0, "angle": 90.0, "q": 9248.91750167555}
{"time": 35.0, "velocity": 140.829, "altitude": 2.136, "velocity_y": 140.993, "velocity_x": 0.0, "acceleration": 15.294, "downrange_distance": 0.0, "angle": 90.0, "q": 9844.633736168427}
{"time": 36.0, "velocity": 146.241, "altitude": 2.28, "velocity_y": 146.635, "velocity_x": -0.192, "acceleration": 15.433, "downrange_distance": -0.0, "angle": 90.0, "q": 10463.019371850478}
{"time": 37.0, "velocity": 152.197, "altitude": 2.429, "velocity_y": 152.342, "velocity_x": -0.436, "acceleration": 15.542, "downrange_distance": -0.0, "angle": 90.0, "q": 11162.418528450296}
{"time": 38.0, "velocity": 158.299, "altitude": 2.584, "velocity_y": 158.088, "velocity_x": -0.63, "acceleration": 15.635, "downrange_distance": -0.001, "angle": 90.0, "q": 11886.250942360139}
{"time": 39.0, "velocity": 164.145, "altitude": 2.746, "velocity_y": 163.9, "velocity_x": -0.677, "acceleration": 15.712, "downrange_distance": -0.002, "angle": 90.0, "q": 12571.632804755327}
{"time": 40.0, "velocity": 169.419, "altitude": 2.912, "velocity_y": 169.784, "velocity_x": -0.701, "acceleration": 15.8, "downrange_distance": -0.002, "angle": 90.0, "q": 13165.339260994413}
{"time": 41.0, "velocity": 175.248, "altitude": 3.085, "velocity_y": 175.73, "velocity_x": -0.518, "acceleration": 15.886, "downrange_distance": -0.003, "angle": 90.0, "q": 13839.081607038805}
{"time": 42.0, "velocity": 181.771, "altitude": 3.263, "velocity_y": 181.795, "velocity_x": 0.642, "acceleration": 15.989, "downrange_distance": -0.003, "angle": 90.0, "q": 14616.211120878208}
{"time": 43.0, "velocity": 187.979, "altitude": 3.448, "velocity_y": 188.038, "velocity_x": 3.194, "acceleration": 16.125, "downrange_distance": -0.001, "angle": 90.0, "q": 15334.312969950397}
{"time": 44.0, "velocity": 194.082, "altitude": 3.639, "velocity_y": 194.451, "velocity_x": 7.334, "acceleration": 16.284, "downrange_distance": 0.004, "angle": 90.0, "q": 16023.505457834537}
{"time": 45.0, "velocity": 200.787, "altitude": 3.837, "velocity_y": 200.973, "velocity_x": 12.69, "acceleration": 16.411, "downrange_distance": 0.014, "angle": 90.0, "q": 16798.523058163642}
{"time": 46.0, "velocity": 207.588, "altitude": 4.041, "velocity_y": 207.288, "velocity_x": 18.993, "acceleration": 16.474, "downrange_distance": 0.03, "angle": 90.0, "q": 17573.56949641593}
{"time": 47.0, "velocity": 214.25, "altitude": 4.252, "velocity_y": 213.089, "velocity_x": 25.809, "acceleration": 16.447, "downrange_distance": 0.053, "angle": 87.851, "q": 18306.117505423248}
{"time": 48.0, "velocity": 220.993, "altitude": 4.469, "velocity_y": 217.968, "velocity_x": 32.772, "acceleration": 16.213, "downrange_distance": 0.082, "angle": 87.851, "q": 19030.386565595534}
{"time": 49.0, "velocity": 227.298, "altitude": 4.692, "velocity_y": 222.106, "velocity_x": 39.49, "acceleration": 15.733, "downrange_distance": 0.118, "angle": 84.295, "q": 19657.45594272878}
{"time": 50.0, "velocity": 232.365, "altitude": 4.923, "velocity_y": 225.584, "velocity_x": 45.324, "acceleration": 15.073, "downrange_distance": 0.16, "angle": 80.333, "q": 20038.33836857829}
{"time": 51.0, "velocity": 236.873, "altitude": 5.146, "velocity_y": 229.143, "velocity_x": 50.105, "acceleration": 14.551, "downrange_distance": 0.208, "angle": 77.081, "q": 20327.613435006362}
{"time": 52.0, "velocity": 241.036, "altitude": 5.369, "velocity_y": 233.434, "velocity_x": 53.642, "acceleration": 14.272, "downrange_distance": 0.26, "angle": 76.577, "q": 20543.58146113784}
{"time": 53.0, "velocity": 245.688, "altitude": 5.604, "velocity_y": 238.785, "velocity_x": 56.186, "acceleration": 14.243, "downrange_distance": 0.315, "angle": 76.577, "q": 20800.46999925597}
{"time": 54.0, "velocity": 250.387, "altitude": 5.853, "velocity_y": 244.477, "velocity_x": 58.018, "acceleration": 14.33, "downrange_distance": 0.372, "angle": 78.498, "q": 21018.136098096948}
{"time": 55.0, "velocity": 254.664, "altitude": 6.1, "velocity_y": 249.972, "velocity_x": 59.92, "acceleration": 14.473, "downrange_distance": 0.431, "angle": 80.629, "q": 21155.95151797157}
{"time": 56.0, "velocity": 260.186, "altitude": 6.37, "velocity_y": 254.64, "velocity_x": 62.748, "acceleration": 14.641, "downrange_distance": 0.492, "angle": 80.353, "q": 21426.95234985747}
{"time": 57.0, "velocity": 265.46, "altitude": 6.626, "velocity_y": 258.682, "velocity_x": 66.576, "acceleration": 14.762, "downrange_distance": 0.557, "angle": 79.389, "q": 21670.92155159848}
{"time": 58.0, "velocity": 270.593, "altitude": 6.886, "velocity_y": 261.864, "velocity_x": 71.243, "acceleration": 14.851, "downrange_distance": 0.626, "angle": 76.269, "q": 21863.74148748671}
{"time": 59.0, "velocity": 275.622, "altitude": 7.143, "velocity_y": 264.98, "velocity_x": 76.154, "acceleration": 14.901, "downrange_distance": 0.7, "angle": 74.638, "q": 22027.52331531652}
{"time": 60.0, "velocity": 281.14, "altitude": 7.412, "velocity_y": 268.433, "velocity_x": 81.059, "acceleration": 14.938, "downrange_distance": 0.778, "angle": 73.586, "q": 22222.2524552077}
{"time": 61.0, "velocity": 286.832, "altitude": 7.698, "velocity_y": 272.48, "velocity_x": 85.629, "acceleration": 14.925, "downrange_distance": 0.862, "angle": 73.623, "q": 22377.301919050453}
{"time": 62.0, "velocity": 292.384, "altitude": 7.969, "velocity_y": 276.825, "velocity_x": 89.878, "acceleration": 14.899, "downrange_distance": 0.949, "angle": 71.565, "q": 22528.76544544113}
{"time": 63.0, "velocity": 297.935, "altitude": 8.262, "velocity_y": 281.685, "velocity_x": 93.93, "acceleration": 14.88, "downrange_distance": 1.041, "angle": 70.854, "q": 22602.444891516494}
{"time": 64.0, "velocity": 303.636, "altitude": 8.551, "velocity_y": 287.382, "velocity_x": 97.692, "acceleration": 15.004, "downrange_distance": 1.137, "angle": 70.499, "q": 22684.55620944261}
{"time": 65.0, "velocity": 309.803, "altitude": 8.771, "velocity_y": 293.406, "velocity_x": 101.225, "acceleration": 15.167, "downrange_distance": 1.236, "angle": 73.382, "q": 23004.11897932129}
{"time": 66.0, "velocity": 315.285, "altitude": 9.139, "velocity_y": 299.412, "velocity_x": 104.567, "acceleration": 15.398, "downrange_distance": 1.339, "angle": 73.078, "q": 22791.70145410408}
{"time": 67.0, "velocity": 321.666, "altitude": 9.45, "velocity_y": 304.533, "velocity_x": 107.895, "acceleration": 15.536, "downrange_distance": 1.446, "angle": 74.786, "q": 22845.340626522968}
{"time": 68.0, "velocity": 327.769, "altitude": 9.761, "velocity_y": 308.83, "velocity_x": 111.114, "acceleration": 15.61, "downrange_distance": 1.555, "angle": 73.964, "q": 22834.534334526965}
{"time": 69.0, "velocity": 333.88, "altitude": 10.069, "velocity_y": 312.562, "velocity_x": 114.167, "acceleration": 15.569, "downrange_distance": 1.668, "angle": 70.864, "q": 22806.29036035877}
{"time": 70.0, "velocity": 340.53, "altitude": 10.392, "velocity_y": 317.251, "velocity_x": 117.123, "acceleration": 15.55, "downrange_distance": 1.783, "angle": 66.661, "q": 22786.848452975206}
{"time": 71.0, "velocity": 347.22, "altitude": 10.699, "velocity_y": 323.217, "velocity_x": 120.29, "acceleration": 15.665, "downrange_distance": 1.902, "angle": 67.17, "q": 22792.7164895111}
{"time": 72.0, "velocity": 353.621, "altitude": 10.937, "velocity_y": 330.095, "velocity_x": 123.849, "acceleration": 16.008, "downrange_distance": 2.024, "angle": 71.137, "q": 22937.27901880644}
{"time": 73.0, "velocity": 360.228, "altitude": 11.383, "velocity_y": 338.162, "velocity_x": 127.946, "acceleration": 16.679, "downrange_distance": 2.15, "angle": 71.067, "q": 22479.83135081421}
{"time": 74.0, "velocity": 368.554, "altitude": 11.736, "velocity_y": 346.541, "velocity_x": 132.599, "acceleration": 17.594, "downrange_distance": 2.28, "angle": 72.516, "q": 22476.36580583018}
{"time": 75.0, "velocity": 378.3, "altitude": 12.082, "velocity_y": 354.856, "velocity_x": 138.02, "acceleration": 18.524, "downrange_distance": 2.416, "angle": 72.152, "q": 22628.37881164657}
{"time": 76.0, "velocity": 388.259, "altitude": 12.422, "velocity_y": 362.025, "velocity_x": 144.406, "acceleration": 19.063, "downrange_distance": 2.557, "angle": 70.92, "q": 22782.9743761199}
{"time": 77.0, "velocity": 398.725, "altitude": 12.779, "velocity_y": 369.036, "velocity_x": 151.798, "acceleration": 19.354, "downrange_distance": 2.705, "angle": 66.112, "q": 22904.286451383763}
{"time": 78.0, "velocity": 410.097, "altitude": 13.184, "velocity_y": 375.983, "velocity_x": 159.868, "acceleration": 19.528, "downrange_distance": 2.861, "angle": 65.324, "q": 22933.355397424315}
{"time": 79.0, "velocity": 420.457, "altitude": 13.558, "velocity_y": 383.69, "velocity_x": 168.369, "acceleration": 19.819, "downrange_distance": 3.025, "angle": 65.5, "q": 22898.779548845552}
{"time": 80.0, "velocity": 431.56, "altitude": 13.931, "velocity_y": 391.867, "velocity_x": 177.076, "acceleration": 20.019, "downrange_distance": 3.198, "angle": 65.332, "q": 22903.70882437427}
{"time": 81.0, "velocity": 442.663, "altitude": 14.332, "velocity_y": 400.955, "velocity_x": 185.777, "acceleration": 20.184, "downrange_distance": 3.379, "angle": 64.793, "q": 22774.286202352727}
{"time": 82.0, "velocity": 454.599, "altitude": 14.757, "velocity_y": 410.618, "velocity_x": 194.169, "acceleration": 20.322, "downrange_distance": 3.569, "angle": 64.352, "q": 22603.50089614647}
{"time": 83.0, "velocity": 465.98, "altitude": 15.18, "velocity_y": 421.027, "velocity_x": 202.263, "acceleration": 20.534, "downrange_distance": 3.767, "angle": 64.671, "q": 22336.525800403}
{"time": 84.0, "velocity": 477.639, "altitude": 15.596, "velocity_y": 431.002, "velocity_x": 210.292, "acceleration": 20.737, "downrange_distance": 3.974, "angle": 64.661, "q": 22076.38012707222}
{"time": 85.0, "velocity": 489.853, "altitude": 16.042, "velocity_y": 439.55, "velocity_x": 218.594, "acceleration": 20.907, "downrange_distance": 4.188, "angle": 63.826, "q": 21723.43574789666}
{"time": 86.0, "velocity": 502.622, "altitude": 16.502, "velocity_y": 447.75, "velocity_x": 227.121, "acceleration": 21.018, "downrange_distance": 4.411, "angle": 62.886, "q": 21332.166235499986}
{"time": 87.0, "velocity": 514.836, "altitude": 16.957, "velocity_y": 456.777, "velocity_x": 235.949, "acceleration": 21.137, "downrange_distance": 4.642, "angle": 62.552, "q": 20864.217858244738}
{"time": 88.0, "velocity": 527.328, "altitude": 17.408, "velocity_y": 466.284, "velocity_x": 244.971, "acceleration": 21.298, "downrange_distance": 4.883, "angle": 62.099, "q": 20394.406289216684}
{"time": 89.0, "velocity": 539.918, "altitude": 17.872, "velocity_y": 475.603, "velocity_x": 254.282, "acceleration": 21.522, "downrange_distance": 5.132, "angle": 61.611, "q": 19855.383353586527}
{"time": 90.0, "velocity": 553.978, "altitude": 18.388, "velocity_y": 486.004, "velocity_x": 263.791, "acceleration": 21.804, "downrange_distance": 5.392, "angle": 61.051, "q": 19221.55403868268}
{"time": 91.0, "velocity": 567.304, "altitude": 18.872, "velocity_y": 497.205, "velocity_x": 273.552, "acceleration": 22.08, "downrange_distance": 5.66, "angle": 61.273, "q": 18604.829557733126}
{"time": 92.0, "velocity": 580.98, "altitude": 19.375, "velocity_y": 508.275, "velocity_x": 283.662, "acceleration": 22.305, "downrange_distance": 5.939, "angle": 61.023, "q": 17923.87653766889}
{"time": 93.0, "velocity": 594.575, "altitude": 19.887, "velocity_y": 518.409, "velocity_x": 294.276, "acceleration": 22.49, "downrange_distance": 6.228, "angle": 60.617, "q": 17186.244131862128}
{"time": 94.0, "velocity": 609.558, "altitude": 20.434, "velocity_y": 528.325, "velocity_x": 305.47, "acceleration": 22.694, "downrange_distance": 6.528, "angle": 59.976, "q": 16405.705744954492}
{"time": 95.0, "velocity": 623.66, "altitude": 20.972, "velocity_y": 537.868, "velocity_x": 317.122, "acceleration": 22.937, "downrange_distance": 6.839, "angle": 59.678, "q": 15587.662016433893}
{"time": 96.0, "velocity": 638.096, "altitude": 21.503, "velocity_y": 546.621, "velocity_x": 329.069, "acceleration": 23.146, "downrange_distance": 7.162, "angle": 59.138, "q": 14795.294016957661}
{"time": 97.0, "velocity": 653.153, "altitude": 22.072, "velocity_y": 555.368, "velocity_x": 341.194, "acceleration": 23.259, "downrange_distance": 7.497, "angle": 58.138, "q": 13923.362426749896}
{"time": 98.0, "velocity": 668.635, "altitude": 22.631, "velocity_y": 565.393, "velocity_x": 353.417, "acceleration": 23.33, "downrange_distance": 7.844, "angle": 57.8, "q": 13094.694007809518}
{"time": 99.0, "velocity": 683.627, "altitude": 23.212, "velocity_y": 576.522, "velocity_x": 365.79, "acceleration": 23.461, "downrange_distance": 8.204, "angle": 57.4, "q": 12194.284969564027}
{"time": 100.0, "velocity": 698.627, "altitude": 23.769, "velocity_y": 587.613, "velocity_x": 378.331, "acceleration": 23.717, "downrange_distance": 8.576, "angle": 57.398, "q": 11366.558477303515}
{"time": 101.0, "velocity": 715.555, "altitude": 24.409, "velocity_y": 599.468, "velocity_x": 391.24, "acceleration": 24.032, "downrange_distance": 8.961, "angle": 56.722, "q": 10422.518161532696}
{"time": 102.0, "velocity": 731.38, "altitude": 25.009, "velocity_y": 611.285, "velocity_x": 404.592, "acceleration": 24.364, "downrange_distance": 9.359, "angle": 56.771, "q": 9559.443291620164}
{"time": 103.0, "velocity": 747.743, "altitude": 25.627, "velocity_y": 622.059, "velocity_x": 418.534, "acceleration": 24.638, "downrange_distance": 9.77, "angle": 56.319, "q": 8702.25380245014}
{"time": 104.0, "velocity": 764.116, "altitude": 26.248, "velocity_y": 631.595, "velocity_x": 432.813, "acceleration": 24.875, "downrange_distance": 10.196, "angle": 55.807, "q": 7870.928577146621}
{"time": 105.0, "velocity": 781.632, "altitude": 26.912, "velocity_y": 640.776, "velocity_x": 447.311, "acceleration": 25.057, "downrange_distance": 10.636, "angle": 54.865, "q": 7023.8660675839255}
{"time": 106.0, "velocity": 798.846, "altitude": 27.566, "velocity_y": 650.077, "velocity_x": 461.755, "acceleration": 25.204, "downrange_distance": 11.091, "angle": 54.495, "q": 6234.123445829249}
{"time": 107.0, "velocity": 815.959, "altitude": 28.193, "velocity_y": 660.157, "velocity_x": 476.077, "acceleration": 25.302, "downrange_distance": 11.56, "angle": 54.133, "q": 5529.010616677352}
{"time": 108.0, "velocity": 833.493, "altitude": 28.87, "velocity_y": 670.871, "velocity_x": 490.265, "acceleration": 25.402, "downrange_distance": 12.043, "angle": 53.46, "q": 4807.608196404973}
{"time": 109.0, "velocity": 851.531, "altitude": 29.568, "velocity_y": 684.203, "velocity_x": 504.327, "acceleration": 25.624, "downrange_distance": 12.54, "angle": 53.393, "q": 4122.580093073718}
{"time": 110.0, "velocity": 870.404, "altitude": 30.267, "velocity_y": 698.93, "velocity_x": 518.419, "acceleration": 26.017, "downrange_distance": 13.051, "angle": 53.518, "q": 3503.5228613557424}
{"time": 111.0, "velocity": 887.247, "altitude": 30.939, "velocity_y": 713.38, "velocity_x": 532.621, "acceleration": 26.522, "downrange_distance": 13.577, "angle": 53.677, "q": 2955.5739390762906}
{"time": 112.0, "velocity": 907.592, "altitude": 31.72, "velocity_y": 726.004, "velocity_x": 547.638, "acceleration": 26.958, "downrange_distance": 14.117, "angle": 53.117, "q": 2395.4393303693205}
{"time": 113.0, "velocity": 927.298, "altitude": 32.463, "velocity_y": 737.763, "velocity_x": 564.134, "acceleration": 27.312, "downrange_distance": 14.673, "angle": 52.818, "q": 1930.5618274844817}
{"time": 114.0, "velocity": 946.447, "altitude": 33.19, "velocity_y": 747.838, "velocity_x": 582.251, "acceleration": 27.514, "downrange_distance": 15.246, "angle": 52.213, "q": 1536.9667391572973}
{"time": 115.0, "velocity": 966.195, "altitude": 33.941, "velocity_y": 757.826, "velocity_x": 601.654, "acceleration": 27.656, "downrange_distance": 15.838, "angle": 51.793, "q": 1190.2085059319727}
{"time": 116.0, "velocity": 986.691, "altitude": 34.713, "velocity_y": 767.374, "velocity_x": 622.024, "acceleration": 27.694, "downrange_distance": 16.45, "angle": 50.919, "q": 893.3970787939538}
{"time": 117.0, "velocity": 1006.952, "altitude": 35.488, "velocity_y": 776.271, "velocity_x": 642.593, "acceleration": 27.745, "downrange_distance": 17.082, "angle": 50.435, "q": 651.0402699442428}
{"time": 118.0, "velocity": 1028.745, "altitude": 36.31, "velocity_y": 784.058, "velocity_x": 662.458, "acceleration": 27.758, "downrange_distance": 17.735, "angle": 49.813, "q": 448.42882652616765}
{"time": 119.0, "velocity": 1048.712, "altitude": 37.065, "velocity_y": 790.986, "velocity_x": 681.261, "acceleration": 27.907, "downrange_distance": 18.407, "angle": 49.042, "q": 306.07003480463766}
{"time": 120.0, "velocity": 1069.124, "altitude": 37.864, "velocity_y": 804.436, "velocity_x": 699.153, "acceleration": 28.176, "downrange_distance": 19.097, "angle": 48.684, "q": 193.71948608325798}
{"time": 121.0, "velocity": 1090.883, "altitude": 38.687, "velocity_y": 818.687, "velocity_x": 716.595, "acceleration": 28.723, "downrange_distance": 19.805, "angle": 48.567, "q": 113.02096571894845}
{"time": 122.0, "velocity": 1110.681, "altitude": 39.46, "velocity_y": 834.997, "velocity_x": 733.788, "acceleration": 29.297, "downrange_distance": 20.53, "angle": 48.779, "q": 62.55712661320445}
{"time": 123.0, "velocity": 1135.555, "altitude": 40.412, "velocity_y": 853.558, "velocity_x": 750.922, "acceleration": 29.953, "downrange_distance": 21.272, "angle": 48.74, "q": 25.935284544908903}
{"time": 124.0, "velocity": 1158.307, "altitude": 41.259, "velocity_y": 873.131, "velocity_x": 768.605, "acceleration": 30.434, "downrange_distance": 22.032, "angle": 48.975, "q": 9.563760753356059}
{"time": 125.0, "velocity": 1181.54, "altitude": 42.127, "velocity_y": 884.832, "velocity_x": 787.632, "acceleration": 30.79, "downrange_distance": 22.81, "angle": 48.546, "q": 2.422546660780652}
{"time": 126.0, "velocity": 1205.269, "altitude": 43.03, "velocity_y": 895.501, "velocity_x": 808.345, "acceleration": 30.904, "downrange_distance": 23.608, "angle": 48.033, "q": 0.2675913200982208}
{"time": 127.0, "velocity": 1229.006, "altitude": 43.956, "velocity_y": 905.585, "velocity_x": 830.658, "acceleration": 30.961, "downrange_distance": 24.428, "angle": 47.249, "q": 0.0013900109708474416}
{"time": 128.0, "velocity": 1252.878, "altitude": 44.855, "velocity_y": 916.327, "velocity_x": 854.273, "acceleration": 31.072, "downrange_distance": 25.27, "angle": 47.009, "q": 0.0}
{"time": 129.0, "velocity": 1277.028, "altitude": 45.755, "velocity_y": 926.585, "velocity_x": 878.892, "acceleration": 31.324, "downrange_distance": 26.137, "angle": 46.552, "q": 0.0}
{"time": 130.0, "velocity": 1302.878, "altitude": 46.721, "velocity_y": 936.205, "velocity_x": 903.874, "acceleration": 31.673, "downrange_distance": 27.028, "angle": 45.952, "q": 0.0}
{"time": 131.0, "velocity": 1328.106, "altitude": 47.686, "velocity_y": 945.195, "velocity_x": 928.586, "acceleration": 32.053, "downrange_distance": 27.944, "angle": 45.423, "q": 0.0}
{"time": 132.0, "velocity": 1352.811, "altitude": 48.619, "velocity_y": 959.836, "velocity_x": 952.846, "acceleration": 32.419, "downrange_distance": 28.885, "angle": 45.243, "q": 0.0}
{"time": 133.0, "velocity": 1378.358, "altitude": 49.577, "velocity_y": 972.923, "velocity_x": 976.807, "acceleration": 32.817, "downrange_distance": 29.85, "angle": 44.932, "q": 0.0}
{"time": 134.0, "velocity": 1404.722, "altitude": 50.55, "velocity_y": 985.683, "velocity_x": 1000.641, "acceleration": 33.23, "downrange_distance": 30.839, "angle": 44.624, "q": 0.0}
{"time": 135.0, "velocity": 1432.205, "altitude": 51.614, "velocity_y": 999.625, "velocity_x": 1024.3, "acceleration": 33.653, "downrange_distance": 31.851, "angle": 44.241, "q": 0.0}
{"time": 136.0, "velocity": 1459.41, "altitude": 52.607, "velocity_y": 1017.079, "velocity_x": 1048.909, "acceleration": 33.996, "downrange_distance": 32.888, "angle": 44.208, "q": 0.0}
{"time": 137.0, "velocity": 1486.565, "altitude": 53.614, "velocity_y": 1029.68, "velocity_x": 1075.247, "acceleration": 34.29, "downrange_distance": 33.95, "angle": 43.894, "q": 0.0}
{"time": 138.0, "velocity": 1514.621, "altitude": 54.644, "velocity_y": 1043.132, "velocity_x": 1103.073, "acceleration": 34.519, "downrange_distance": 35.039, "angle": 43.454, "q": 0.0}
{"time": 139.0, "velocity": 1543.804, "altitude": 55.745, "velocity_y": 1057.248, "velocity_x": 1131.058, "acceleration": 34.666, "downrange_distance": 36.156, "angle": 43.135, "q": 0.0}
{"time": 140.0, "velocity": 1572.626, "altitude": 56.815, "velocity_y": 1071.395, "velocity_x": 1157.556, "acceleration": 34.708, "downrange_distance": 37.3, "angle": 43.054, "q": 0.0}
{"time": 141.0, "velocity": 1600.757, "altitude": 57.841, "velocity_y": 1081.932, "velocity_x": 1181.585, "acceleration": 34.603, "downrange_distance": 38.47, "angle": 42.581, "q": 0.0}
{"time": 142.0, "velocity": 1630.976, "altitude": 59.009, "velocity_y": 1089.977, "velocity_x": 1202.496, "acceleration": 34.153, "downrange_distance": 39.662, "angle": 42.178, "q": 0.0}
{"time": 143.0, "velocity": 1658.459, "altitude": 60.115, "velocity_y": 1095.88, "velocity_x": 1219.747, "acceleration": 32.025, "downrange_distance": 40.873, "angle": 41.967, "q": 0.0}
{"time": 144.0, "velocity": 1680.388, "altitude": 61.125, "velocity_y": 1100.822, "velocity_x": 1232.716, "acceleration": 24.026, "downrange_distance": 42.099, "angle": 42.052, "q": 0.0}
{"time": 145.0, "velocity": 1684.32, "altitude": 62.363, "velocity_y": 1104.473, "velocity_x": 1241.554, "acceleration": 13.793, "downrange_distance": 43.336, "angle": 41.53, "q": 0.0}
{"time": 146.0, "velocity": 1680.378, "altitude": 63.47, "velocity_y": 1107.087, "velocity_x": 1246.549, "acceleration": 4.634, "downrange_distance": 44.58, "angle": 41.36, "q": 0.0}
{"time": 147.0, "velocity": 1673.998, "altitude": 64.579, "velocity_y": 1107.371, "velocity_x": 1248.233, "acceleration": 1.176, "downrange_distance": 45.828, "angle": 41.407, "q": 0.0}
{"time": 148.0, "velocity": 1666.902, "altitude": 65.577, "velocity_y": 1104.363, "velocity_x": 1247.282, "acceleration": 0.262, "downrange_distance": 47.076, "angle": 41.705, "q": 0.0}
{"time": 149.0, "velocity": 1659.846, "altitude": 66.715, "velocity_y": 1098.438, "velocity_x": 1244.926, "acceleration": -0.044, "downrange_distance": 48.322, "angle": 41.492, "q": 0.0}
{"time": 150.0, "velocity": 1653.261, "altitude": 67.907, "velocity_y": 1090.791, "velocity_x": 1243.081, "acceleration": -0.111, "downrange_distance": 49.566, "angle": 41.724, "q": 0.0}
{"time": 151.0, "velocity": 1647.015, "altitude": 68.966, "velocity_y": 1081.273, "velocity_x": 1242.173, "acceleration": -0.163, "downrange_distance": 50.808, "angle": 41.771, "q": 0.0}
{"time": 152.0, "velocity": 1640.908, "altitude": 70.032, "velocity_y": 1071.581, "velocity_x": 1241.645, "acceleration": -0.235, "downrange_distance": 52.05, "angle": 41.403, "q": 0.0}
{"time": 153.0, "velocity": 1634.245, "altitude": 71.133, "velocity_y": 1063.077, "velocity_x": 1240.99, "acceleration": -0.342, "downrange_distance": 53.291, "angle": 40.799, "q": 0.0}
{"time": 154.0, "velocity": 1627.945, "altitude": 72.162, "velocity_y": 1054.794, "velocity_x": 1240.239, "acceleration": -0.482, "downrange_distance": 54.532, "angle": 40.43, "q": 0.0}
{"time": 155.0, "velocity": 1621.007, "altitude": 73.178, "velocity_y": 1045.247, "velocity_x": 1239.393, "acceleration": -0.633, "downrange_distance": 55.772, "angle": 40.192, "q": 0.0}
{"time": 156.0, "velocity": 1613.146, "altitude": 74.264, "velocity_y": 1034.604, "velocity_x": 1238.408, "acceleration": -0.74, "downrange_distance": 57.011, "angle": 39.871, "q": 0.0}
{"time": 157.0, "velocity": 1605.471, "altitude": 75.294, "velocity_y": 1024.02, "velocity_x": 1237.152, "acceleration": -0.839, "downrange_distance": 58.249, "angle": 39.627, "q": 0.0}
{"time": 158.0, "velocity": 1598.257, "altitude": 76.259, "velocity_y": 1013.898, "velocity_x": 1235.463, "acceleration": -0.947, "downrange_distance": 59.485, "angle": 39.352, "q": 0.0}
{"time": 159.0, "velocity": 1591.318, "altitude": 77.287, "velocity_y": 1004.71, "velocity_x": 1233.522, "acceleration": -1.085, "downrange_distance": 60.719, "angle": 38.845, "q": 0.0}
{"time": 160.0, "velocity": 1584.83, "altitude": 78.291, "velocity_y": 996.79, "velocity_x": 1231.435, "acceleration": -1.197, "downrange_distance": 61.952, "angle": 38.579, "q": 0.0}
{"time": 161.0, "velocity": 1578.723, "altitude": 79.232, "velocity_y": 990.391, "velocity_x": 1229.272, "acceleration": -1.4, "downrange_distance": 63.182, "angle": 38.65, "q": 0.0}
{"time": 162.0, "velocity": 1571.346, "altitude": 80.189, "velocity_y": 983.774, "velocity_x": 1226.979, "acceleration": -1.843, "downrange_distance": 64.41, "angle": 38.877, "q": 0.0}
{"time": 163.0, "velocity": 1562.743, "altitude": 81.221, "velocity_y": 976.701, "velocity_x": 1223.605, "acceleration": -2.617, "downrange_distance": 65.636, "angle": 38.79, "q": 0.0}
{"time": 164.0, "velocity": 1553.03, "altitude": 82.21, "velocity_y": 968.418, "velocity_x": 1218.187, "acceleration": -3.54, "downrange_distance": 66.857, "angle": 38.96, "q": 0.0}
{"time": 165.0, "velocity": 1541.927, "altitude": 83.186, "velocity_y": 955.998, "velocity_x": 1210.071, "acceleration": -4.56, "downrange_distance": 68.071, "angle": 38.586, "q": 0.0}
{"time": 166.0, "velocity": 1531.371, "altitude": 84.086, "velocity_y": 943.044, "velocity_x": 1198.645, "acceleration": -7.535, "downrange_distance": 69.275, "angle": 38.324, "q": 0.0}
{"time": 167.0, "velocity": 1512.777, "altitude": 85.078, "velocity_y": 931.0, "velocity_x": 1183.484, "acceleration": -11.347, "downrange_distance": 70.466, "angle": 37.821, "q": 0.0}
{"time": 168.0, "velocity": 1491.136, "altitude": 85.889, "velocity_y": 918.465, "velocity_x": 1164.84, "acceleration": -16.577, "downrange_distance": 71.64, "angle": 38.145, "q": 0.0}
{"time": 169.0, "velocity": 1461.176, "altitude": 86.848, "velocity_y": 906.826, "velocity_x": 1142.819, "acceleration": -19.857, "downrange_distance": 72.794, "angle": 38.378, "q": 0.0}
{"time": 170.0, "velocity": 1432.9, "altitude": 87.747, "velocity_y": 898.74, "velocity_x": 1117.683, "acceleration": -22.138, "downrange_distance": 73.924, "angle": 39.111, "q": 0.0}
{"time": 171.0, "velocity": 1405.098, "altitude": 88.646, "velocity_y": 891.294, "velocity_x": 1089.972, "acceleration": -22.69, "downrange_distance": 75.028, "angle": 39.587, "q": 0.0}
{"time": 172.0, "velocity": 1375.678, "altitude": 89.546, "velocity_y": 882.897, "velocity_x": 1060.264, "acceleration": -22.911, "downrange_distance": 76.103, "angle": 40.304, "q": 0.0}
{"time": 173.0, "velocity": 1346.562, "altitude": 90.413, "velocity_y": 873.773, "velocity_x": 1029.364, "acceleration": -23.288, "downrange_distance": 77.148, "angle": 40.641, "q": 0.0}
{"time": 174.0, "velocity": 1317.394, "altitude": 91.27, "velocity_y": 860.805, "velocity_x": 997.778, "acceleration": -23.885, "downrange_distance": 78.162, "angle": 40.889, "q": 0.0}
{"time": 175.0, "velocity": 1285.473, "altitude": 92.144, "velocity_y": 847.437, "velocity_x": 966.046, "acceleration": -24.771, "downrange_distance": 79.144, "angle": 41.296, "q": 0.0}
{"time": 176.0, "velocity": 1253.627, "altitude": 92.972, "velocity_y": 834.135, "velocity_x": 934.245, "acceleration": -25.621, "downrange_distance": 80.094, "angle": 41.78, "q": 0.0}
{"time": 177.0, "velocity": 1221.242, "altitude": 93.739, "velocity_y": 820.665, "velocity_x": 901.707, "acceleration": -26.482, "downrange_distance": 81.012, "angle": 42.364, "q": 0.0}
{"time": 178.0, "velocity": 1186.102, "altitude": 94.608, "velocity_y": 806.39, "velocity_x": 868.225, "acceleration": -27.305, "downrange_distance": 81.897, "angle": 42.862, "q": 0.0}
{"time": 179.0, "velocity": 1151.786, "altitude": 95.395, "velocity_y": 794.533, "velocity_x": 834.276, "acceleration": -27.933, "downrange_distance": 82.748, "angle": 43.73, "q": 0.0}
{"time": 180.0, "velocity": 1116.985, "altitude": 96.14, "velocity_y": 782.46, "velocity_x": 799.285, "acceleration": -28.254, "downrange_distance": 83.565, "angle": 44.623, "q": 0.0}
{"time": 181.0, "velocity": 1080.294, "altitude": 96.938, "velocity_y": 766.338, "velocity_x": 762.981, "acceleration": -28.402, "downrange_distance": 84.346, "angle": 45.288, "q": 0.0}
{"time": 182.0, "velocity": 1043.145, "altitude": 97.702, "velocity_y": 750.309, "velocity_x": 725.388, "acceleration": -28.601, "downrange_distance": 85.09, "angle": 45.701, "q": 0.0}
{"time": 183.0, "velocity": 1006.977, "altitude": 98.419, "velocity_y": 735.932, "velocity_x": 687.048, "acceleration": -28.89, "downrange_distance": 85.796, "angle": 46.803, "q": 0.0}
{"time": 184.0, "velocity": 972.006, "altitude": 99.121, "velocity_y": 722.72, "velocity_x": 648.3, "acceleration": -28.895, "downrange_distance": 86.464, "angle": 48.142, "q": 0.0}
{"time": 185.0, "velocity": 937.957, "altitude": 99.803, "velocity_y": 709.989, "velocity_x": 608.853, "acceleration": -28.577, "downrange_distance": 87.092, "angle": 49.573, "q": 0.0}
{"time": 186.0, "velocity": 899.632, "altitude": 100.561, "velocity_y": 697.641, "velocity_x": 568.664, "acceleration": -27.974, "downrange_distance": 87.681, "angle": 50.982, "q": 0.0}
{"time": 187.0, "velocity": 863.154, "altitude": 101.25, "velocity_y": 685.807, "velocity_x": 528.0, "acceleration": -27.493, "downrange_distance": 88.23, "angle": 52.996, "q": 0.0}
{"time": 188.0, "velocity": 828.186, "altitude": 101.894, "velocity_y": 673.731, "velocity_x": 485.796, "acceleration": -27.08, "downrange_distance": 88.736, "angle": 54.906, "q": 0.0}
{"time": 189.0, "velocity": 794.134, "altitude": 102.553, "velocity_y": 658.487, "velocity_x": 442.072, "acceleration": -26.721, "downrange_distance": 89.2, "angle": 56.411, "q": 0.0}
{"time": 190.0, "velocity": 757.418, "altitude": 103.228, "velocity_y": 642.955, "velocity_x": 396.888, "acceleration": -26.049, "downrange_distance": 89.62, "angle": 57.982, "q": 0.0}
{"time": 191.0, "velocity": 723.366, "altitude": 103.845, "velocity_y": 631.532, "velocity_x": 351.701, "acceleration": -25.215, "downrange_distance": 89.994, "angle": 60.964, "q": 0.0}
{"time": 192.0, "velocity": 692.63, "altitude": 104.424, "velocity_y": 620.566, "velocity_x": 302.344, "acceleration": -24.092, "downrange_distance": 90.321, "angle": 64.801, "q": 0.0}
{"time": 193.0, "velocity": 660.506, "altitude": 105.059, "velocity_y": 607.165, "velocity_x": 253.458, "acceleration": -22.802, "downrange_distance": 90.599, "angle": 67.972, "q": 0.0}
{"time": 194.0, "velocity": 628.161, "altitude": 105.685, "velocity_y": 593.957, "velocity_x": 206.606, "acceleration": -20.951, "downrange_distance": 90.829, "angle": 71.218, "q": 0.0}
{"time": 195.0, "velocity": 600.696, "altitude": 106.247, "velocity_y": 580.04, "velocity_x": 160.636, "acceleration": -18.821, "downrange_distance": 91.013, "angle": 76.078, "q": 0.0}
{"time": 196.0, "velocity": 574.599, "altitude": 106.799, "velocity_y": 564.086, "velocity_x": 115.274, "acceleration": -16.529, "downrange_distance": 91.151, "angle": 80.437, "q": 0.0}
{"time": 197.0, "velocity": 550.457, "altitude": 107.356, "velocity_y": 546.621, "velocity_x": 71.039, "acceleration": -13.938, "downrange_distance": 91.244, "angle": 83.37, "q": 0.0}
{"time": 198.0, "velocity": 529.975, "altitude": 107.895, "velocity_y": 531.063, "velocity_x": 27.55, "acceleration": -10.458, "downrange_distance": 91.293, "angle": 86.374, "q": 0.0}
{"time": 199.0, "velocity": 514.427, "altitude": 108.415, "velocity_y": 516.853, "velocity_x": -16.268, "acceleration": -6.197, "downrange_distance": 91.299, "angle": 87.381, "q": 0.0}
{"time": 200.0, "velocity": 503.325, "altitude": 108.926, "velocity_y": 501.73, "velocity_x": -61.195, "acceleration": -1.613, "downrange_distance": 91.26, "angle": 84.404, "q": 0.0}
{"time": 201.0, "velocity": 496.761, "altitude": 109.42, "velocity_y": 487.012, "velocity_x": -108.126, "acceleration": 3.303, "downrange_distance": 91.175, "angle": 79.389, "q": 0.0}
{"time": 202.0, "velocity": 496.33, "altitude": 109.887, "velocity_y": 473.157, "velocity_x": -157.155, "acceleration": 8.529, "downrange_distance": 91.043, "angle": 73.518, "q": 0.0}
{"time": 203.0, "velocity": 501.649, "altitude": 110.335, "velocity_y": 459.714, "velocity_x": -206.773, "acceleration": 13.794, "downrange_distance": 90.861, "angle": 66.65, "q": 0.0}
{"time": 204.0, "velocity": 512.727, "altitude": 110.783, "velocity_y": 445.832, "velocity_x": -255.761, "acceleration": 17.193, "downrange_distance": 90.63, "angle": 60.407, "q": 0.0}
{"time": 205.0, "velocity": 530.488, "altitude": 111.227, "velocity_y": 431.57, "velocity_x": -302.828, "acceleration": 18.643, "downrange_distance": 90.35, "angle": 55.067, "q": 0.0}
{"time": 206.0, "velocity": 551.304, "altitude": 111.649, "velocity_y": 417.234, "velocity_x": -348.859, "acceleration": 18.04, "downrange_distance": 90.024, "angle": 50.396, "q": 0.0}
{"time": 207.0, "velocity": 568.838, "altitude": 112.044, "velocity_y": 403.118, "velocity_x": -386.625, "acceleration": 16.568, "downrange_distance": 89.657, "angle": 46.288, "q": 0.0}
{"time": 208.0, "velocity": 576.607, "altitude": 112.422, "velocity_y": 389.846, "velocity_x": -416.17, "acceleration": 14.593, "downrange_distance": 89.255, "angle": 42.96, "q": 0.0}
{"time": 209.0, "velocity": 582.048, "altitude": 112.797, "velocity_y": 378.212, "velocity_x": -439.077, "acceleration": 12.534, "downrange_distance": 88.828, "angle": 40.637, "q": 0.0}
{"time": 210.0, "velocity": 587.701, "altitude": 113.169, "velocity_y": 368.583, "velocity_x": -455.187, "acceleration": 9.915, "downrange_distance": 88.381, "angle": 39.148, "q": 0.0}
{"time": 211.0, "velocity": 588.455, "altitude": 113.532, "velocity_y": 359.247, "velocity_x": -464.998, "acceleration": 6.503, "downrange_distance": 87.92, "angle": 38.0, "q": 0.0}
{"time": 212.0, "velocity": 584.49, "altitude": 113.885, "velocity_y": 349.136, "velocity_x": -469.778, "acceleration": 3.234, "downrange_distance": 87.453, "angle": 36.88, "q": 0.0}
{"time": 213.0, "velocity": 578.939, "altitude": 114.224, "velocity_y": 337.927, "velocity_x": -471.506, "acceleration": 1.148, "downrange_distance": 86.982, "angle": 35.734, "q": 0.0}
{"time": 214.0, "velocity": 573.72, "altitude": 114.549, "velocity_y": 326.37, "velocity_x": -472.01, "acceleration": 0.471, "downrange_distance": 86.511, "angle": 34.616, "q": 0.0}
{"time": 215.0, "velocity": 568.669, "altitude": 114.86, "velocity_y": 315.629, "velocity_x": -472.221, "acceleration": 0.224, "downrange_distance": 86.039, "angle": 33.624, "q": 0.0}
{"time": 216.0, "velocity": 563.459, "altitude": 115.16, "velocity_y": 306.488, "velocity_x": -471.943, "acceleration": 0.129, "downrange_distance": 85.566, "angle": 32.85, "q": 0.0}
{"time": 217.0, "velocity": 559.027, "altitude": 115.456, "velocity_y": 298.947, "velocity_x": -471.564, "acceleration": 0.103, "downrange_distance": 85.095, "angle": 32.297, "q": 0.0}
{"time": 218.0, "velocity": 554.031, "altitude": 115.75, "velocity_y": 292.203, "velocity_x": -471.41, "acceleration": 0.135, "downrange_distance": 84.623, "angle": 31.846, "q": 0.0}
{"time": 219.0, "velocity": 549.04, "altitude": 116.04, "velocity_y": 285.102, "velocity_x": -471.57, "acceleration": 0.206, "downrange_distance": 84.152, "angle": 31.328, "q": 0.0}
{"time": 220.0, "velocity": 544.386, "altitude": 116.322, "velocity_y": 276.667, "velocity_x": -471.863, "acceleration": 0.239, "downrange_distance": 83.68, "angle": 30.607, "q": 0.0}
{"time": 221.0, "velocity": 539.872, "altitude": 116.592, "velocity_y": 266.593, "velocity_x": -472.134, "acceleration": 0.226, "downrange_distance": 83.208, "angle": 29.632, "q": 0.0}
{"time": 222.0, "velocity": 535.505, "altitude": 116.846, "velocity_y": 255.314, "velocity_x": -472.318, "acceleration": 0.173, "downrange_distance": 82.736, "angle": 28.471, "q": 0.0}
{"time": 223.0, "velocity": 531.343, "altitude": 117.088, "velocity_y": 243.706, "velocity_x": -472.429, "acceleration": 0.114, "downrange_distance": 82.263, "angle": 27.263, "q": 0.0}
{"time": 224.0, "velocity": 527.286, "altitude": 117.318, "velocity_y": 232.588, "velocity_x": -472.488, "acceleration": 0.042, "downrange_distance": 81.791, "angle": 26.124, "q": 0.0}
{"time": 225.0, "velocity": 523.121, "altitude": 117.538, "velocity_y": 222.401, "velocity_x": -472.501, "acceleration": -0.01, "downrange_distance": 81.318, "angle": 25.106, "q": 0.0}
{"time": 226.0, "velocity": 519.144, "altitude": 117.751, "velocity_y": 213.099, "velocity_x": -472.504, "acceleration": -0.028, "downrange_distance": 80.846, "angle": 24.194, "q": 0.0}
{"time": 227.0, "velocity": 515.386, "altitude": 117.955, "velocity_y": 204.397, "velocity_x": -472.508, "acceleration": 0.007, "downrange_distance": 80.373, "angle": 23.34, "q": 0.0}
{"time": 228.0, "velocity": 511.836, "altitude": 118.151, "velocity_y": 195.955, "velocity_x": -472.54, "acceleration": 0.057, "downrange_distance": 79.901, "angle": 22.497, "q": 0.0}
{"time": 229.0, "velocity": 508.451, "altitude": 118.339, "velocity_y": 187.522, "velocity_x": -472.585, "acceleration": 0.088, "downrange_distance": 79.428, "angle": 21.636, "q": 0.0}
{"time": 230.0, "velocity": 505.26, "altitude": 118.518, "velocity_y": 178.968, "velocity_x": -472.642, "acceleration": 0.075, "downrange_distance": 78.956, "angle": 20.745, "q": 0.0}
{"time": 231.0, "velocity": 502.027, "altitude": 118.689, "velocity_y": 170.24, "velocity_x": -472.701, "acceleration": 0.059, "downrange_distance": 78.483, "angle": 19.818, "q": 0.0}
{"time": 232.0, "velocity": 498.884, "altitude": 118.85, "velocity_y": 161.325, "velocity_x": -472.76, "acceleration": 0.063, "downrange_distance": 78.01, "angle": 18.857, "q": 0.0}
{"time": 233.0, "velocity": 496.2, "altitude": 119.003, "velocity_y": 152.212, "velocity_x": -472.816, "acceleration": 0.114, "downrange_distance": 77.538, "angle": 17.86, "q": 0.0}
{"time": 234.0, "velocity": 493.611, "altitude": 119.146, "velocity_y": 142.896, "velocity_x": -472.886, "acceleration": 0.133, "downrange_distance": 77.065, "angle": 16.826, "q": 0.0}
{"time": 235.0, "velocity": 491.182, "altitude": 119.28, "velocity_y": 133.382, "velocity_x": -472.98, "acceleration": 0.132, "downrange_distance": 76.592, "angle": 15.755, "q": 0.0}
{"time": 236.0, "velocity": 488.823, "altitude": 119.404, "velocity_y": 123.69, "velocity_x": -473.102, "acceleration": 0.084, "downrange_distance": 76.119, "angle": 14.653, "q": 0.0}
{"time": 237.0, "velocity": 486.741, "altitude": 119.518, "velocity_y": 113.853, "velocity_x": -473.252, "acceleration": 0.064, "downrange_distance": 75.646, "angle": 13.524, "q": 0.0}
{"time": 238.0, "velocity": 484.634, "altitude": 119.622, "velocity_y": 103.919, "velocity_x": -473.43, "acceleration": 0.044, "downrange_distance": 75.172, "angle": 12.374, "q": 0.0}
{"time": 239.0, "velocity": 482.897, "altitude": 119.716, "velocity_y": 93.936, "velocity_x": -473.629, "acceleration": 0.053, "downrange_distance": 74.699, "angle": 11.209, "q": 0.0}
{"time": 240.0, "velocity": 481.304, "altitude": 119.8, "velocity_y": 83.946, "velocity_x": -473.834, "acceleration": 0.046, "downrange_distance": 74.225, "angle": 10.037, "q": 0.0}
{"time": 241.0, "velocity": 479.871, "altitude": 119.874, "velocity_y": 73.981, "velocity_x": -474.043, "acceleration": 0.034, "downrange_distance": 73.751, "angle": 8.861, "q": 0.0}
{"time": 242.0, "velocity": 478.62, "altitude": 119.938, "velocity_y": 64.057, "velocity_x": -474.247, "acceleration": 0.019, "downrange_distance": 73.277, "angle": 7.684, "q": 0.0}
{"time": 243.0, "velocity": 477.509, "altitude": 119.992, "velocity_y": 54.178, "velocity_x": -474.441, "acceleration": 0.0, "downrange_distance": 72.803, "angle": 6.508, "q": 0.0}
{"time": 244.0, "velocity": 476.699, "altitude": 120.036, "velocity_y": 44.345, "velocity_x": -474.622, "acceleration": 0.006, "downrange_distance": 72.328, "angle": 5.332, "q": 0.0}
{"time": 245.0, "velocity": 475.917, "altitude": 120.07, "velocity_y": 34.558, "velocity_x": -474.784, "acceleration": 0.01, "downrange_distance": 71.853, "angle": 4.159, "q": 0.0}
{"time": 246.0, "velocity": 475.511, "altitude": 120.095, "velocity_y": 24.817, "velocity_x": -474.932, "acceleration": 0.058, "downrange_distance": 71.378, "angle": 2.988, "q": 0.0}
{"time": 247.0, "velocity": 475.305, "altitude": 120.11, "velocity_y": 15.122, "velocity_x": -475.064, "acceleration": 0.083, "downrange_distance": 70.903, "angle": 1.821, "q": 0.0}
{"time": 248.0, "velocity": 475.385, "altitude": 120.116, "velocity_y": 5.474, "velocity_x": -475.189, "acceleration": 0.072, "downrange_distance": 70.428, "angle": 0.658, "q": 0.0}
{"time": 249.0, "velocity": 475.466, "altitude": 120.111, "velocity_y": -4.129, "velocity_x": -475.304, "acceleration": 0.013, "downrange_distance": 69.953, "angle": -0.499, "q": 0.0}
{"time": 250.0, "velocity": 475.546, "altitude": 120.098, "velocity_y": -13.685, "velocity_x": -475.405, "acceleration": -0.042, "downrange_distance": 69.478, "angle": -1.649, "q": 0.0}
{"time": 251.0, "velocity": 476.05, "altitude": 120.074, "velocity_y": -23.195, "velocity_x": -475.495, "acceleration": -0.042, "downrange_distance": 69.002, "angle": -2.792, "q": 0.0}
{"time": 252.0, "velocity": 476.636, "altitude": 120.042, "velocity_y": -32.659, "velocity_x": -475.573, "acceleration": -0.033, "downrange_distance": 68.527, "angle": -3.927, "q": 0.0}
{"time": 253.0, "velocity": 477.482, "altitude": 120.0, "velocity_y": -42.077, "velocity_x": -475.644, "acceleration": -0.014, "downrange_distance": 68.051, "angle": -5.053, "q": 0.0}
{"time": 254.0, "velocity": 478.486, "altitude": 119.948, "velocity_y": -51.449, "velocity_x": -475.706, "acceleration": -0.029, "downrange_distance": 67.575, "angle": -6.17, "q": 0.0}
{"time": 255.0, "velocity": 479.647, "altitude": 119.887, "velocity_y": -60.775, "velocity_x": -475.777, "acceleration": -0.033, "downrange_distance": 67.1, "angle": -7.276, "q": 0.0}
{"time": 256.0, "velocity": 480.941, "altitude": 119.817, "velocity_y": -70.055, "velocity_x": -475.862, "acceleration": -0.035, "downrange_distance": 66.624, "angle": -8.37, "q": 0.0}
{"time": 257.0, "velocity": 482.517, "altitude": 119.738, "velocity_y": -79.29, "velocity_x": -475.966, "acceleration": -0.021, "downrange_distance": 66.148, "angle": -9.452, "q": 0.0}
{"time": 258.0, "velocity": 484.255, "altitude": 119.649, "velocity_y": -88.489, "velocity_x": -476.082, "acceleration": -0.026, "downrange_distance": 65.672, "angle": -10.523, "q": 0.0}
{"time": 259.0, "velocity": 486.124, "altitude": 119.551, "velocity_y": -97.666, "velocity_x": -476.207, "acceleration": -0.032, "downrange_distance": 65.196, "angle": -11.582, "q": 0.0}
{"time": 260.0, "velocity": 488.07, "altitude": 119.445, "velocity_y": -106.846, "velocity_x": -476.337, "acceleration": -0.03, "downrange_distance": 64.72, "angle": -12.632, "q": 0.0}
{"time": 261.0, "velocity": 490.36, "altitude": 119.329, "velocity_y": -116.057, "velocity_x": -476.467, "acceleration": -0.003, "downrange_distance": 64.243, "angle": -13.677, "q": 0.0}
{"time": 262.0, "velocity": 492.885, "altitude": 119.204, "velocity_y": -125.328, "velocity_x": -476.593, "acceleration": 0.018, "downrange_distance": 63.767, "angle": -14.719, "q": 0.0}
{"time": 263.0, "velocity": 495.383, "altitude": 119.069, "velocity_y": -134.685, "velocity_x": -476.709, "acceleration": 0.021, "downrange_distance": 63.29, "angle": -15.759, "q": 0.0}
{"time": 264.0, "velocity": 498.158, "altitude": 118.925, "velocity_y": -144.138, "velocity_x": -476.812, "acceleration": 0.019, "downrange_distance": 62.813, "angle": -16.801, "q": 0.0}
{"time": 265.0, "velocity": 501.211, "altitude": 118.772, "velocity_y": -153.686, "velocity_x": -476.9, "acceleration": 0.01, "downrange_distance": 62.336, "angle": -17.845, "q": 0.0}
{"time": 266.0, "velocity": 504.169, "altitude": 118.608, "velocity_y": -163.308, "velocity_x": -476.973, "acceleration": -0.001, "downrange_distance": 61.859, "angle": -18.886, "q": 0.0}
{"time": 267.0, "velocity": 507.363, "altitude": 118.435, "velocity_y": -172.966, "velocity_x": -477.024, "acceleration": -0.008, "downrange_distance": 61.382, "angle": -19.918, "q": 0.0}
{"time": 268.0, "velocity": 510.738, "altitude": 118.253, "velocity_y": -182.614, "velocity_x": -477.055, "acceleration": -0.002, "downrange_distance": 60.905, "angle": -20.937, "q": 0.0}
{"time": 269.0, "velocity": 514.346, "altitude": 118.06, "velocity_y": -192.209, "velocity_x": -477.072, "acceleration": 0.008, "downrange_distance": 60.428, "angle": -21.935, "q": 0.0}
{"time": 270.0, "velocity": 518.042, "altitude": 117.858, "velocity_y": -201.725, "velocity_x": -477.084, "acceleration": 0.002, "downrange_distance": 59.951, "angle": -22.908, "q": 0.0}
{"time": 271.0, "velocity": 521.841, "altitude": 117.647, "velocity_y": -211.17, "velocity_x": -477.094, "acceleration": -0.014, "downrange_distance": 59.474, "angle": -23.855, "q": 0.0}
{"time": 272.0, "velocity": 525.812, "altitude": 117.426, "velocity_y": -220.588, "velocity_x": -477.104, "acceleration": -0.023, "downrange_distance": 58.997, "angle": -24.787, "q": 0.0}
{"time": 273.0, "velocity": 530.078, "altitude": 117.197, "velocity_y": -230.045, "velocity_x": -477.117, "acceleration": -0.033, "downrange_distance": 58.52, "angle": -25.71, "q": 0.0}
{"time": 274.0, "velocity": 534.137, "altitude": 116.957, "velocity_y": -239.605, "velocity_x": -477.13, "acceleration": -0.024, "downrange_distance": 58.043, "angle": -26.631, "q": 0.0}
{"time": 275.0, "velocity": 538.441, "altitude": 116.708, "velocity_y": -249.303, "velocity_x": -477.126, "acceleration": -0.016, "downrange_distance": 57.566, "angle": -27.555, "q": 0.0}
{"time": 276.0, "velocity": 543.018, "altitude": 116.45, "velocity_y": -259.137, "velocity_x": -477.124, "acceleration": 0.002, "downrange_distance": 57.089, "angle": -28.484, "q": 0.0}
{"time": 277.0, "velocity": 547.736, "altitude": 116.18, "velocity_y": -269.058, "velocity_x": -477.148, "acceleration": -0.004, "downrange_distance": 56.611, "angle": -29.406, "q": 0.0}
{"time": 278.0, "velocity": 552.454, "altitude": 115.901, "velocity_y": -278.968, "velocity_x": -477.225, "acceleration": -0.026, "downrange_distance": 56.134, "angle": -30.315, "q": 0.0}
{"time": 279.0, "velocity": 557.591, "altitude": 115.612, "velocity_y": -288.727, "velocity_x": -477.353, "acceleration": -0.043, "downrange_distance": 55.657, "angle": -31.194, "q": 0.0}
{"time": 280.0, "velocity": 562.446, "altitude": 115.313, "velocity_y": -298.187, "velocity_x": -477.525, "acceleration": -0.042, "downrange_distance": 55.179, "angle": -32.022, "q": 0.0}
{"time": 281.0, "velocity": 567.442, "altitude": 115.005, "velocity_y": -307.248, "velocity_x": -477.74, "acceleration": -0.032, "downrange_distance": 54.702, "angle": -32.78, "q": 0.0}
{"time": 282.0, "velocity": 572.655, "altitude": 114.688, "velocity_y": -315.921, "velocity_x": -477.981, "acceleration": -0.022, "downrange_distance": 54.224, "angle": -33.476, "q": 0.0}
{"time": 283.0, "velocity": 578.13, "altitude": 114.364, "velocity_y": -324.361, "velocity_x": -478.23, "acceleration": -0.01, "downrange_distance": 53.746, "angle": -34.121, "q": 0.0}
{"time": 284.0, "velocity": 583.404, "altitude": 114.032, "velocity_y": -332.865, "velocity_x": -478.47, "acceleration": 0.01, "downrange_distance": 53.268, "angle": -34.754, "q": 0.0}
{"time": 285.0, "velocity": 589.019, "altitude": 113.691, "velocity_y": -341.823, "velocity_x": -478.696, "acceleration": 0.018, "downrange_distance": 52.789, "angle": -35.424, "q": 0.0}
{"time": 286.0, "velocity": 594.54, "altitude": 113.342, "velocity_y": -351.506, "velocity_x": -478.901, "acceleration": 0.017, "downrange_distance": 52.31, "angle": -36.19, "q": 0.0}
{"time": 287.0, "velocity": 600.472, "altitude": 112.982, "velocity_y": -361.762, "velocity_x": -479.074, "acceleration": 0.005, "downrange_distance": 51.831, "angle": -37.041, "q": 0.0}
{"time": 288.0, "velocity": 606.217, "altitude": 112.609, "velocity_y": -371.918, "velocity_x": -479.183, "acceleration": -0.012, "downrange_distance": 51.352, "angle": -37.88, "q": 0.0}
{"time": 289.0, "velocity": 612.042, "altitude": 112.223, "velocity_y": -381.274, "velocity_x": -479.224, "acceleration": -0.035, "downrange_distance": 50.873, "angle": -38.565, "q": 0.0}
{"time": 290.0, "velocity": 617.96, "altitude": 111.827, "velocity_y": -389.786, "velocity_x": -479.229, "acceleration": -0.067, "downrange_distance": 50.394, "angle": -39.09, "q": 0.0}
{"time": 291.0, "velocity": 624.344, "altitude": 111.43, "velocity_y": -398.101, "velocity_x": -479.243, "acceleration": -0.097, "downrange_distance": 49.914, "angle": -39.588, "q": 0.0}
{"time": 292.0, "velocity": 630.351, "altitude": 111.033, "velocity_y": -407.418, "velocity_x": -479.281, "acceleration": -0.129, "downrange_distance": 49.435, "angle": -40.218, "q": 0.0}
{"time": 293.0, "velocity": 636.453, "altitude": 110.624, "velocity_y": -417.697, "velocity_x": -479.341, "acceleration": -0.17, "downrange_distance": 48.956, "angle": -40.986, "q": 0.0}
{"time": 294.0, "velocity": 642.388, "altitude": 110.191, "velocity_y": -428.492, "velocity_x": -479.404, "acceleration": -0.194, "downrange_distance": 48.476, "angle": -41.818, "q": 0.0}
{"time": 295.0, "velocity": 649.383, "altitude": 109.74, "velocity_y": -438.938, "velocity_x": -479.461, "acceleration": -0.172, "downrange_distance": 47.997, "angle": -42.592, "q": 0.0}
{"time": 296.0, "velocity": 655.854, "altitude": 109.286, "velocity_y": -448.57, "velocity_x": -479.49, "acceleration": -0.071, "downrange_distance": 47.517, "angle": -43.197, "q": 0.0}
{"time": 297.0, "velocity": 661.977, "altitude": 108.833, "velocity_y": -457.212, "velocity_x": -479.489, "acceleration": 0.04, "downrange_distance": 47.038, "angle": -43.642, "q": 0.0}
{"time": 298.0, "velocity": 669.037, "altitude": 108.375, "velocity_y": -466.208, "velocity_x": -479.47, "acceleration": 0.12, "downrange_distance": 46.559, "angle": -44.118, "q": 0.0}
{"time": 299.0, "velocity": 675.841, "altitude": 107.905, "velocity_y": -475.865, "velocity_x": -479.458, "acceleration": 0.131, "downrange_distance": 46.079, "angle": -44.738, "q": 0.0}
{"time": 300.0, "velocity": 682.504, "altitude": 107.416, "velocity_y": -485.952, "velocity_x": -479.438, "acceleration": 0.116, "downrange_distance": 45.6, "angle": -45.41, "q": 0.0}
{"time": 301.0, "velocity": 689.444, "altitude": 106.909, "velocity_y": -495.74, "velocity_x": -479.408, "acceleration": 0.076, "downrange_distance": 45.12, "angle": -46.004, "q": 0.0}
{"time": 302.0, "velocity": 696.38, "altitude": 106.399, "velocity_y": -504.909, "velocity_x": -479.365, "acceleration": 0.034, "downrange_distance": 44.641, "angle": -46.491, "q": 0.0}
{"time": 303.0, "velocity": 703.316, "altitude": 105.894, "velocity_y": -513.47, "velocity_x": -479.343, "acceleration": -0.016, "downrange_distance": 44.161, "angle": -46.884, "q": 0.0}
{"time": 304.0, "velocity": 709.988, "altitude": 105.38, "velocity_y": -522.278, "velocity_x": -479.371, "acceleration": -0.066, "downrange_distance": 43.682, "angle": -47.278, "q": 0.0}
{"time": 305.0, "velocity": 717.744, "altitude": 104.847, "velocity_y": -532.05, "velocity_x": -479.477, "acceleration": -0.099, "downrange_distance": 43.203, "angle": -47.796, "q": 0.0}
{"time": 306.0, "velocity": 724.423, "altitude": 104.302, "velocity_y": -543.072, "velocity_x": -479.682, "acceleration": -0.117, "downrange_distance": 42.723, "angle": -48.519, "q": 0.0}
{"time": 307.0, "velocity": 731.615, "altitude": 103.747, "velocity_y": -554.351, "velocity_x": -479.978, "acceleration": -0.107, "downrange_distance": 42.243, "angle": -49.329, "q": 0.0}
{"time": 308.0, "velocity": 738.552, "altitude": 103.182, "velocity_y": -564.507, "velocity_x": -480.323, "acceleration": -0.105, "downrange_distance": 41.763, "angle": -49.95, "q": 0.0}
{"time": 309.0, "velocity": 746.044, "altitude": 102.603, "velocity_y": -573.369, "velocity_x": -480.697, "acceleration": -0.085, "downrange_distance": 41.283, "angle": -50.204, "q": 0.0}
{"time": 310.0, "velocity": 753.535, "altitude": 102.012, "velocity_y": -581.789, "velocity_x": -481.072, "acceleration": -0.057, "downrange_distance": 40.802, "angle": -50.529, "q": 0.0}
{"time": 311.0, "velocity": 760.749, "altitude": 101.43, "velocity_y": -589.977, "velocity_x": -481.458, "acceleration": -0.022, "downrange_distance": 40.32, "angle": -50.933, "q": 0.0}
{"time": 312.0, "velocity": 767.962, "altitude": 100.855, "velocity_y": -597.844, "velocity_x": -481.846, "acceleration": -0.03, "downrange_distance": 39.839, "angle": -51.213, "q": 0.0}
{"time": 313.0, "velocity": 775.454, "altitude": 100.222, "velocity_y": -606.131, "velocity_x": -482.231, "acceleration": -0.073, "downrange_distance": 39.357, "angle": -51.243, "q": 0.0}
{"time": 314.0, "velocity": 783.416, "altitude": 99.594, "velocity_y": -615.601, "velocity_x": -482.588, "acceleration": -0.116, "downrange_distance": 38.874, "angle": -51.814, "q": 0.0}
{"time": 315.0, "velocity": 790.715, "altitude": 98.998, "velocity_y": -625.28, "velocity_x": -482.925, "acceleration": -0.138, "downrange_distance": 38.392, "angle": -52.415, "q": 0.0}
{"time": 316.0, "velocity": 797.929, "altitude": 98.38, "velocity_y": -634.985, "velocity_x": -483.218, "acceleration": -0.141, "downrange_distance": 37.909, "angle": -53.109, "q": 0.0}
{"time": 317.0, "velocity": 806.181, "altitude": 97.687, "velocity_y": -644.644, "velocity_x": -483.473, "acceleration": -0.146, "downrange_distance": 37.425, "angle": -53.112, "q": 0.0}
{"time": 318.0, "velocity": 813.818, "altitude": 97.041, "velocity_y": -654.218, "velocity_x": -483.66, "acceleration": -0.124, "downrange_distance": 36.942, "angle": -53.635, "q": 0.0}
{"time": 319.0, "velocity": 821.237, "altitude": 96.367, "velocity_y": -662.982, "velocity_x": -483.781, "acceleration": -0.093, "downrange_distance": 36.458, "angle": -53.821, "q": 0.0}
{"time": 320.0, "velocity": 828.729, "altitude": 95.739, "velocity_y": -673.748, "velocity_x": -483.824, "acceleration": -0.018, "downrange_distance": 35.974, "angle": -54.505, "q": 0.0}
{"time": 321.0, "velocity": 836.776, "altitude": 95.041, "velocity_y": -684.026, "velocity_x": -483.765, "acceleration": 0.037, "downrange_distance": 35.49, "angle": -54.591, "q": 0.0}
{"time": 322.0, "velocity": 844.823, "altitude": 94.342, "velocity_y": -693.618, "velocity_x": -483.588, "acceleration": 0.11, "downrange_distance": 35.007, "angle": -55.389, "q": 0.0}
{"time": 323.0, "velocity": 852.594, "altitude": 93.604, "velocity_y": -702.416, "velocity_x": -483.333, "acceleration": 0.133, "downrange_distance": 34.523, "angle": -55.5, "q": 0.0}
{"time": 324.0, "velocity": 860.639, "altitude": 92.921, "velocity_y": -710.741, "velocity_x": -483.048, "acceleration": 0.162, "downrange_distance": 34.04, "angle": -55.738, "q": 0.0}
{"time": 325.0, "velocity": 868.687, "altitude": 92.196, "velocity_y": -716.98, "velocity_x": -482.793, "acceleration": 0.152, "downrange_distance": 33.557, "angle": -55.36, "q": 0.0}
{"time": 326.0, "velocity": 876.455, "altitude": 91.492, "velocity_y": -726.51, "velocity_x": -482.585, "acceleration": 0.135, "downrange_distance": 33.074, "angle": -55.784, "q": 0.0}
{"time": 327.0, "velocity": 883.947, "altitude": 90.768, "velocity_y": -738.077, "velocity_x": -482.448, "acceleration": 0.083, "downrange_distance": 32.592, "angle": -56.235, "q": 0.0}
{"time": 328.0, "velocity": 892.11, "altitude": 90.01, "velocity_y": -750.932, "velocity_x": -482.39, "acceleration": 0.036, "downrange_distance": 32.109, "angle": -57.424, "q": 0.0}
{"time": 329.0, "velocity": 900.596, "altitude": 89.22, "velocity_y": -764.478, "velocity_x": -482.413, "acceleration": -0.005, "downrange_distance": 31.627, "angle": -58.146, "q": 0.0}
{"time": 330.0, "velocity": 908.645, "altitude": 88.465, "velocity_y": -776.952, "velocity_x": -482.49, "acceleration": -0.007, "downrange_distance": 31.145, "angle": -58.934, "q": 0.0}
{"time": 331.0, "velocity": 916.969, "altitude": 87.647, "velocity_y": -785.885, "velocity_x": -482.593, "acceleration": 0.015, "downrange_distance": 30.662, "angle": -58.996, "q": 0.0}
{"time": 332.0, "velocity": 925.294, "altitude": 86.873, "velocity_y": -793.616, "velocity_x": -482.693, "acceleration": 0.059, "downrange_distance": 30.179, "angle": -59.111, "q": 0.0}
{"time": 333.0, "velocity": 933.2, "altitude": 86.074, "velocity_y": -801.079, "velocity_x": -482.787, "acceleration": 0.085, "downrange_distance": 29.697, "angle": -59.11, "q": 0.0}
{"time": 334.0, "velocity": 941.388, "altitude": 85.263, "velocity_y": -809.022, "velocity_x": -482.837, "acceleration": 0.09, "downrange_distance": 29.214, "angle": -59.149, "q": 0.0}
{"time": 335.0, "velocity": 949.714, "altitude": 84.451, "velocity_y": -817.788, "velocity_x": -482.853, "acceleration": 0.067, "downrange_distance": 28.731, "angle": -59.414, "q": 0.0}
{"time": 336.0, "velocity": 958.039, "altitude": 83.605, "velocity_y": -827.02, "velocity_x": -482.874, "acceleration": 0.028, "downrange_distance": 28.248, "angle": -59.866, "q": 0.0}
{"time": 337.0, "velocity": 966.364, "altitude": 82.805, "velocity_y": -835.516, "velocity_x": -483.005, "acceleration": 0.006, "downrange_distance": 27.765, "angle": -60.462, "q": 0.0}
{"time": 338.0, "velocity": 974.935, "altitude": 81.921, "velocity_y": -843.878, "velocity_x": -483.291, "acceleration": -0.001, "downrange_distance": 27.282, "angle": -60.125, "q": 0.0}
{"time": 339.0, "velocity": 983.292, "altitude": 81.055, "velocity_y": -851.998, "velocity_x": -483.719, "acceleration": 0.023, "downrange_distance": 26.799, "angle": -60.174, "q": 0.0}
{"time": 340.0, "velocity": 991.504, "altitude": 80.2, "velocity_y": -861.132, "velocity_x": -484.247, "acceleration": 0.035, "downrange_distance": 26.315, "angle": -60.197, "q": 0.0}
{"time": 341.0, "velocity": 999.278, "altitude": 79.388, "velocity_y": -872.555, "velocity_x": -484.812, "acceleration": 0.048, "downrange_distance": 25.83, "angle": -60.749, "q": 0.0}
{"time": 342.0, "velocity": 1007.924, "altitude": 78.486, "velocity_y": -884.262, "velocity_x": -485.329, "acceleration": 0.029, "downrange_distance": 25.345, "angle": -60.825, "q": 0.0}
{"time": 343.0, "velocity": 1016.629, "altitude": 77.558, "velocity_y": -895.208, "velocity_x": -485.726, "acceleration": -0.003, "downrange_distance": 24.859, "angle": -61.454, "q": 0.0}
{"time": 344.0, "velocity": 1025.099, "altitude": 76.66, "velocity_y": -905.709, "velocity_x": -485.964, "acceleration": -0.037, "downrange_distance": 24.374, "angle": -62.363, "q": 0.0}
{"time": 345.0, "velocity": 1033.52, "altitude": 75.76, "velocity_y": -915.475, "velocity_x": -486.066, "acceleration": -0.05, "downrange_distance": 23.888, "angle": -62.434, "q": 0.0}
{"time": 346.0, "velocity": 1041.846, "altitude": 74.832, "velocity_y": -922.594, "velocity_x": -486.059, "acceleration": -0.028, "downrange_distance": 23.401, "angle": -62.278, "q": 0.0}
{"time": 347.0, "velocity": 1050.729, "altitude": 73.862, "velocity_y": -930.479, "velocity_x": -485.979, "acceleration": -0.014, "downrange_distance": 22.915, "angle": -62.203, "q": 0.0}
{"time": 348.0, "velocity": 1058.774, "altitude": 72.996, "velocity_y": -940.165, "velocity_x": -485.86, "acceleration": 0.011, "downrange_distance": 22.43, "angle": -62.929, "q": 0.0}
{"time": 349.0, "velocity": 1067.377, "altitude": 72.011, "velocity_y": -950.135, "velocity_x": -485.759, "acceleration": 0.016, "downrange_distance": 21.944, "angle": -62.917, "q": 0.0}
{"time": 350.0, "velocity": 1075.98, "altitude": 71.033, "velocity_y": -958.846, "velocity_x": -485.723, "acceleration": 0.025, "downrange_distance": 21.458, "angle": -63.076, "q": 0.0}
{"time": 351.0, "velocity": 1084.863, "altitude": 70.067, "velocity_y": -967.562, "velocity_x": -485.791, "acceleration": 0.001, "downrange_distance": 20.972, "angle": -63.06, "q": 0.0}
{"time": 352.0, "velocity": 1093.121, "altitude": 69.099, "velocity_y": -979.075, "velocity_x": -485.946, "acceleration": -0.015, "downrange_distance": 20.486, "angle": -63.752, "q": 0.0}
{"time": 353.0, "velocity": 1101.789, "altitude": 68.136, "velocity_y": -989.539, "velocity_x": -486.124, "acceleration": -0.039, "downrange_distance": 20.0, "angle": -63.629, "q": 0.0}
{"time": 354.0, "velocity": 1110.393, "altitude": 67.133, "velocity_y": -998.777, "velocity_x": -486.283, "acceleration": -0.047, "downrange_distance": 19.514, "angle": -63.898, "q": 0.0}
{"time": 355.0, "velocity": 1119.247, "altitude": 66.068, "velocity_y": -1009.192, "velocity_x": -486.341, "acceleration": -0.073, "downrange_distance": 19.028, "angle": -64.27, "q": 0.0}
{"time": 356.0, "velocity": 1127.598, "altitude": 65.104, "velocity_y": -1019.682, "velocity_x": -486.242, "acceleration": -0.1, "downrange_distance": 18.542, "angle": -64.882, "q": 0.0}
{"time": 357.0, "velocity": 1136.013, "altitude": 64.072, "velocity_y": -1026.983, "velocity_x": -485.982, "acceleration": -0.139, "downrange_distance": 18.055, "angle": -64.726, "q": 0.0}
{"time": 358.0, "velocity": 1145.081, "altitude": 63.007, "velocity_y": -1034.244, "velocity_x": -485.621, "acceleration": -0.165, "downrange_distance": 17.57, "angle": -64.524, "q": 0.0}
{"time": 359.0, "velocity": 1153.785, "altitude": 61.975, "velocity_y": -1043.482, "velocity_x": -485.256, "acceleration": -0.186, "downrange_distance": 17.084, "angle": -64.629, "q": 0.0}
{"time": 360.0, "velocity": 1162.287, "altitude": 60.942, "velocity_y": -1053.304, "velocity_x": -484.912, "acceleration": -0.182, "downrange_distance": 16.599, "angle": -65.204, "q": 0.0}
{"time": 361.0, "velocity": 1170.669, "altitude": 59.885, "velocity_y": -1064.053, "velocity_x": -484.635, "acceleration": -0.186, "downrange_distance": 16.114, "angle": -65.155, "q": 0.0}
{"time": 362.0, "velocity": 1179.771, "altitude": 58.784, "velocity_y": -1074.638, "velocity_x": -484.458, "acceleration": -0.197, "downrange_distance": 15.63, "angle": -65.591, "q": 0.0}
{"time": 363.0, "velocity": 1188.374, "altitude": 57.689, "velocity_y": -1085.404, "velocity_x": -484.374, "acceleration": -0.23, "downrange_distance": 15.145, "angle": -66.06, "q": 0.0}
{"time": 364.0, "velocity": 1196.699, "altitude": 56.644, "velocity_y": -1094.868, "velocity_x": -484.354, "acceleration": -0.246, "downrange_distance": 14.661, "angle": -66.457, "q": 0.0}
{"time": 365.0, "velocity": 1205.858, "altitude": 55.481, "velocity_y": -1104.22, "velocity_x": -484.4, "acceleration": -0.265, "downrange_distance": 14.177, "angle": -66.148, "q": 0.0}
{"time": 366.0, "velocity": 1214.46, "altitude": 54.388, "velocity_y": -1114.66, "velocity_x": -484.576, "acceleration": -0.283, "downrange_distance": 13.692, "angle": -66.764, "q": 0.0}
{"time": 367.0, "velocity": 1222.785, "altitude": 53.282, "velocity_y": -1125.641, "velocity_x": -484.743, "acceleration": -0.344, "downrange_distance": 13.207, "angle": -67.147, "q": 0.0}
{"time": 368.0, "velocity": 1231.388, "altitude": 52.15, "velocity_y": -1135.623, "velocity_x": -484.749, "acceleration": -0.425, "downrange_distance": 12.723, "angle": -67.351, "q": 0.0}
{"time": 369.0, "velocity": 1240.269, "altitude": 50.951, "velocity_y": -1144.805, "velocity_x": -484.571, "acceleration": -0.556, "downrange_distance": 12.238, "angle": -67.487, "q": 0.0}
{"time": 370.0, "velocity": 1248.594, "altitude": 49.813, "velocity_y": -1150.986, "velocity_x": -484.454, "acceleration": -0.92, "downrange_distance": 11.754, "angle": -68.815, "q": 0.0}
{"time": 371.0, "velocity": 1256.919, "altitude": 48.705, "velocity_y": -1152.91, "velocity_x": -488.53, "acceleration": -2.707, "downrange_distance": 11.267, "angle": -69.195, "q": 0.0}
{"time": 372.0, "velocity": 1260.157, "altitude": 47.455, "velocity_y": -1151.273, "velocity_x": -491.128, "acceleration": -7.068, "downrange_distance": 10.777, "angle": -68.743, "q": 0.0}
{"time": 373.0, "velocity": 1255.021, "altitude": 46.22, "velocity_y": -1142.984, "velocity_x": -488.176, "acceleration": -11.815, "downrange_distance": 10.288, "angle": -68.11, "q": 0.0}
{"time": 374.0, "velocity": 1248.661, "altitude": 45.159, "velocity_y": -1131.762, "velocity_x": -479.444, "acceleration": -16.231, "downrange_distance": 9.804, "angle": -66.571, "q": 0.0}
{"time": 375.0, "velocity": 1238.51, "altitude": 44.018, "velocity_y": -1118.872, "velocity_x": -465.443, "acceleration": -23.999, "downrange_distance": 9.331, "angle": -65.748, "q": 0.000655554423178851}
{"time": 376.0, "velocity": 1209.646, "altitude": 42.888, "velocity_y": -1102.04, "velocity_x": -447.555, "acceleration": -31.539, "downrange_distance": 8.875, "angle": -65.581, "q": 0.41854512421452156}
{"time": 377.0, "velocity": 1181.185, "altitude": 42.006, "velocity_y": -1083.476, "velocity_x": -427.132, "acceleration": -40.998, "downrange_distance": 8.437, "angle": -70.268, "q": 3.040125275740887}
{"time": 378.0, "velocity": 1136.181, "altitude": 40.738, "velocity_y": -1064.388, "velocity_x": -405.541, "acceleration": -44.652, "downrange_distance": 8.021, "angle": -72.308, "q": 17.938669423429282}
{"time": 379.0, "velocity": 1097.222, "altitude": 39.695, "velocity_y": -1039.634, "velocity_x": -384.145, "acceleration": -47.888, "downrange_distance": 7.626, "angle": -75.002, "q": 49.48693234402644}
{"time": 380.0, "velocity": 1058.555, "altitude": 38.662, "velocity_y": -1007.206, "velocity_x": -364.07, "acceleration": -47.954, "downrange_distance": 7.252, "angle": -75.64, "q": 108.39527594784226}
{"time": 381.0, "velocity": 1017.382, "altitude": 37.686, "velocity_y": -976.106, "velocity_x": -346.562, "acceleration": -47.466, "downrange_distance": 6.897, "angle": -75.378, "q": 196.89314276761831}
{"time": 382.0, "velocity": 979.797, "altitude": 36.764, "velocity_y": -947.024, "velocity_x": -332.953, "acceleration": -41.054, "downrange_distance": 6.557, "angle": -71.108, "q": 317.4596864962686}
{"time": 383.0, "velocity": 960.101, "altitude": 35.884, "velocity_y": -924.376, "velocity_x": -324.804, "acceleration": -30.247, "downrange_distance": 6.228, "angle": -69.755, "q": 486.9901127502409}
{"time": 384.0, "velocity": 953.916, "altitude": 35.012, "velocity_y": -910.192, "velocity_x": -323.184, "acceleration": -16.447, "downrange_distance": 5.904, "angle": -68.924, "q": 730.2803728810633}
{"time": 385.0, "velocity": 958.121, "altitude": 34.099, "velocity_y": -907.018, "velocity_x": -328.511, "acceleration": -8.287, "downrange_distance": 5.578, "angle": -68.66, "q": 1096.5631588758447}
{"time": 386.0, "velocity": 964.014, "altitude": 33.235, "velocity_y": -908.322, "velocity_x": -332.747, "acceleration": -4.563, "downrange_distance": 5.248, "angle": -69.189, "q": 1567.5908586269834}
{"time": 387.0, "velocity": 970.335, "altitude": 32.301, "velocity_y": -911.781, "velocity_x": -335.061, "acceleration": -4.216, "downrange_distance": 4.914, "angle": -69.409, "q": 2240.212376691781}
{"time": 388.0, "velocity": 976.304, "altitude": 31.37, "velocity_y": -915.349, "velocity_x": -336.779, "acceleration": -4.24, "downrange_distance": 4.578, "angle": -69.803, "q": 3114.4990710370366}
{"time": 389.0, "velocity": 981.3, "altitude": 30.468, "velocity_y": -918.647, "velocity_x": -338.096, "acceleration": -4.535, "downrange_distance": 4.241, "angle": -70.004, "q": 4189.39277385709}
{"time": 390.0, "velocity": 985.462, "altitude": 29.539, "velocity_y": -921.439, "velocity_x": -339.372, "acceleration": -5.094, "downrange_distance": 3.902, "angle": -69.794, "q": 5568.419524257712}
{"time": 391.0, "velocity": 988.73, "altitude": 28.607, "velocity_y": -923.664, "velocity_x": -340.544, "acceleration": -5.872, "downrange_distance": 3.562, "angle": -69.263, "q": 7269.050983352528}
{"time": 392.0, "velocity": 991.181, "altitude": 27.669, "velocity_y": -925.643, "velocity_x": -341.38, "acceleration": -6.841, "downrange_distance": 3.221, "angle": -69.257, "q": 9347.53806347123}
{"time": 393.0, "velocity": 992.504, "altitude": 26.77, "velocity_y": -927.514, "velocity_x": -341.856, "acceleration": -7.947, "downrange_distance": 2.879, "angle": -69.46, "q": 11722.297358237445}
{"time": 394.0, "velocity": 992.403, "altitude": 25.842, "velocity_y": -929.252, "velocity_x": -341.872, "acceleration": -9.196, "downrange_distance": 2.537, "angle": -69.743, "q": 14590.328712079565}
{"time": 395.0, "velocity": 991.212, "altitude": 24.877, "velocity_y": -929.694, "velocity_x": -341.592, "acceleration": -10.612, "downrange_distance": 2.196, "angle": -69.909, "q": 18077.725182473812}
{"time": 396.0, "velocity": 988.451, "altitude": 23.973, "velocity_y": -927.909, "velocity_x": -340.724, "acceleration": -12.257, "downrange_distance": 1.854, "angle": -70.828, "q": 21808.26245436762}
{"time": 397.0, "velocity": 983.594, "altitude": 23.021, "velocity_y": -923.832, "velocity_x": -338.683, "acceleration": -14.211, "downrange_distance": 1.515, "angle": -70.804, "q": 26229.621298892427}
{"time": 398.0, "velocity": 976.641, "altitude": 22.114, "velocity_y": -917.291, "velocity_x": -334.735, "acceleration": -16.451, "downrange_distance": 1.178, "angle": -71.039, "q": 30881.927934257354}
{"time": 399.0, "velocity": 966.649, "altitude": 21.174, "velocity_y": -908.375, "velocity_x": -327.865, "acceleration": -18.841, "downrange_distance": 0.847, "angle": -70.325, "q": 36086.55444681467}
{"time": 400.0, "velocity": 954.983, "altitude": 20.303, "velocity_y": -897.32, "velocity_x": -318.03, "acceleration": -21.415, "downrange_distance": 0.524, "angle": -71.111, "q": 41213.62185047738}
{"time": 401.0, "velocity": 940.0, "altitude": 19.4, "velocity_y": -885.501, "velocity_x": -306.061, "acceleration": -24.13, "downrange_distance": 0.212, "angle": -70.997, "q": 46721.90081347569}
{"time": 402.0, "velocity": 922.508, "altitude": 18.551, "velocity_y": -872.721, "velocity_x": -292.807, "acceleration": -27.453, "downrange_distance": -0.088, "angle": -72.232, "q": 51893.50210443561}
{"time": 403.0, "velocity": 900.328, "altitude": 17.652, "velocity_y": -856.352, "velocity_x": -279.343, "acceleration": -30.7, "downrange_distance": -0.374, "angle": -72.844, "q": 57191.55983468758}
{"time": 404.0, "velocity": 876.187, "altitude": 16.828, "velocity_y": -835.961, "velocity_x": -266.22, "acceleration": -34.241, "downrange_distance": -0.647, "angle": -73.854, "q": 61650.18670470001}
{"time": 405.0, "velocity": 847.668, "altitude": 16.003, "velocity_y": -814.181, "velocity_x": -254.26, "acceleration": -36.957, "downrange_distance": -0.907, "angle": -74.485, "q": 65438.150933101955}
{"time": 406.0, "velocity": 816.792, "altitude": 15.203, "velocity_y": -782.728, "velocity_x": -243.318, "acceleration": -39.256, "downrange_distance": -1.156, "angle": -73.902, "q": 68404.16550888977}
{"time": 407.0, "velocity": 786.313, "altitude": 14.478, "velocity_y": -750.812, "velocity_x": -233.972, "acceleration": -40.513, "downrange_distance": -1.394, "angle": -73.514, "q": 70382.98113663157}
{"time": 408.0, "velocity": 749.705, "altitude": 13.709, "velocity_y": -713.95, "velocity_x": -226.193, "acceleration": -41.4, "downrange_distance": -1.624, "angle": -72.173, "q": 71297.83622788462}
{"time": 409.0, "velocity": 717.003, "altitude": 13.099, "velocity_y": -680.682, "velocity_x": -220.116, "acceleration": -41.798, "downrange_distance": -1.847, "angle": -72.087, "q": 70926.8761166495}
{"time": 410.0, "velocity": 681.313, "altitude": 12.412, "velocity_y": -642.72, "velocity_x": -215.354, "acceleration": -41.923, "downrange_distance": -2.065, "angle": -70.448, "q": 70251.16756203212}
{"time": 411.0, "velocity": 648.03, "altitude": 11.818, "velocity_y": -612.717, "velocity_x": -211.486, "acceleration": -41.662, "downrange_distance": -2.279, "angle": -70.859, "q": 68741.95996456532}
{"time": 412.0, "velocity": 615.833, "altitude": 11.239, "velocity_y": -579.656, "velocity_x": -208.092, "acceleration": -41.247, "downrange_distance": -2.488, "angle": -70.181, "q": 66930.37105185082}
{"time": 413.0, "velocity": 584.671, "altitude": 10.695, "velocity_y": -551.071, "velocity_x": -204.238, "acceleration": -40.42, "downrange_distance": -2.695, "angle": -70.365, "q": 64657.020766357906}
{"time": 414.0, "velocity": 553.661, "altitude": 10.156, "velocity_y": -518.775, "velocity_x": -199.849, "acceleration": -39.142, "downrange_distance": -2.897, "angle": -68.95, "q": 62039.552936633845}
{"time": 415.0, "velocity": 525.353, "altitude": 9.673, "velocity_y": -489.092, "velocity_x": -195.082, "acceleration": -37.299, "downrange_distance": -3.094, "angle": -67.923, "q": 59295.39395226095}
{"time": 416.0, "velocity": 499.671, "altitude": 9.228, "velocity_y": -459.862, "velocity_x": -190.014, "acceleration": -35.167, "downrange_distance": -3.287, "angle": -66.306, "q": 56634.78085090364}
{"time": 417.0, "velocity": 475.126, "altitude": 8.787, "velocity_y": -434.411, "velocity_x": -184.992, "acceleration": -32.797, "downrange_distance": -3.474, "angle": -65.126, "q": 54004.28289258969}
{"time": 418.0, "velocity": 454.318, "altitude": 8.401, "velocity_y": -413.322, "velocity_x": -180.001, "acceleration": -30.702, "downrange_distance": -3.657, "angle": -65.026, "q": 51696.89765657021}
{"time": 419.0, "velocity": 434.469, "altitude": 8.011, "velocity_y": -396.304, "velocity_x": -175.234, "acceleration": -28.85, "downrange_distance": -3.834, "angle": -65.654, "q": 49504.67495479238}
{"time": 420.0, "velocity": 415.32, "altitude": 7.61, "velocity_y": -381.056, "velocity_x": -170.15, "acceleration": -27.22, "downrange_distance": -4.007, "angle": -65.948, "q": 47400.7341508194}
{"time": 421.0, "velocity": 399.503, "altitude": 7.245, "velocity_y": -366.762, "velocity_x": -165.001, "acceleration": -25.35, "downrange_distance": -4.174, "angle": -65.949, "q": 45742.18737495261}
{"time": 422.0, "velocity": 384.621, "altitude": 6.891, "velocity_y": -352.827, "velocity_x": -159.714, "acceleration": -23.444, "downrange_distance": -4.337, "angle": -65.902, "q": 44150.25619619126}
{"time": 423.0, "velocity": 372.407, "altitude": 6.567, "velocity_y": -339.471, "velocity_x": -154.874, "acceleration": -21.725, "downrange_distance": -4.494, "angle": -65.175, "q": 42935.15348254406}
{"time": 424.0, "velocity": 361.304, "altitude": 6.247, "velocity_y": -326.478, "velocity_x": -150.875, "acceleration": -20.361, "downrange_distance": -4.647, "angle": -64.309, "q": 41889.25516377735}
{"time": 425.0, "velocity": 350.404, "altitude": 5.914, "velocity_y": -316.449, "velocity_x": -148.113, "acceleration": -19.234, "downrange_distance": -4.796, "angle": -63.806, "q": 40889.20311859227}
{"time": 426.0, "velocity": 341.321, "altitude": 5.618, "velocity_y": -307.916, "velocity_x": -146.299, "acceleration": -18.196, "downrange_distance": -4.944, "angle": -63.983, "q": 40082.17250105331}
{"time": 427.0, "velocity": 332.996, "altitude": 5.32, "velocity_y": -300.829, "velocity_x": -144.472, "acceleration": -17.344, "downrange_distance": -5.089, "angle": -64.194, "q": 39416.04176427125}
{"time": 428.0, "velocity": 325.504, "altitude": 5.03, "velocity_y": -294.382, "velocity_x": -141.521, "acceleration": -16.704, "downrange_distance": -5.232, "angle": -64.264, "q": 38868.466031706055}
{"time": 429.0, "velocity": 319.56, "altitude": 4.739, "velocity_y": -288.846, "velocity_x": -137.078, "acceleration": -16.455, "downrange_distance": -5.371, "angle": -64.269, "q": 38656.82553165061}
{"time": 430.0, "velocity": 314.564, "altitude": 4.449, "velocity_y": -283.868, "velocity_x": -131.253, "acceleration": -16.563, "downrange_distance": -5.506, "angle": -65.01, "q": 38641.0117611703}
{"time": 431.0, "velocity": 308.026, "altitude": 4.177, "velocity_y": -278.999, "velocity_x": -124.59, "acceleration": -17.107, "downrange_distance": -5.633, "angle": -66.17, "q": 38140.89247314422}
{"time": 432.0, "velocity": 299.149, "altitude": 3.903, "velocity_y": -272.929, "velocity_x": -117.153, "acceleration": -18.077, "downrange_distance": -5.754, "angle": -67.674, "q": 37028.89586411479}
{"time": 433.0, "velocity": 287.205, "altitude": 3.63, "velocity_y": -265.63, "velocity_x": -109.208, "acceleration": -19.17, "downrange_distance": -5.868, "angle": -68.314, "q": 35122.131762444275}
{"time": 434.0, "velocity": 274.166, "altitude": 3.367, "velocity_y": -257.274, "velocity_x": -100.572, "acceleration": -20.129, "downrange_distance": -5.972, "angle": -69.547, "q": 32895.20027852618}
{"time": 435.0, "velocity": 262.793, "altitude": 3.117, "velocity_y": -248.646, "velocity_x": -91.153, "acceleration": -20.775, "downrange_distance": -6.068, "angle": -70.835, "q": 31016.201553355528}
{"time": 436.0, "velocity": 252.516, "altitude": 2.899, "velocity_y": -238.987, "velocity_x": -80.933, "acceleration": -21.215, "downrange_distance": -6.154, "angle": -72.729, "q": 29287.207344508217}
{"time": 437.0, "velocity": 240.024, "altitude": 2.651, "velocity_y": -229.154, "velocity_x": -70.379, "acceleration": -21.511, "downrange_distance": -6.23, "angle": -72.709, "q": 27143.07099968246}
{"time": 438.0, "velocity": 228.644, "altitude": 2.431, "velocity_y": -219.19, "velocity_x": -60.05, "acceleration": -21.704, "downrange_distance": -6.295, "angle": -74.683, "q": 25187.62278504708}
{"time": 439.0, "velocity": 216.193, "altitude": 2.225, "velocity_y": -209.651, "velocity_x": -50.439, "acceleration": -21.781, "downrange_distance": -6.35, "angle": -76.782, "q": 22994.2783302177}
{"time": 440.0, "velocity": 203.937, "altitude": 2.031, "velocity_y": -199.145, "velocity_x": -41.573, "acceleration": -21.73, "downrange_distance": -6.396, "angle": -80.324, "q": 20864.719065763733}
{"time": 441.0, "velocity": 191.225, "altitude": 1.833, "velocity_y": -188.785, "velocity_x": -33.328, "acceleration": -21.457, "downrange_distance": -6.434, "angle": -80.18, "q": 18713.694032057025}
{"time": 442.0, "velocity": 179.509, "altitude": 1.657, "velocity_y": -178.41, "velocity_x": -25.609, "acceleration": -21.046, "downrange_distance": -6.463, "angle": -83.62, "q": 16782.350776399042}
{"time": 443.0, "velocity": 169.24, "altitude": 1.49, "velocity_y": -168.558, "velocity_x": -18.791, "acceleration": -20.524, "downrange_distance": -6.486, "angle": -86.045, "q": 15167.291121875713}
{"time": 444.0, "velocity": 159.052, "altitude": 1.335, "velocity_y": -158.576, "velocity_x": -13.163, "acceleration": -20.164, "downrange_distance": -6.502, "angle": -87.742, "q": 13604.204133348152}
{"time": 445.0, "velocity": 148.934, "altitude": 1.179, "velocity_y": -148.919, "velocity_x": -8.993, "acceleration": -19.911, "downrange_distance": -6.513, "angle": -87.742, "q": 12113.053605277533}
{"time": 446.0, "velocity": 139.264, "altitude": 1.038, "velocity_y": -139.344, "velocity_x": -5.985, "acceleration": -19.786, "downrange_distance": -6.52, "angle": -90.0, "q": 10739.44182079367}
{"time": 447.0, "velocity": 130.106, "altitude": 0.915, "velocity_y": -129.846, "velocity_x": -4.119, "acceleration": -19.66, "downrange_distance": -6.525, "angle": -90.0, "q": 9487.831734163785}
{"time": 448.0, "velocity": 120.391, "altitude": 0.788, "velocity_y": -120.148, "velocity_x": -2.933, "acceleration": -19.616, "downrange_distance": -6.529, "angle": -90.0, "q": 8224.94881342632}
{"time": 449.0, "velocity": 110.4, "altitude": 0.673, "velocity_y": -110.4, "velocity_x": -2.105, "acceleration": -19.647, "downrange_distance": -6.531, "angle": -90.0, "q": 6994.676759174711}
{"time": 450.0, "velocity": 100.686, "altitude": 0.568, "velocity_y": -100.556, "velocity_x": -1.365, "acceleration": -19.74, "downrange_distance": -6.533, "angle": -90.0, "q": 5877.521012254124}
{"time": 451.0, "velocity": 90.694, "altitude": 0.472, "velocity_y": -90.657, "velocity_x": -0.749, "acceleration": -19.771, "downrange_distance": -6.534, "angle": -90.0, "q": 4813.460040177735}
{"time": 452.0, "velocity": 80.702, "altitude": 0.386, "velocity_y": -80.788, "velocity_x": -0.293, "acceleration": -19.74, "downrange_distance": -6.534, "angle": -90.0, "q": 3843.4572586058584}
{"time": 453.0, "velocity": 70.71, "altitude": 0.31, "velocity_y": -71.098, "velocity_x": -0.029, "acceleration": -19.638, "downrange_distance": -6.535, "angle": -90.0, "q": 2972.3726126008946}
{"time": 454.0, "velocity": 60.997, "altitude": 0.247, "velocity_y": -61.593, "velocity_x": 0.112, "acceleration": -19.517, "downrange_distance": -6.535, "angle": -90.0, "q": 2225.223936511796}
{"time": 455.0, "velocity": 51.733, "altitude": 0.195, "velocity_y": -52.41, "velocity_x": 0.158, "acceleration": -19.239, "downrange_distance": -6.534, "angle": -90.0, "q": 1608.7363616308796}
{"time": 456.0, "velocity": 43.702, "altitude": 0.139, "velocity_y": -43.622, "velocity_x": 0.163, "acceleration": -18.765, "downrange_distance": -6.534, "angle": -90.0, "q": 1154.2668067597083}
{"time": 457.0, "velocity": 34.076, "altitude": 0.066, "velocity_y": -35.39, "velocity_x": 0.117, "acceleration": -18.052, "downrange_distance": -6.534, "angle": -90.0, "q": 706.7299220012644}
{"time": 458.0, "velocity": 26.584, "altitude": 0.0, "velocity_y": -27.757, "velocity_x": 0.055, "acceleration": -17.354, "downrange_distance": -6.534, "angle": -90.0, "q": 432.86666100479175}
{"time": 459.0, "velocity": 19.926, "altitude": 0.0, "velocity_y": -20.877, "velocity_x": -0.017, "acceleration": -16.6, "downrange_distance": -6.534, "angle": -90.0, "q": 243.20023748026134}
{"time": 460.0, "velocity": 13.441, "altitude": 0.0, "velocity_y": -14.878, "velocity_x": -0.081, "acceleration": -15.874, "downrange_distance": -6.534, "angle": -90.0, "q": 110.65250237670679}
{"time": 461.0, "velocity": 8.582, "altitude": 0.0, "velocity_y": -9.921, "velocity_x": -0.116, "acceleration": -14.906, "downrange_distance": -6.534, "angle": -90.0, "q": 45.11056663770715}
{"time": 462.0, "velocity": 4.282, "altitude": 0.0, "velocity_y": -6.053, "velocity_x": -0.104, "acceleration": -13.812, "downrange_distance": -6.534, "angle": -90.0, "q": 11.231440213962548}
{"time": 463.0, "velocity": 1.518, "altitude": 0.0, "velocity_y": -2.717, "velocity_x": -0.027, "acceleration": -12.502, "downrange_distance": -6.534, "angle": -90.0, "q": 1.410642573672429}
{"time": 464.0, "velocity": 0.423, "altitude": 0.0, "velocity_y": 0.62, "velocity_x": 0.135, "acceleration": -11.158, "downrange_distance": -6.534, "angle": -90.0, "q": 0.10971211264067808}
