{"time": 0.0, "velocity": 0.277, "altitude": 0.0, "velocity_y": -0.122, "velocity_x": 0.0, "acceleration": 10.711, "downrange_distance": 0.0, "angle": 90.0, "q": 0.046996480116054146}
{"time": 1.0, "velocity": 1.545, "altitude": 0.001, "velocity_y": 1.912, "velocity_x": 0.0, "acceleration": 11.111, "downrange_distance": 0.0, "angle": 90.0, "q": 1.461482890793487}
{"time": 2.0, "velocity": 2.848, "altitude": 0.003, "velocity_y": 3.946, "velocity_x": 0.0, "acceleration": 11.602, "downrange_distance": 0.0, "angle": 90.0, "q": 4.965873691485733}
{"time": 3.0, "velocity": 5.21, "altitude": 0.007, "velocity_y": 6.263, "velocity_x": 0.0, "acceleration": 12.175, "downrange_distance": 0.0, "angle": 90.0, "q": 16.61661640187068}
{"time": 4.0, "velocity": 8.799, "altitude": 0.014, "velocity_y": 9.073, "velocity_x": 0.0, "acceleration": 12.745, "downrange_distance": 0.0, "angle": 90.0, "q": 47.360718247011775}
{"time": 5.0, "velocity": 12.226, "altitude": 0.025, "velocity_y": 12.227, "velocity_x": 0.0, "acceleration": 13.104, "downrange_distance": 0.0, "angle": 90.0, "q": 91.34009407309162}
{"time": 6.0, "velocity": 15.559, "altitude": 0.039, "velocity_y": 15.583, "velocity_x": 0.0, "acceleration": 13.254, "downrange_distance": 0.0, "angle": 90.0, "q": 147.73151667592106}
{"time": 7.0, "velocity": 19.033, "altitude": 0.056, "velocity_y": 19.008, "velocity_x": 0.0, "acceleration": 13.295, "downrange_distance": 0.0, "angle": 90.0, "q": 220.6991992763101}
{"time": 8.0, "velocity": 22.32, "altitude": 0.077, "velocity_y": 22.468, "velocity_x": 0.0, "acceleration": 13.336, "downrange_distance": 0.0, "angle": 90.0, "q": 302.9089165901912}
{"time": 9.0, "velocity": 25.839, "altitude": 0.101, "velocity_y": 25.978, "velocity_x": 0.0, "acceleration": 13.377, "downrange_distance": 0.0, "angle": 90.0, "q": 404.98908596131923}
{"time": 10.0, "velocity": 29.452, "altitude": 0.128, "velocity_y": 29.574, "velocity_x": 0.0, "acceleration": 13.433, "downrange_distance": 0.0, "angle": 90.0, "q": 524.7947443446982}
{"time": 11.0, "velocity": 33.2, "altitude": 0.16, "velocity_y": 33.263, "velocity_x": 0.0, "acceleration": 13.52, "downrange_distance": 0.0, "angle": 90.0, "q": 664.8486028021744}
{"time": 12.0, "velocity": 36.811, "altitude": 0.195, "velocity_y": 37.068, "velocity_x": 0.0, "acceleration": 13.638, "downrange_distance": 0.0, "angle": 90.0, "q": 814.5840202444911}
{"time": 13.0, "velocity": 40.841, "altitude": 0.233, "velocity_y": 40.972, "velocity_x": 0.0, "acceleration": 13.766, "downrange_distance": 0.0, "angle": 90.0, "q": 998.9593175603119}
{"time": 14.0, "velocity": 44.867, "altitude": 0.276, "velocity_y": 44.975, "velocity_x": 0.0, "acceleration": 13.854, "downrange_distance": 0.0, "angle": 90.0, "q": 1200.6323566030735}
{"time": 15.0, "velocity": 48.985, "altitude": 0.323, "velocity_y": 49.046, "velocity_x": 0.0, "acceleration": 13.905, "downrange_distance": 0.0, "angle": 90.0, "q": 1424.6669619490458}
{"time": 16.0, "velocity": 53.2, "altitude": 0.374, "velocity_y": 53.144, "velocity_x": 0.0, "acceleration": 13.924, "downrange_distance": 0.0, "angle": 90.0, "q": 1672.0975232259043}
{"time": 17.0, "velocity": 57.319, "altitude": 0.43, "velocity_y": 57.251, "velocity_x": 0.0, "acceleration": 13.955, "downrange_distance": 0.0, "angle": 90.0, "q": 1930.6848526140775}
{"time": 18.0, "velocity": 61.392, "altitude": 0.489, "velocity_y": 61.405, "velocity_x": 0.0, "acceleration": 14.002, "downrange_distance": 0.0, "angle": 90.0, "q": 2202.0879402319338}
{"time": 19.0, "velocity": 65.28, "altitude": 0.552, "velocity_y": 65.655, "velocity_x": 0.0, "acceleration": 14.11, "downrange_distance": 0.0, "angle": 90.0, "q": 2474.5388338741113}
{"time": 20.0, "velocity": 69.633, "altitude": 0.62, "velocity_y": 70.029, "velocity_x": 0.0, "acceleration": 14.259, "downrange_distance": 0.0, "angle": 90.0, "q": 2797.160945239007}
{"time": 21.0, "velocity": 74.448, "altitude": 0.692, "velocity_y": 74.542, "velocity_x": 0.0, "acceleration": 14.423, "downrange_distance": 0.0, "angle": 90.0, "q": 3175.0154212766215}
{"time": 22.0, "velocity": 79.174, "altitude": 0.769, "velocity_y": 79.197, "velocity_x": 0.0, "acceleration": 14.521, "downrange_distance": 0.0, "angle": 90.0, "q": 3564.114898155414}
{"time": 23.0, "velocity": 83.896, "altitude": 0.85, "velocity_y": 83.944, "velocity_x": 0.0, "acceleration": 14.563, "downrange_distance": 0.0, "angle": 90.0, "q": 3970.1421764927013}
{"time": 24.0, "velocity": 88.615, "altitude": 0.936, "velocity_y": 88.756, "velocity_x": 0.0, "acceleration": 14.595, "downrange_distance": 0.0, "angle": 90.0, "q": 4392.023992636084}
{"time": 25.0, "velocity": 93.619, "altitude": 1.027, "velocity_y": 93.607, "velocity_x": 0.0, "acceleration": 14.657, "downrange_distance": 0.0, "angle": 90.0, "q": 4858.374849546689}
{"time": 26.0, "velocity": 98.337, "altitude": 1.123, "velocity_y": 98.533, "velocity_x": 0.0, "acceleration": 14.764, "downrange_distance": 0.0, "angle": 90.0, "q": 5310.041880838983}
{"time": 27.0, "velocity": 103.476, "altitude": 1.224, "velocity_y": 103.523, "velocity_x": 0.0, "acceleration": 14.856, "downrange_distance": 0.0, "angle": 90.0, "q": 5821.329423879243}
{"time": 28.0, "velocity": 108.476, "altitude": 1.33, "velocity_y": 108.616, "velocity_x": 0.0, "acceleration": 14.948, "downrange_distance": 0.0, "angle": 90.0, "q": 6330.828480327076}
{"time": 29.0, "velocity": 113.615, "altitude": 1.441, "velocity_y": 113.792, "velocity_x": 0.0, "acceleration": 15.009, "downrange_distance": 0.0, "angle": 90.0, "q": 6868.8591211059265}
{"time": 30.0, "velocity": 118.896, "altitude": 1.558, "velocity_y": 119.061, "velocity_x": 0.0, "acceleration": 15.086, "downrange_distance": 0.0, "angle": 90.0, "q": 7435.891120292695}
{"time": 31.0, "velocity": 124.448, "altitude": 1.679, "velocity_y": 124.404, "velocity_x": 0.0, "acceleration": 15.162, "downrange_distance": 0.0, "angle": 90.0, "q": 8048.355553315476}
{"time": 32.0, "velocity": 129.731, "altitude": 1.806, "velocity_y": 129.848, "velocity_x": 0.0, "acceleration": 15.268, "downrange_distance": 0.0, "angle": 90.0, "q": 8635.750045461264}
{"time": 33.0, "velocity": 135.143, "altitude": 1.939, "velocity_y": 135.385, "velocity_x": 0.0, "acceleration": 15.39, "downrange_distance": 0.0, "angle": 90.0, "q": 9247.716459273888}
{"time": 34.0, "velocity": 140.837, "altitude": 2.077, "velocity_y": 141.032, "velocity_x": 0.0, "acceleration": 15.513, "downrange_distance": 0.0, "angle": 90.0, "q": 9905.070583567162}
{"time": 35.0, "velocity": 146.67, "altitude": 2.221, "velocity_y": 146.801, "velocity_x": 0.0, "acceleration": 15.607, "downrange_distance": 0.0, "angle": 90.0, "q": 10587.847938867562}
{"time": 36.0, "velocity": 152.504, "altitude": 2.37, "velocity_y": 152.681, "velocity_x": -0.06, "acceleration": 15.684, "downrange_distance": -0.0, "angle": 90.0, "q": 11274.832229163905}
{"time": 37.0, "velocity": 158.619, "altitude": 2.526, "velocity_y": 158.655, "velocity_x": -0.261, "acceleration": 15.761, "downrange_distance": -0.0, "angle": 90.0, "q": 12005.891885896583}
{"time": 38.0, "velocity": 164.73, "altitude": 2.687, "velocity_y": 164.711, "velocity_x": -0.611, "acceleration": 15.884, "downrange_distance": -0.001, "angle": 90.0, "q": 12737.013012727633}
{"time": 39.0, "velocity": 170.563, "altitude": 2.855, "velocity_y": 170.878, "velocity_x": -1.054, "acceleration": 16.008, "downrange_distance": -0.001, "angle": 90.0, "q": 13422.576889753756}
{"time": 40.0, "velocity": 176.952, "altitude": 3.029, "velocity_y": 177.147, "velocity_x": -1.228, "acceleration": 16.145, "downrange_distance": -0.003, "angle": 90.0, "q": 14191.150292215174}
{"time": 41.0, "velocity": 183.341, "altitude": 3.209, "velocity_y": 183.545, "velocity_x": -0.652, "acceleration": 16.252, "downrange_distance": -0.004, "angle": 90.0, "q": 14953.621646780133}
{"time": 42.0, "velocity": 190.008, "altitude": 3.396, "velocity_y": 190.072, "velocity_x": 0.91, "acceleration": 16.358, "downrange_distance": -0.003, "angle": 89.853, "q": 15752.924136497022}
{"time": 43.0, "velocity": 196.531, "altitude": 3.589, "velocity_y": 196.72, "velocity_x": 3.548, "acceleration": 16.435, "downrange_distance": -0.001, "angle": 89.575, "q": 16517.012415281035}
{"time": 44.0, "velocity": 203.341, "altitude": 3.789, "velocity_y": 203.433, "velocity_x": 7.057, "acceleration": 16.481, "downrange_distance": 0.004, "angle": 89.297, "q": 17315.19873318906}
{"time": 45.0, "velocity": 210.285, "altitude": 3.996, "velocity_y": 210.127, "velocity_x": 11.396, "acceleration": 16.495, "downrange_distance": 0.013, "angle": 89.02, "q": 18119.29805821468}
{"time": 46.0, "velocity": 216.952, "altitude": 4.209, "velocity_y": 216.444, "velocity_x": 16.353, "acceleration": 16.4, "downrange_distance": 0.027, "angle": 88.495, "q": 18855.464326599624}
{"time": 47.0, "velocity": 223.756, "altitude": 4.43, "velocity_y": 222.226, "velocity_x": 21.823, "acceleration": 16.034, "downrange_distance": 0.046, "angle": 87.809, "q": 19591.932317181218}
{"time": 48.0, "velocity": 229.589, "altitude": 4.656, "velocity_y": 227.195, "velocity_x": 27.675, "acceleration": 15.372, "downrange_distance": 0.071, "angle": 86.962, "q": 20132.707550381554}
{"time": 49.0, "velocity": 233.619, "altitude": 4.85, "velocity_y": 231.323, "velocity_x": 33.636, "acceleration": 14.469, "downrange_distance": 0.102, "angle": 85.815, "q": 20415.36694834232}
{"time": 50.0, "velocity": 237.874, "altitude": 5.124, "velocity_y": 234.478, "velocity_x": 39.247, "acceleration": 13.663, "downrange_distance": 0.138, "angle": 84.467, "q": 20549.167843963518}
{"time": 51.0, "velocity": 240.744, "altitude": 5.363, "velocity_y": 236.937, "velocity_x": 44.073, "acceleration": 13.008, "downrange_distance": 0.18, "angle": 83.229, "q": 20506.550003191493}
{"time": 52.0, "velocity": 243.336, "altitude": 5.605, "velocity_y": 238.864, "velocity_x": 47.781, "acceleration": 12.67, "downrange_distance": 0.226, "angle": 82.13, "q": 20402.215850792873}
{"time": 53.0, "velocity": 245.93, "altitude": 5.842, "velocity_y": 240.471, "velocity_x": 50.377, "acceleration": 12.495, "downrange_distance": 0.275, "angle": 81.167, "q": 20302.505874359544}
{"time": 54.0, "velocity": 248.708, "altitude": 6.083, "velocity_y": 242.291, "velocity_x": 52.374, "acceleration": 12.472, "downrange_distance": 0.326, "angle": 80.249, "q": 20214.774848292425}
{"time": 55.0, "velocity": 251.485, "altitude": 6.319, "velocity_y": 244.724, "velocity_x": 54.41, "acceleration": 12.489, "downrange_distance": 0.38, "angle": 79.159, "q": 20133.093958386064}
{"time": 56.0, "velocity": 254.589, "altitude": 6.567, "velocity_y": 247.809, "velocity_x": 56.782, "acceleration": 12.54, "downrange_distance": 0.435, "angle": 77.89, "q": 20065.59713514608}
{"time": 57.0, "velocity": 257.504, "altitude": 6.816, "velocity_y": 250.993, "velocity_x": 59.626, "acceleration": 12.641, "downrange_distance": 0.493, "angle": 76.723, "q": 19957.80784957073}
{"time": 58.0, "velocity": 260.652, "altitude": 7.077, "velocity_y": 254.174, "velocity_x": 62.812, "acceleration": 12.92, "downrange_distance": 0.555, "angle": 75.726, "q": 19850.822884238834}
{"time": 59.0, "velocity": 264.17, "altitude": 7.342, "velocity_y": 257.14, "velocity_x": 66.451, "acceleration": 13.556, "downrange_distance": 0.619, "angle": 74.926, "q": 19778.784203034582}
{"time": 60.0, "velocity": 269.174, "altitude": 7.598, "velocity_y": 260.27, "velocity_x": 70.493, "acceleration": 14.605, "downrange_distance": 0.688, "angle": 74.423, "q": 19937.83656325939}
{"time": 61.0, "velocity": 275.841, "altitude": 7.85, "velocity_y": 264.76, "velocity_x": 75.121, "acceleration": 15.847, "downrange_distance": 0.761, "angle": 74.045, "q": 20332.444932260903}
{"time": 62.0, "velocity": 283.619, "altitude": 8.114, "velocity_y": 270.784, "velocity_x": 80.478, "acceleration": 16.94, "downrange_distance": 0.838, "angle": 73.485, "q": 20841.564316003005}
{"time": 63.0, "velocity": 292.23, "altitude": 8.395, "velocity_y": 278.185, "velocity_x": 86.613, "acceleration": 17.687, "downrange_distance": 0.922, "angle": 72.67, "q": 21405.590951615763}
{"time": 64.0, "velocity": 301.396, "altitude": 8.687, "velocity_y": 286.328, "velocity_x": 93.479, "acceleration": 18.073, "downrange_distance": 1.012, "angle": 71.766, "q": 21991.58246050744}
{"time": 65.0, "velocity": 310.293, "altitude": 8.977, "velocity_y": 294.436, "velocity_x": 100.869, "acceleration": 18.239, "downrange_distance": 1.109, "angle": 70.845, "q": 22511.97775353893}
{"time": 66.0, "velocity": 319.313, "altitude": 9.288, "velocity_y": 301.666, "velocity_x": 108.366, "acceleration": 18.288, "downrange_distance": 1.214, "angle": 70.094, "q": 22959.812440992355}
{"time": 67.0, "velocity": 328.341, "altitude": 9.592, "velocity_y": 308.575, "velocity_x": 115.718, "acceleration": 18.316, "downrange_distance": 1.326, "angle": 69.521, "q": 23394.077067580776}
{"time": 68.0, "velocity": 337.508, "altitude": 9.899, "velocity_y": 315.094, "velocity_x": 122.804, "acceleration": 18.382, "downrange_distance": 1.445, "angle": 69.145, "q": 23800.87188657783}
{"time": 69.0, "velocity": 347.23, "altitude": 10.23, "velocity_y": 321.282, "velocity_x": 129.497, "acceleration": 18.5, "downrange_distance": 1.571, "angle": 68.787, "q": 24179.590581687477}
{"time": 70.0, "velocity": 356.396, "altitude": 10.563, "velocity_y": 327.558, "velocity_x": 135.5, "acceleration": 18.695, "downrange_distance": 1.704, "angle": 68.491, "q": 24429.540263851195}
{"time": 71.0, "velocity": 366.674, "altitude": 10.886, "velocity_y": 336.322, "velocity_x": 140.494, "acceleration": 18.863, "downrange_distance": 1.842, "angle": 68.203, "q": 24821.750146884202}
{"time": 72.0, "velocity": 376.405, "altitude": 11.229, "velocity_y": 345.766, "velocity_x": 144.409, "acceleration": 19.031, "downrange_distance": 1.984, "angle": 68.002, "q": 25035.640931247744}
{"time": 73.0, "velocity": 386.396, "altitude": 11.576, "velocity_y": 355.944, "velocity_x": 147.536, "acceleration": 19.141, "downrange_distance": 2.13, "angle": 67.78, "q": 25224.804775291224}
{"time": 74.0, "velocity": 396.396, "altitude": 11.963, "velocity_y": 366.411, "velocity_x": 150.387, "acceleration": 19.283, "downrange_distance": 2.279, "angle": 67.62, "q": 25236.826379592985}
{"time": 75.0, "velocity": 406.683, "altitude": 12.337, "velocity_y": 378.499, "velocity_x": 153.679, "acceleration": 19.426, "downrange_distance": 2.431, "angle": 67.439, "q": 25282.354892138494}
{"time": 76.0, "velocity": 417.23, "altitude": 12.724, "velocity_y": 388.634, "velocity_x": 157.992, "acceleration": 19.596, "downrange_distance": 2.587, "angle": 67.278, "q": 25266.6409421632}
{"time": 77.0, "velocity": 428.063, "altitude": 13.112, "velocity_y": 397.964, "velocity_x": 163.714, "acceleration": 19.766, "downrange_distance": 2.748, "angle": 67.02, "q": 25234.606110680685}
{"time": 78.0, "velocity": 438.905, "altitude": 13.537, "velocity_y": 406.375, "velocity_x": 170.761, "acceleration": 19.933, "downrange_distance": 2.915, "angle": 66.767, "q": 25024.293410361635}
{"time": 79.0, "velocity": 450.563, "altitude": 13.95, "velocity_y": 414.264, "velocity_x": 178.734, "acceleration": 20.098, "downrange_distance": 3.09, "angle": 66.48, "q": 24898.472813980145}
{"time": 80.0, "velocity": 461.674, "altitude": 14.376, "velocity_y": 420.532, "velocity_x": 187.103, "acceleration": 20.258, "downrange_distance": 3.273, "angle": 66.201, "q": 24617.66435119668}
{"time": 81.0, "velocity": 473.063, "altitude": 14.794, "velocity_y": 427.898, "velocity_x": 195.654, "acceleration": 20.382, "downrange_distance": 3.464, "angle": 65.791, "q": 24345.72505824252}
{"time": 82.0, "velocity": 484.452, "altitude": 15.223, "velocity_y": 435.992, "velocity_x": 204.402, "acceleration": 20.53, "downrange_distance": 3.664, "angle": 65.304, "q": 23992.764800859546}
{"time": 83.0, "velocity": 496.119, "altitude": 15.664, "velocity_y": 446.215, "velocity_x": 213.387, "acceleration": 20.675, "downrange_distance": 3.873, "angle": 64.704, "q": 23577.539948327103}
{"time": 84.0, "velocity": 508.341, "altitude": 16.134, "velocity_y": 457.667, "velocity_x": 222.567, "acceleration": 20.878, "downrange_distance": 4.091, "angle": 64.099, "q": 23074.019139672757}
{"time": 85.0, "velocity": 520.571, "altitude": 16.592, "velocity_y": 469.434, "velocity_x": 231.768, "acceleration": 21.053, "downrange_distance": 4.318, "angle": 63.501, "q": 22568.922866651195}
{"time": 86.0, "velocity": 533.072, "altitude": 17.085, "velocity_y": 479.046, "velocity_x": 241.015, "acceleration": 21.26, "downrange_distance": 4.554, "angle": 63.02, "q": 21927.35904186577}
{"time": 87.0, "velocity": 546.119, "altitude": 17.58, "velocity_y": 487.412, "velocity_x": 250.491, "acceleration": 21.442, "downrange_distance": 4.8, "angle": 62.625, "q": 21284.484619111638}
{"time": 88.0, "velocity": 558.905, "altitude": 18.067, "velocity_y": 494.045, "velocity_x": 260.28, "acceleration": 21.658, "downrange_distance": 5.056, "angle": 62.324, "q": 20618.09665848481}
{"time": 89.0, "velocity": 571.952, "altitude": 18.57, "velocity_y": 500.885, "velocity_x": 270.405, "acceleration": 21.878, "downrange_distance": 5.321, "angle": 62.024, "q": 19884.475877094686}
{"time": 90.0, "velocity": 585.563, "altitude": 19.065, "velocity_y": 510.908, "velocity_x": 280.708, "acceleration": 22.127, "downrange_distance": 5.597, "angle": 61.688, "q": 19190.165105696284}
{"time": 91.0, "velocity": 599.452, "altitude": 19.584, "velocity_y": 522.788, "velocity_x": 290.962, "acceleration": 22.343, "downrange_distance": 5.882, "angle": 61.27, "q": 18410.03661938683}
{"time": 92.0, "velocity": 613.619, "altitude": 20.117, "velocity_y": 535.025, "velocity_x": 300.61, "acceleration": 22.559, "downrange_distance": 6.178, "angle": 60.872, "q": 17583.621133828197}
{"time": 93.0, "velocity": 628.35, "altitude": 20.685, "velocity_y": 547.258, "velocity_x": 309.359, "acceleration": 22.811, "downrange_distance": 6.483, "angle": 60.549, "q": 16666.68828686777}
{"time": 94.0, "velocity": 643.619, "altitude": 21.25, "velocity_y": 560.101, "velocity_x": 317.335, "acceleration": 23.129, "downrange_distance": 6.796, "angle": 60.325, "q": 15775.20093393213}
{"time": 95.0, "velocity": 657.239, "altitude": 21.791, "velocity_y": 571.951, "velocity_x": 325.271, "acceleration": 23.477, "downrange_distance": 7.118, "angle": 60.136, "q": 14871.39009533844}
{"time": 96.0, "velocity": 672.247, "altitude": 22.384, "velocity_y": 582.73, "velocity_x": 334.147, "acceleration": 23.79, "downrange_distance": 7.448, "angle": 59.906, "q": 13889.79488306583}
{"time": 97.0, "velocity": 688.358, "altitude": 22.992, "velocity_y": 594.733, "velocity_x": 344.817, "acceleration": 24.066, "downrange_distance": 7.787, "angle": 59.575, "q": 12923.373630680691}
{"time": 98.0, "velocity": 704.174, "altitude": 23.591, "velocity_y": 608.419, "velocity_x": 357.707, "acceleration": 24.306, "downrange_distance": 8.138, "angle": 59.11, "q": 11978.750682361522}
{"time": 99.0, "velocity": 720.017, "altitude": 24.202, "velocity_y": 620.687, "velocity_x": 372.505, "acceleration": 24.536, "downrange_distance": 8.503, "angle": 58.563, "q": 11027.690152020536}
{"time": 100.0, "velocity": 737.23, "altitude": 24.851, "velocity_y": 630.052, "velocity_x": 388.735, "acceleration": 24.732, "downrange_distance": 8.884, "angle": 57.967, "q": 10057.427261006218}
{"time": 101.0, "velocity": 753.896, "altitude": 25.502, "velocity_y": 638.295, "velocity_x": 405.715, "acceleration": 24.864, "downrange_distance": 9.281, "angle": 57.412, "q": 9100.096330208784}
{"time": 102.0, "velocity": 770.841, "altitude": 26.151, "velocity_y": 644.283, "velocity_x": 422.84, "acceleration": 24.939, "downrange_distance": 9.695, "angle": 56.912, "q": 8195.040945090537}
{"time": 103.0, "velocity": 787.508, "altitude": 26.795, "velocity_y": 647.828, "velocity_x": 439.562, "acceleration": 24.985, "downrange_distance": 10.127, "angle": 56.44, "q": 7335.751665960857}
{"time": 104.0, "velocity": 804.461, "altitude": 27.426, "velocity_y": 656.079, "velocity_x": 455.7, "acceleration": 25.06, "downrange_distance": 10.574, "angle": 55.942, "q": 6548.725196817961}
{"time": 105.0, "velocity": 820.85, "altitude": 28.094, "velocity_y": 667.303, "velocity_x": 471.227, "acceleration": 25.288, "downrange_distance": 11.038, "angle": 55.406, "q": 5744.222658053117}
{"time": 106.0, "velocity": 838.35, "altitude": 28.751, "velocity_y": 682.137, "velocity_x": 486.124, "acceleration": 25.698, "downrange_distance": 11.516, "angle": 54.862, "q": 5025.98371036739}
{"time": 107.0, "velocity": 857.508, "altitude": 29.477, "velocity_y": 697.745, "velocity_x": 500.575, "acceleration": 26.233, "downrange_distance": 12.01, "angle": 54.346, "q": 4291.288788850664}
{"time": 108.0, "velocity": 876.405, "altitude": 30.199, "velocity_y": 714.097, "velocity_x": 514.951, "acceleration": 26.679, "downrange_distance": 12.518, "angle": 53.894, "q": 3626.276362548559}
{"time": 109.0, "velocity": 896.119, "altitude": 30.925, "velocity_y": 727.368, "velocity_x": 529.818, "acceleration": 27.006, "downrange_distance": 13.04, "angle": 53.53, "q": 3028.9814259792147}
{"time": 110.0, "velocity": 914.739, "altitude": 31.651, "velocity_y": 738.69, "velocity_x": 545.542, "acceleration": 27.248, "downrange_distance": 13.578, "angle": 53.225, "q": 2490.390581967176}
{"time": 111.0, "velocity": 934.183, "altitude": 32.402, "velocity_y": 747.155, "velocity_x": 562.092, "acceleration": 27.494, "downrange_distance": 14.131, "angle": 52.964, "q": 2003.075992815056}
{"time": 112.0, "velocity": 954.469, "altitude": 33.176, "velocity_y": 755.833, "velocity_x": 579.168, "acceleration": 27.713, "downrange_distance": 14.702, "angle": 52.697, "q": 1571.4256188188263}
{"time": 113.0, "velocity": 974.461, "altitude": 33.926, "velocity_y": 766.902, "velocity_x": 596.345, "acceleration": 27.93, "downrange_distance": 15.29, "angle": 52.411, "q": 1218.104094692422}
{"time": 114.0, "velocity": 994.739, "altitude": 34.702, "velocity_y": 778.44, "velocity_x": 613.506, "acceleration": 28.143, "downrange_distance": 15.895, "angle": 52.072, "q": 912.6834599130377}
{"time": 115.0, "velocity": 1015.572, "altitude": 35.485, "velocity_y": 791.228, "velocity_x": 630.684, "acceleration": 28.41, "downrange_distance": 16.517, "angle": 51.693, "q": 663.0341926240843}
{"time": 116.0, "velocity": 1036.961, "altitude": 36.297, "velocity_y": 808.388, "velocity_x": 648.167, "acceleration": 28.674, "downrange_distance": 17.156, "angle": 51.284, "q": 458.82185906009767}
{"time": 117.0, "velocity": 1058.072, "altitude": 37.124, "velocity_y": 826.524, "velocity_x": 666.146, "acceleration": 28.999, "downrange_distance": 17.813, "angle": 50.871, "q": 300.83777519293824}
{"time": 118.0, "velocity": 1079.739, "altitude": 37.951, "velocity_y": 841.634, "velocity_x": 684.934, "acceleration": 29.357, "downrange_distance": 18.489, "angle": 50.471, "q": 186.5234139062707}
{"time": 119.0, "velocity": 1102.794, "altitude": 38.851, "velocity_y": 853.471, "velocity_x": 704.723, "acceleration": 29.778, "downrange_distance": 19.184, "angle": 50.084, "q": 101.87105050909975}
{"time": 120.0, "velocity": 1125.58, "altitude": 39.718, "velocity_y": 862.739, "velocity_x": 725.63, "acceleration": 30.165, "downrange_distance": 19.899, "angle": 49.713, "q": 50.97752168353046}
{"time": 121.0, "velocity": 1148.089, "altitude": 40.551, "velocity_y": 870.152, "velocity_x": 747.59, "acceleration": 30.487, "downrange_distance": 20.636, "angle": 49.344, "q": 22.72759359479077}
{"time": 122.0, "velocity": 1171.7, "altitude": 41.451, "velocity_y": 877.87, "velocity_x": 770.53, "acceleration": 30.746, "downrange_distance": 21.395, "angle": 48.941, "q": 7.440982665144568}
{"time": 123.0, "velocity": 1195.294, "altitude": 42.316, "velocity_y": 888.764, "velocity_x": 794.348, "acceleration": 30.973, "downrange_distance": 22.177, "angle": 48.478, "q": 1.6911761071266642}
{"time": 124.0, "velocity": 1219.191, "altitude": 43.216, "velocity_y": 901.586, "velocity_x": 818.572, "acceleration": 31.228, "downrange_distance": 22.984, "angle": 47.984, "q": 0.1419527703630004}
{"time": 125.0, "velocity": 1243.636, "altitude": 44.151, "velocity_y": 915.164, "velocity_x": 842.622, "acceleration": 31.574, "downrange_distance": 23.814, "angle": 47.498, "q": 6.272093676230681e-05}
{"time": 126.0, "velocity": 1268.358, "altitude": 45.079, "velocity_y": 928.939, "velocity_x": 866.188, "acceleration": 31.951, "downrange_distance": 24.669, "angle": 47.05, "q": 0.0}
{"time": 127.0, "velocity": 1293.913, "altitude": 46.021, "velocity_y": 942.124, "velocity_x": 889.511, "acceleration": 32.302, "downrange_distance": 25.546, "angle": 46.634, "q": 0.0}
{"time": 128.0, "velocity": 1319.469, "altitude": 46.951, "velocity_y": 953.673, "velocity_x": 912.971, "acceleration": 32.625, "downrange_distance": 26.448, "angle": 46.277, "q": 0.0}
{"time": 129.0, "velocity": 1346.691, "altitude": 47.951, "velocity_y": 965.452, "velocity_x": 937.211, "acceleration": 32.98, "downrange_distance": 27.373, "angle": 45.91, "q": 0.0}
{"time": 130.0, "velocity": 1373.628, "altitude": 48.918, "velocity_y": 977.801, "velocity_x": 962.487, "acceleration": 33.425, "downrange_distance": 28.323, "angle": 45.524, "q": 0.0}
{"time": 131.0, "velocity": 1398.367, "altitude": 49.885, "velocity_y": 990.594, "velocity_x": 988.758, "acceleration": 33.808, "downrange_distance": 29.298, "angle": 45.103, "q": 0.0}
{"time": 132.0, "velocity": 1425.311, "altitude": 50.922, "velocity_y": 1003.004, "velocity_x": 1015.536, "acceleration": 34.131, "downrange_distance": 30.3, "angle": 44.702, "q": 0.0}
{"time": 133.0, "velocity": 1453.097, "altitude": 51.911, "velocity_y": 1014.545, "velocity_x": 1042.523, "acceleration": 34.453, "downrange_distance": 31.329, "angle": 44.306, "q": 0.0}
{"time": 134.0, "velocity": 1481.969, "altitude": 52.985, "velocity_y": 1025.792, "velocity_x": 1069.583, "acceleration": 34.808, "downrange_distance": 32.385, "angle": 43.933, "q": 0.0}
{"time": 135.0, "velocity": 1511.136, "altitude": 53.986, "velocity_y": 1037.952, "velocity_x": 1096.762, "acceleration": 35.224, "downrange_distance": 33.469, "angle": 43.58, "q": 0.0}
{"time": 136.0, "velocity": 1540.572, "altitude": 55.091, "velocity_y": 1047.389, "velocity_x": 1124.192, "acceleration": 35.521, "downrange_distance": 34.579, "angle": 43.239, "q": 0.0}
{"time": 137.0, "velocity": 1568.35, "altitude": 56.077, "velocity_y": 1063.184, "velocity_x": 1151.991, "acceleration": 35.935, "downrange_distance": 35.717, "angle": 42.886, "q": 0.0}
{"time": 138.0, "velocity": 1597.264, "altitude": 57.123, "velocity_y": 1078.879, "velocity_x": 1179.963, "acceleration": 36.41, "downrange_distance": 36.883, "angle": 42.539, "q": 0.0}
{"time": 139.0, "velocity": 1628.367, "altitude": 58.292, "velocity_y": 1093.936, "velocity_x": 1207.859, "acceleration": 37.008, "downrange_distance": 38.077, "angle": 42.185, "q": 0.0}
{"time": 140.0, "velocity": 1659.764, "altitude": 59.422, "velocity_y": 1108.544, "velocity_x": 1235.678, "acceleration": 37.364, "downrange_distance": 39.299, "angle": 41.851, "q": 0.0}
{"time": 141.0, "velocity": 1691.136, "altitude": 60.52, "velocity_y": 1123.865, "velocity_x": 1264.267, "acceleration": 37.444, "downrange_distance": 40.549, "angle": 41.521, "q": 0.0}
{"time": 142.0, "velocity": 1722.239, "altitude": 61.617, "velocity_y": 1135.604, "velocity_x": 1294.637, "acceleration": 37.277, "downrange_distance": 41.828, "angle": 41.189, "q": 0.0}
{"time": 143.0, "velocity": 1751.969, "altitude": 62.78, "velocity_y": 1147.649, "velocity_x": 1327.147, "acceleration": 37.046, "downrange_distance": 43.139, "angle": 40.82, "q": 0.0}
{"time": 144.0, "velocity": 1781.969, "altitude": 63.951, "velocity_y": 1159.459, "velocity_x": 1360.669, "acceleration": 36.843, "downrange_distance": 44.483, "angle": 40.437, "q": 0.0}
{"time": 145.0, "velocity": 1812.247, "altitude": 65.151, "velocity_y": 1169.405, "velocity_x": 1393.419, "acceleration": 36.669, "downrange_distance": 45.86, "angle": 40.054, "q": 0.0}
{"time": 146.0, "velocity": 1842.802, "altitude": 66.351, "velocity_y": 1177.201, "velocity_x": 1423.697, "acceleration": 36.527, "downrange_distance": 47.269, "angle": 39.68, "q": 0.0}
{"time": 147.0, "velocity": 1874.2, "altitude": 67.487, "velocity_y": 1180.595, "velocity_x": 1450.532, "acceleration": 36.419, "downrange_distance": 48.706, "angle": 39.337, "q": 0.0}
{"time": 148.0, "velocity": 1905.311, "altitude": 68.651, "velocity_y": 1182.341, "velocity_x": 1473.121, "acceleration": 36.298, "downrange_distance": 50.168, "angle": 39.037, "q": 0.0}
{"time": 149.0, "velocity": 1935.589, "altitude": 69.902, "velocity_y": 1183.32, "velocity_x": 1491.339, "acceleration": 30.605, "downrange_distance": 51.65, "angle": 38.786, "q": 0.0}
{"time": 150.0, "velocity": 1948.889, "altitude": 71.052, "velocity_y": 1184.043, "velocity_x": 1505.059, "acceleration": 19.823, "downrange_distance": 53.148, "angle": 38.573, "q": 0.0}
{"time": 151.0, "velocity": 1946.799, "altitude": 72.303, "velocity_y": 1184.555, "velocity_x": 1514.543, "acceleration": 8.474, "downrange_distance": 54.658, "angle": 38.404, "q": 0.0}
{"time": 152.0, "velocity": 1942.077, "altitude": 73.451, "velocity_y": 1184.89, "velocity_x": 1519.999, "acceleration": 2.352, "downrange_distance": 56.175, "angle": 38.269, "q": 0.0}
{"time": 153.0, "velocity": 1937.355, "altitude": 74.599, "velocity_y": 1185.225, "velocity_x": 1522.103, "acceleration": 1.22, "downrange_distance": 57.696, "angle": 38.168, "q": 0.0}
{"time": 154.0, "velocity": 1931.799, "altitude": 75.851, "velocity_y": 1185.199, "velocity_x": 1522.058, "acceleration": 0.588, "downrange_distance": 59.218, "angle": 38.078, "q": 0.0}
{"time": 155.0, "velocity": 1926.103, "altitude": 77.051, "velocity_y": 1184.453, "velocity_x": 1521.368, "acceleration": 0.31, "downrange_distance": 60.74, "angle": 37.974, "q": 0.0}
{"time": 156.0, "velocity": 1920.273, "altitude": 78.251, "velocity_y": 1182.524, "velocity_x": 1521.286, "acceleration": 0.123, "downrange_distance": 62.261, "angle": 37.845, "q": 0.0}
{"time": 157.0, "velocity": 1914.44, "altitude": 79.406, "velocity_y": 1179.148, "velocity_x": 1522.063, "acceleration": 0.056, "downrange_distance": 63.783, "angle": 37.699, "q": 0.0}
{"time": 158.0, "velocity": 1908.603, "altitude": 80.621, "velocity_y": 1173.422, "velocity_x": 1523.431, "acceleration": 0.058, "downrange_distance": 65.306, "angle": 37.534, "q": 0.0}
{"time": 159.0, "velocity": 1902.769, "altitude": 81.779, "velocity_y": 1161.521, "velocity_x": 1525.038, "acceleration": 0.295, "downrange_distance": 66.83, "angle": 37.347, "q": 0.0}
{"time": 160.0, "velocity": 1897.311, "altitude": 82.912, "velocity_y": 1149.872, "velocity_x": 1526.961, "acceleration": 2.048, "downrange_distance": 68.356, "angle": 37.143, "q": 0.0}
{"time": 161.0, "velocity": 1897.05, "altitude": 84.092, "velocity_y": 1138.571, "velocity_x": 1529.47, "acceleration": 4.276, "downrange_distance": 69.884, "angle": 36.906, "q": 0.0}
{"time": 162.0, "velocity": 1898.558, "altitude": 85.151, "velocity_y": 1127.676, "velocity_x": 1532.736, "acceleration": 6.599, "downrange_distance": 71.415, "angle": 36.625, "q": 0.0}
{"time": 163.0, "velocity": 1900.558, "altitude": 86.201, "velocity_y": 1118.346, "velocity_x": 1537.171, "acceleration": 7.523, "downrange_distance": 72.95, "angle": 36.29, "q": 0.0}
{"time": 164.0, "velocity": 1903.197, "altitude": 87.419, "velocity_y": 1114.428, "velocity_x": 1542.756, "acceleration": 7.994, "downrange_distance": 74.49, "angle": 35.943, "q": 0.0}
{"time": 165.0, "velocity": 1905.836, "altitude": 88.52, "velocity_y": 1109.592, "velocity_x": 1549.439, "acceleration": 8.144, "downrange_distance": 76.036, "angle": 35.601, "q": 0.0}
{"time": 166.0, "velocity": 1908.613, "altitude": 89.651, "velocity_y": 1103.599, "velocity_x": 1556.773, "acceleration": 8.173, "downrange_distance": 77.589, "angle": 35.307, "q": 0.0}
{"time": 167.0, "velocity": 1911.253, "altitude": 90.751, "velocity_y": 1097.206, "velocity_x": 1564.379, "acceleration": 8.144, "downrange_distance": 79.15, "angle": 35.057, "q": 0.0}
{"time": 168.0, "velocity": 1913.961, "altitude": 91.818, "velocity_y": 1090.867, "velocity_x": 1571.817, "acceleration": 8.127, "downrange_distance": 80.718, "angle": 34.841, "q": 0.0}
{"time": 169.0, "velocity": 1916.577, "altitude": 92.922, "velocity_y": 1085.129, "velocity_x": 1578.71, "acceleration": 8.149, "downrange_distance": 82.293, "angle": 34.639, "q": 0.0}
{"time": 170.0, "velocity": 1919.589, "altitude": 93.984, "velocity_y": 1080.196, "velocity_x": 1585.081, "acceleration": 8.19, "downrange_distance": 83.875, "angle": 34.441, "q": 0.0}
{"time": 171.0, "velocity": 1922.225, "altitude": 95.003, "velocity_y": 1076.726, "velocity_x": 1591.039, "acceleration": 8.257, "downrange_distance": 85.463, "angle": 34.221, "q": 0.0}
{"time": 172.0, "velocity": 1925.188, "altitude": 96.087, "velocity_y": 1074.633, "velocity_x": 1596.804, "acceleration": 8.296, "downrange_distance": 87.057, "angle": 33.986, "q": 0.0}
{"time": 173.0, "velocity": 1928.244, "altitude": 97.186, "velocity_y": 1073.272, "velocity_x": 1602.422, "acceleration": 8.328, "downrange_distance": 88.657, "angle": 33.755, "q": 0.0}
{"time": 174.0, "velocity": 1931.208, "altitude": 98.251, "velocity_y": 1071.461, "velocity_x": 1608.034, "acceleration": 8.344, "downrange_distance": 90.262, "angle": 33.559, "q": 0.0}
{"time": 175.0, "velocity": 1934.355, "altitude": 99.351, "velocity_y": 1068.877, "velocity_x": 1613.748, "acceleration": 8.374, "downrange_distance": 91.873, "angle": 33.383, "q": 0.0}
{"time": 176.0, "velocity": 1937.504, "altitude": 100.412, "velocity_y": 1065.083, "velocity_x": 1619.598, "acceleration": 8.406, "downrange_distance": 93.49, "angle": 33.224, "q": 0.0}
{"time": 177.0, "velocity": 1940.836, "altitude": 101.464, "velocity_y": 1060.622, "velocity_x": 1625.621, "acceleration": 8.444, "downrange_distance": 95.112, "angle": 33.069, "q": 0.0}
{"time": 178.0, "velocity": 1944.077, "altitude": 102.536, "velocity_y": 1055.77, "velocity_x": 1631.833, "acceleration": 8.47, "downrange_distance": 96.741, "angle": 32.91, "q": 0.0}
{"time": 179.0, "velocity": 1947.411, "altitude": 103.57, "velocity_y": 1051.096, "velocity_x": 1638.223, "acceleration": 8.475, "downrange_distance": 98.376, "angle": 32.733, "q": 0.0}
{"time": 180.0, "velocity": 1950.744, "altitude": 104.605, "velocity_y": 1046.972, "velocity_x": 1644.739, "acceleration": 8.481, "downrange_distance": 100.017, "angle": 32.533, "q": 0.0}
{"time": 181.0, "velocity": 1954.077, "altitude": 105.64, "velocity_y": 1043.835, "velocity_x": 1651.385, "acceleration": 8.537, "downrange_distance": 101.665, "angle": 32.305, "q": 0.0}
{"time": 182.0, "velocity": 1957.645, "altitude": 106.672, "velocity_y": 1041.411, "velocity_x": 1658.208, "acceleration": 8.662, "downrange_distance": 103.32, "angle": 32.064, "q": 0.0}
{"time": 183.0, "velocity": 1961.669, "altitude": 107.714, "velocity_y": 1038.744, "velocity_x": 1665.282, "acceleration": 8.811, "downrange_distance": 104.982, "angle": 31.821, "q": 0.0}
{"time": 184.0, "velocity": 1965.652, "altitude": 108.78, "velocity_y": 1034.496, "velocity_x": 1672.651, "acceleration": 8.916, "downrange_distance": 106.651, "angle": 31.597, "q": 0.0}
{"time": 185.0, "velocity": 1969.726, "altitude": 109.813, "velocity_y": 1029.526, "velocity_x": 1680.333, "acceleration": 8.96, "downrange_distance": 108.327, "angle": 31.382, "q": 0.0}
{"time": 186.0, "velocity": 1973.615, "altitude": 110.835, "velocity_y": 1023.86, "velocity_x": 1688.29, "acceleration": 8.97, "downrange_distance": 110.012, "angle": 31.175, "q": 0.0}
{"time": 187.0, "velocity": 1977.645, "altitude": 111.847, "velocity_y": 1016.692, "velocity_x": 1696.422, "acceleration": 8.994, "downrange_distance": 111.704, "angle": 30.959, "q": 0.0}
{"time": 188.0, "velocity": 1981.948, "altitude": 112.861, "velocity_y": 1009.311, "velocity_x": 1704.587, "acceleration": 9.032, "downrange_distance": 113.405, "angle": 30.735, "q": 0.0}
{"time": 189.0, "velocity": 1986.115, "altitude": 113.831, "velocity_y": 1003.717, "velocity_x": 1712.611, "acceleration": 9.069, "downrange_distance": 115.113, "angle": 30.494, "q": 0.0}
{"time": 190.0, "velocity": 1990.422, "altitude": 114.833, "velocity_y": 999.158, "velocity_x": 1720.312, "acceleration": 9.076, "downrange_distance": 116.83, "angle": 30.256, "q": 0.0}
{"time": 191.0, "velocity": 1994.726, "altitude": 115.847, "velocity_y": 995.528, "velocity_x": 1727.59, "acceleration": 9.075, "downrange_distance": 118.554, "angle": 30.034, "q": 0.0}
{"time": 192.0, "velocity": 1999.17, "altitude": 116.864, "velocity_y": 993.211, "velocity_x": 1734.434, "acceleration": 9.077, "downrange_distance": 120.285, "angle": 29.846, "q": 0.0}
{"time": 193.0, "velocity": 2003.478, "altitude": 117.82, "velocity_y": 991.381, "velocity_x": 1740.931, "acceleration": 9.113, "downrange_distance": 122.022, "angle": 29.681, "q": 0.0}
{"time": 194.0, "velocity": 2007.922, "altitude": 118.801, "velocity_y": 989.506, "velocity_x": 1747.22, "acceleration": 9.15, "downrange_distance": 123.766, "angle": 29.529, "q": 0.0}
{"time": 195.0, "velocity": 2012.508, "altitude": 119.793, "velocity_y": 987.721, "velocity_x": 1753.526, "acceleration": 9.202, "downrange_distance": 125.517, "angle": 29.366, "q": 0.0}
{"time": 196.0, "velocity": 2017.089, "altitude": 120.764, "velocity_y": 986.379, "velocity_x": 1760.037, "acceleration": 9.238, "downrange_distance": 127.274, "angle": 29.195, "q": 0.0}
{"time": 197.0, "velocity": 2021.811, "altitude": 121.771, "velocity_y": 984.967, "velocity_x": 1766.885, "acceleration": 9.272, "downrange_distance": 129.037, "angle": 29.011, "q": 0.0}
{"time": 198.0, "velocity": 2026.67, "altitude": 122.759, "velocity_y": 981.268, "velocity_x": 1774.111, "acceleration": 9.29, "downrange_distance": 130.808, "angle": 28.827, "q": 0.0}
{"time": 199.0, "velocity": 2031.392, "altitude": 123.735, "velocity_y": 976.73, "velocity_x": 1781.766, "acceleration": 9.321, "downrange_distance": 132.585, "angle": 28.63, "q": 0.0}
{"time": 200.0, "velocity": 2036.392, "altitude": 124.725, "velocity_y": 971.828, "velocity_x": 1789.835, "acceleration": 9.367, "downrange_distance": 134.371, "angle": 28.429, "q": 0.0}
{"time": 201.0, "velocity": 2041.115, "altitude": 125.659, "velocity_y": 965.739, "velocity_x": 1798.276, "acceleration": 9.41, "downrange_distance": 136.165, "angle": 28.205, "q": 0.0}
{"time": 202.0, "velocity": 2046.115, "altitude": 126.632, "velocity_y": 959.36, "velocity_x": 1806.986, "acceleration": 9.421, "downrange_distance": 137.968, "angle": 27.965, "q": 0.0}
{"time": 203.0, "velocity": 2051.114, "altitude": 127.596, "velocity_y": 954.295, "velocity_x": 1815.814, "acceleration": 9.399, "downrange_distance": 139.779, "angle": 27.709, "q": 0.0}
{"time": 204.0, "velocity": 2056.118, "altitude": 128.532, "velocity_y": 948.121, "velocity_x": 1824.553, "acceleration": 9.378, "downrange_distance": 141.6, "angle": 27.462, "q": 0.0}
{"time": 205.0, "velocity": 2061.255, "altitude": 129.469, "velocity_y": 941.893, "velocity_x": 1833.06, "acceleration": 9.389, "downrange_distance": 143.428, "angle": 27.228, "q": 0.0}
{"time": 206.0, "velocity": 2066.67, "altitude": 130.44, "velocity_y": 936.657, "velocity_x": 1841.266, "acceleration": 9.432, "downrange_distance": 145.266, "angle": 27.012, "q": 0.0}
{"time": 207.0, "velocity": 2071.67, "altitude": 131.323, "velocity_y": 932.02, "velocity_x": 1849.191, "acceleration": 9.478, "downrange_distance": 147.111, "angle": 26.804, "q": 0.0}
{"time": 208.0, "velocity": 2076.948, "altitude": 132.251, "velocity_y": 928.342, "velocity_x": 1856.872, "acceleration": 9.494, "downrange_distance": 148.964, "angle": 26.612, "q": 0.0}
{"time": 209.0, "velocity": 2082.226, "altitude": 133.169, "velocity_y": 926.595, "velocity_x": 1864.425, "acceleration": 9.48, "downrange_distance": 150.824, "angle": 26.417, "q": 0.0}
{"time": 210.0, "velocity": 2087.504, "altitude": 134.091, "velocity_y": 925.068, "velocity_x": 1871.94, "acceleration": 9.466, "downrange_distance": 152.693, "angle": 26.227, "q": 0.0}
{"time": 211.0, "velocity": 2092.922, "altitude": 135.036, "velocity_y": 922.842, "velocity_x": 1879.515, "acceleration": 9.469, "downrange_distance": 154.568, "angle": 26.038, "q": 0.0}
{"time": 212.0, "velocity": 2098.341, "altitude": 135.957, "velocity_y": 919.422, "velocity_x": 1887.196, "acceleration": 9.519, "downrange_distance": 156.452, "angle": 25.872, "q": 0.0}
{"time": 213.0, "velocity": 2103.619, "altitude": 136.868, "velocity_y": 915.288, "velocity_x": 1895.014, "acceleration": 9.586, "downrange_distance": 158.343, "angle": 25.704, "q": 0.0}
{"time": 214.0, "velocity": 2109.311, "altitude": 137.762, "velocity_y": 910.651, "velocity_x": 1902.937, "acceleration": 9.668, "downrange_distance": 160.242, "angle": 25.538, "q": 0.0}
{"time": 215.0, "velocity": 2115.008, "altitude": 138.66, "velocity_y": 905.756, "velocity_x": 1910.908, "acceleration": 9.72, "downrange_distance": 162.149, "angle": 25.371, "q": 0.0}
{"time": 216.0, "velocity": 2120.978, "altitude": 139.623, "velocity_y": 901.188, "velocity_x": 1918.857, "acceleration": 9.756, "downrange_distance": 164.064, "angle": 25.212, "q": 0.0}
{"time": 217.0, "velocity": 2126.811, "altitude": 140.473, "velocity_y": 897.691, "velocity_x": 1926.736, "acceleration": 9.776, "downrange_distance": 165.986, "angle": 25.045, "q": 0.0}
{"time": 218.0, "velocity": 2132.645, "altitude": 141.351, "velocity_y": 895.23, "velocity_x": 1934.566, "acceleration": 9.78, "downrange_distance": 167.917, "angle": 24.874, "q": 0.0}
{"time": 219.0, "velocity": 2138.341, "altitude": 142.261, "velocity_y": 893.509, "velocity_x": 1942.444, "acceleration": 9.782, "downrange_distance": 169.856, "angle": 24.688, "q": 0.0}
{"time": 220.0, "velocity": 2144.174, "altitude": 143.151, "velocity_y": 892.248, "velocity_x": 1950.507, "acceleration": 9.798, "downrange_distance": 171.802, "angle": 24.493, "q": 0.0}
{"time": 221.0, "velocity": 2150.559, "altitude": 144.027, "velocity_y": 890.676, "velocity_x": 1958.879, "acceleration": 9.86, "downrange_distance": 173.757, "angle": 24.288, "q": 0.0}
{"time": 222.0, "velocity": 2156.811, "altitude": 144.925, "velocity_y": 887.667, "velocity_x": 1967.574, "acceleration": 9.951, "downrange_distance": 175.72, "angle": 24.084, "q": 0.0}
{"time": 223.0, "velocity": 2162.922, "altitude": 145.83, "velocity_y": 881.711, "velocity_x": 1976.555, "acceleration": 10.043, "downrange_distance": 177.692, "angle": 23.882, "q": 0.0}
{"time": 224.0, "velocity": 2168.896, "altitude": 146.702, "velocity_y": 873.762, "velocity_x": 1985.716, "acceleration": 10.105, "downrange_distance": 179.673, "angle": 23.696, "q": 0.0}
{"time": 225.0, "velocity": 2175.285, "altitude": 147.558, "velocity_y": 865.406, "velocity_x": 1994.969, "acceleration": 10.122, "downrange_distance": 181.663, "angle": 23.518, "q": 0.0}
{"time": 226.0, "velocity": 2181.674, "altitude": 148.416, "velocity_y": 857.883, "velocity_x": 2004.188, "acceleration": 10.109, "downrange_distance": 183.663, "angle": 23.337, "q": 0.0}
{"time": 227.0, "velocity": 2188.059, "altitude": 149.249, "velocity_y": 852.066, "velocity_x": 2013.228, "acceleration": 10.081, "downrange_distance": 185.672, "angle": 23.143, "q": 0.0}
{"time": 228.0, "velocity": 2194.448, "altitude": 150.103, "velocity_y": 849.117, "velocity_x": 2022.001, "acceleration": 10.051, "downrange_distance": 187.689, "angle": 22.945, "q": 0.0}
{"time": 229.0, "velocity": 2200.285, "altitude": 150.944, "velocity_y": 848.129, "velocity_x": 2030.49, "acceleration": 10.037, "downrange_distance": 189.716, "angle": 22.753, "q": 0.0}
{"time": 230.0, "velocity": 2206.952, "altitude": 151.793, "velocity_y": 846.994, "velocity_x": 2038.749, "acceleration": 10.054, "downrange_distance": 191.75, "angle": 22.566, "q": 0.0}
{"time": 231.0, "velocity": 2213.619, "altitude": 152.672, "velocity_y": 844.755, "velocity_x": 2046.844, "acceleration": 10.103, "downrange_distance": 193.793, "angle": 22.39, "q": 0.0}
{"time": 232.0, "velocity": 2220.008, "altitude": 153.501, "velocity_y": 841.723, "velocity_x": 2054.928, "acceleration": 10.155, "downrange_distance": 195.844, "angle": 22.225, "q": 0.0}
{"time": 233.0, "velocity": 2226.533, "altitude": 154.334, "velocity_y": 838.583, "velocity_x": 2063.143, "acceleration": 10.176, "downrange_distance": 197.903, "angle": 22.065, "q": 0.0}
{"time": 234.0, "velocity": 2233.2, "altitude": 155.168, "velocity_y": 834.801, "velocity_x": 2071.613, "acceleration": 10.182, "downrange_distance": 199.97, "angle": 21.903, "q": 0.0}
{"time": 235.0, "velocity": 2240.145, "altitude": 155.999, "velocity_y": 830.053, "velocity_x": 2080.349, "acceleration": 10.203, "downrange_distance": 202.046, "angle": 21.741, "q": 0.0}
{"time": 236.0, "velocity": 2246.952, "altitude": 156.837, "velocity_y": 825.837, "velocity_x": 2089.293, "acceleration": 10.254, "downrange_distance": 204.131, "angle": 21.578, "q": 0.0}
{"time": 237.0, "velocity": 2253.619, "altitude": 157.661, "velocity_y": 822.26, "velocity_x": 2098.381, "acceleration": 10.32, "downrange_distance": 206.225, "angle": 21.414, "q": 0.0}
{"time": 238.0, "velocity": 2260.563, "altitude": 158.448, "velocity_y": 818.261, "velocity_x": 2107.554, "acceleration": 10.386, "downrange_distance": 208.328, "angle": 21.246, "q": 0.0}
{"time": 239.0, "velocity": 2268.063, "altitude": 159.257, "velocity_y": 814.018, "velocity_x": 2116.8, "acceleration": 10.451, "downrange_distance": 210.44, "angle": 21.073, "q": 0.0}
{"time": 240.0, "velocity": 2275.145, "altitude": 160.067, "velocity_y": 810.787, "velocity_x": 2126.078, "acceleration": 10.501, "downrange_distance": 212.562, "angle": 20.894, "q": 0.0}
{"time": 241.0, "velocity": 2282.645, "altitude": 160.888, "velocity_y": 807.165, "velocity_x": 2135.345, "acceleration": 10.52, "downrange_distance": 214.692, "angle": 20.721, "q": 0.0}
{"time": 242.0, "velocity": 2290.008, "altitude": 161.722, "velocity_y": 802.76, "velocity_x": 2144.575, "acceleration": 10.526, "downrange_distance": 216.832, "angle": 20.559, "q": 0.0}
{"time": 243.0, "velocity": 2297.23, "altitude": 162.527, "velocity_y": 798.136, "velocity_x": 2153.759, "acceleration": 10.533, "downrange_distance": 218.981, "angle": 20.408, "q": 0.0}
{"time": 244.0, "velocity": 2304.452, "altitude": 163.293, "velocity_y": 794.168, "velocity_x": 2162.893, "acceleration": 10.556, "downrange_distance": 221.14, "angle": 20.26, "q": 0.0}
{"time": 245.0, "velocity": 2311.674, "altitude": 164.096, "velocity_y": 790.729, "velocity_x": 2171.972, "acceleration": 10.579, "downrange_distance": 223.307, "angle": 20.11, "q": 0.0}
{"time": 246.0, "velocity": 2319.311, "altitude": 164.89, "velocity_y": 788.03, "velocity_x": 2181.026, "acceleration": 10.599, "downrange_distance": 225.484, "angle": 19.951, "q": 0.0}
{"time": 247.0, "velocity": 2326.674, "altitude": 165.656, "velocity_y": 785.747, "velocity_x": 2190.085, "acceleration": 10.619, "downrange_distance": 227.669, "angle": 19.78, "q": 0.0}
{"time": 248.0, "velocity": 2334.174, "altitude": 166.448, "velocity_y": 783.459, "velocity_x": 2199.193, "acceleration": 10.624, "downrange_distance": 229.864, "angle": 19.602, "q": 0.0}
{"time": 249.0, "velocity": 2341.674, "altitude": 167.24, "velocity_y": 780.527, "velocity_x": 2208.358, "acceleration": 10.643, "downrange_distance": 232.068, "angle": 19.424, "q": 0.0}
{"time": 250.0, "velocity": 2349.452, "altitude": 168.016, "velocity_y": 776.976, "velocity_x": 2217.583, "acceleration": 10.678, "downrange_distance": 234.281, "angle": 19.251, "q": 0.0}
{"time": 251.0, "velocity": 2357.23, "altitude": 168.782, "velocity_y": 772.866, "velocity_x": 2226.859, "acceleration": 10.743, "downrange_distance": 236.503, "angle": 19.092, "q": 0.0}
{"time": 252.0, "velocity": 2364.739, "altitude": 169.553, "velocity_y": 768.574, "velocity_x": 2236.18, "acceleration": 10.78, "downrange_distance": 238.734, "angle": 18.949, "q": 0.0}
{"time": 253.0, "velocity": 2372.512, "altitude": 170.323, "velocity_y": 764.692, "velocity_x": 2245.579, "acceleration": 10.804, "downrange_distance": 240.975, "angle": 18.813, "q": 0.0}
{"time": 254.0, "velocity": 2380.841, "altitude": 171.077, "velocity_y": 761.739, "velocity_x": 2255.063, "acceleration": 10.829, "downrange_distance": 243.226, "angle": 18.678, "q": 0.0}
{"time": 255.0, "velocity": 2388.756, "altitude": 171.827, "velocity_y": 759.154, "velocity_x": 2264.648, "acceleration": 10.914, "downrange_distance": 245.485, "angle": 18.544, "q": 0.0}
{"time": 256.0, "velocity": 2396.396, "altitude": 172.574, "velocity_y": 756.418, "velocity_x": 2274.317, "acceleration": 11.03, "downrange_distance": 247.755, "angle": 18.403, "q": 0.0}
{"time": 257.0, "velocity": 2404.453, "altitude": 173.304, "velocity_y": 753.462, "velocity_x": 2284.097, "acceleration": 11.144, "downrange_distance": 250.034, "angle": 18.248, "q": 0.0}
{"time": 258.0, "velocity": 2413.059, "altitude": 174.057, "velocity_y": 750.042, "velocity_x": 2294.022, "acceleration": 11.197, "downrange_distance": 252.323, "angle": 18.085, "q": 0.0}
{"time": 259.0, "velocity": 2421.397, "altitude": 174.848, "velocity_y": 745.738, "velocity_x": 2304.107, "acceleration": 11.203, "downrange_distance": 254.622, "angle": 17.922, "q": 0.0}
{"time": 260.0, "velocity": 2430.009, "altitude": 175.625, "velocity_y": 740.66, "velocity_x": 2314.33, "acceleration": 11.178, "downrange_distance": 256.931, "angle": 17.763, "q": 0.0}
{"time": 261.0, "velocity": 2438.342, "altitude": 176.336, "velocity_y": 735.577, "velocity_x": 2324.626, "acceleration": 11.154, "downrange_distance": 259.251, "angle": 17.608, "q": 0.0}
{"time": 262.0, "velocity": 2446.675, "altitude": 177.057, "velocity_y": 730.253, "velocity_x": 2334.934, "acceleration": 11.129, "downrange_distance": 261.581, "angle": 17.454, "q": 0.0}
{"time": 263.0, "velocity": 2455.008, "altitude": 177.797, "velocity_y": 724.999, "velocity_x": 2345.191, "acceleration": 11.102, "downrange_distance": 263.921, "angle": 17.293, "q": 0.0}
{"time": 264.0, "velocity": 2463.619, "altitude": 178.525, "velocity_y": 719.929, "velocity_x": 2355.387, "acceleration": 11.074, "downrange_distance": 266.271, "angle": 17.118, "q": 0.0}
{"time": 265.0, "velocity": 2471.952, "altitude": 179.221, "velocity_y": 715.872, "velocity_x": 2365.563, "acceleration": 11.076, "downrange_distance": 268.632, "angle": 16.933, "q": 0.0}
{"time": 266.0, "velocity": 2480.285, "altitude": 179.929, "velocity_y": 712.401, "velocity_x": 2375.738, "acceleration": 11.108, "downrange_distance": 271.002, "angle": 16.741, "q": 0.0}
{"time": 267.0, "velocity": 2488.896, "altitude": 180.641, "velocity_y": 709.748, "velocity_x": 2385.958, "acceleration": 11.201, "downrange_distance": 273.383, "angle": 16.547, "q": 0.0}
{"time": 268.0, "velocity": 2497.23, "altitude": 181.335, "velocity_y": 707.294, "velocity_x": 2396.186, "acceleration": 11.295, "downrange_distance": 275.774, "angle": 16.367, "q": 0.0}
{"time": 269.0, "velocity": 2506.396, "altitude": 182.063, "velocity_y": 702.727, "velocity_x": 2406.446, "acceleration": 11.414, "downrange_distance": 278.175, "angle": 16.211, "q": 0.0}
{"time": 270.0, "velocity": 2515.655, "altitude": 182.782, "velocity_y": 697.87, "velocity_x": 2416.725, "acceleration": 11.495, "downrange_distance": 280.587, "angle": 16.076, "q": 0.0}
{"time": 271.0, "velocity": 2524.734, "altitude": 183.457, "velocity_y": 693.356, "velocity_x": 2427.071, "acceleration": 11.57, "downrange_distance": 283.009, "angle": 15.95, "q": 0.0}
{"time": 272.0, "velocity": 2533.619, "altitude": 184.121, "velocity_y": 688.822, "velocity_x": 2437.458, "acceleration": 11.593, "downrange_distance": 285.441, "angle": 15.827, "q": 0.0}
{"time": 273.0, "velocity": 2541.952, "altitude": 184.795, "velocity_y": 684.543, "velocity_x": 2447.859, "acceleration": 11.604, "downrange_distance": 287.884, "angle": 15.7, "q": 0.0}
{"time": 274.0, "velocity": 2551.396, "altitude": 185.478, "velocity_y": 682.687, "velocity_x": 2458.234, "acceleration": 11.602, "downrange_distance": 290.337, "angle": 15.564, "q": 0.0}
{"time": 275.0, "velocity": 2560.285, "altitude": 186.157, "velocity_y": 681.167, "velocity_x": 2468.574, "acceleration": 11.611, "downrange_distance": 292.8, "angle": 15.426, "q": 0.0}
{"time": 276.0, "velocity": 2570.285, "altitude": 186.85, "velocity_y": 678.867, "velocity_x": 2478.909, "acceleration": 11.611, "downrange_distance": 295.274, "angle": 15.294, "q": 0.0}
{"time": 277.0, "velocity": 2579.452, "altitude": 187.546, "velocity_y": 676.148, "velocity_x": 2489.285, "acceleration": 11.663, "downrange_distance": 297.758, "angle": 15.172, "q": 0.0}
{"time": 278.0, "velocity": 2588.619, "altitude": 188.215, "velocity_y": 673.141, "velocity_x": 2499.766, "acceleration": 11.736, "downrange_distance": 300.253, "angle": 15.06, "q": 0.0}
{"time": 279.0, "velocity": 2597.794, "altitude": 188.877, "velocity_y": 670.049, "velocity_x": 2510.383, "acceleration": 11.869, "downrange_distance": 302.758, "angle": 14.949, "q": 0.0}
{"time": 280.0, "velocity": 2607.508, "altitude": 189.546, "velocity_y": 666.291, "velocity_x": 2521.108, "acceleration": 11.94, "downrange_distance": 305.273, "angle": 14.827, "q": 0.0}
{"time": 281.0, "velocity": 2617.239, "altitude": 190.214, "velocity_y": 662.527, "velocity_x": 2531.927, "acceleration": 12.009, "downrange_distance": 307.8, "angle": 14.687, "q": 0.0}
{"time": 282.0, "velocity": 2627.23, "altitude": 190.872, "velocity_y": 659.16, "velocity_x": 2542.8, "acceleration": 12.019, "downrange_distance": 310.337, "angle": 14.538, "q": 0.0}
{"time": 283.0, "velocity": 2636.674, "altitude": 191.522, "velocity_y": 655.975, "velocity_x": 2553.731, "acceleration": 12.028, "downrange_distance": 312.886, "angle": 14.39, "q": 0.0}
{"time": 284.0, "velocity": 2646.396, "altitude": 192.173, "velocity_y": 652.518, "velocity_x": 2564.695, "acceleration": 12.006, "downrange_distance": 315.445, "angle": 14.248, "q": 0.0}
{"time": 285.0, "velocity": 2656.396, "altitude": 192.829, "velocity_y": 649.183, "velocity_x": 2575.707, "acceleration": 11.986, "downrange_distance": 318.015, "angle": 14.115, "q": 0.0}
{"time": 286.0, "velocity": 2666.119, "altitude": 193.48, "velocity_y": 645.845, "velocity_x": 2586.745, "acceleration": 11.997, "downrange_distance": 320.596, "angle": 13.992, "q": 0.0}
{"time": 287.0, "velocity": 2675.841, "altitude": 194.109, "velocity_y": 642.255, "velocity_x": 2597.836, "acceleration": 12.039, "downrange_distance": 323.189, "angle": 13.87, "q": 0.0}
{"time": 288.0, "velocity": 2686.119, "altitude": 194.727, "velocity_y": 638.459, "velocity_x": 2609.001, "acceleration": 12.11, "downrange_distance": 325.792, "angle": 13.739, "q": 0.0}
{"time": 289.0, "velocity": 2696.119, "altitude": 195.352, "velocity_y": 635.257, "velocity_x": 2620.301, "acceleration": 12.18, "downrange_distance": 328.407, "angle": 13.601, "q": 0.0}
{"time": 290.0, "velocity": 2705.85, "altitude": 196.001, "velocity_y": 632.077, "velocity_x": 2631.714, "acceleration": 12.25, "downrange_distance": 331.033, "angle": 13.463, "q": 0.0}
{"time": 291.0, "velocity": 2716.674, "altitude": 196.65, "velocity_y": 627.987, "velocity_x": 2643.18, "acceleration": 12.322, "downrange_distance": 333.67, "angle": 13.334, "q": 0.0}
{"time": 292.0, "velocity": 2726.952, "altitude": 197.274, "velocity_y": 623.389, "velocity_x": 2654.602, "acceleration": 12.397, "downrange_distance": 336.319, "angle": 13.221, "q": 0.0}
{"time": 293.0, "velocity": 2736.952, "altitude": 197.89, "velocity_y": 618.986, "velocity_x": 2665.958, "acceleration": 12.442, "downrange_distance": 338.979, "angle": 13.122, "q": 0.0}
{"time": 294.0, "velocity": 2747.785, "altitude": 198.501, "velocity_y": 614.764, "velocity_x": 2677.291, "acceleration": 12.487, "downrange_distance": 341.651, "angle": 13.025, "q": 0.0}
{"time": 295.0, "velocity": 2758.063, "altitude": 199.1, "velocity_y": 611.282, "velocity_x": 2688.72, "acceleration": 12.499, "downrange_distance": 344.334, "angle": 12.915, "q": 0.0}
{"time": 296.0, "velocity": 2768.619, "altitude": 199.703, "velocity_y": 609.55, "velocity_x": 2700.287, "acceleration": 12.54, "downrange_distance": 347.028, "angle": 12.783, "q": 0.0}
{"time": 297.0, "velocity": 2779.174, "altitude": 200.317, "velocity_y": 609.018, "velocity_x": 2711.999, "acceleration": 12.577, "downrange_distance": 349.734, "angle": 12.629, "q": 0.0}
{"time": 298.0, "velocity": 2789.452, "altitude": 200.927, "velocity_y": 608.285, "velocity_x": 2723.867, "acceleration": 12.642, "downrange_distance": 352.452, "angle": 12.461, "q": 0.0}
{"time": 299.0, "velocity": 2800.563, "altitude": 201.543, "velocity_y": 605.961, "velocity_x": 2735.886, "acceleration": 12.707, "downrange_distance": 355.182, "angle": 12.298, "q": 0.0}
{"time": 300.0, "velocity": 2812.239, "altitude": 202.173, "velocity_y": 598.338, "velocity_x": 2748.043, "acceleration": 12.776, "downrange_distance": 357.924, "angle": 12.152, "q": 0.0}
{"time": 301.0, "velocity": 2823.35, "altitude": 202.776, "velocity_y": 590.399, "velocity_x": 2760.309, "acceleration": 12.818, "downrange_distance": 360.678, "angle": 12.021, "q": 0.0}
{"time": 302.0, "velocity": 2834.174, "altitude": 203.337, "velocity_y": 582.448, "velocity_x": 2772.675, "acceleration": 12.83, "downrange_distance": 363.445, "angle": 11.894, "q": 0.0}
{"time": 303.0, "velocity": 2844.174, "altitude": 203.881, "velocity_y": 574.548, "velocity_x": 2785.127, "acceleration": 12.778, "downrange_distance": 366.224, "angle": 11.758, "q": 0.0}
{"time": 304.0, "velocity": 2855.008, "altitude": 204.427, "velocity_y": 567.559, "velocity_x": 2797.571, "acceleration": 12.785, "downrange_distance": 369.015, "angle": 11.607, "q": 0.0}
{"time": 305.0, "velocity": 2866.396, "altitude": 204.986, "velocity_y": 565.199, "velocity_x": 2809.867, "acceleration": 12.854, "downrange_distance": 371.819, "angle": 11.452, "q": 0.0}
{"time": 306.0, "velocity": 2876.961, "altitude": 205.558, "velocity_y": 562.908, "velocity_x": 2821.946, "acceleration": 13.016, "downrange_distance": 374.635, "angle": 11.309, "q": 0.0}
{"time": 307.0, "velocity": 2888.619, "altitude": 206.137, "velocity_y": 560.381, "velocity_x": 2833.857, "acceleration": 13.119, "downrange_distance": 377.463, "angle": 11.19, "q": 0.0}
{"time": 308.0, "velocity": 2900.285, "altitude": 206.709, "velocity_y": 558.164, "velocity_x": 2845.748, "acceleration": 13.166, "downrange_distance": 380.303, "angle": 11.097, "q": 0.0}
{"time": 309.0, "velocity": 2911.683, "altitude": 207.266, "velocity_y": 556.493, "velocity_x": 2857.731, "acceleration": 13.154, "downrange_distance": 383.154, "angle": 11.024, "q": 0.0}
{"time": 310.0, "velocity": 2923.063, "altitude": 207.803, "velocity_y": 554.743, "velocity_x": 2869.829, "acceleration": 13.145, "downrange_distance": 386.018, "angle": 10.951, "q": 0.0}
{"time": 311.0, "velocity": 2934.174, "altitude": 208.336, "velocity_y": 552.616, "velocity_x": 2882.074, "acceleration": 13.194, "downrange_distance": 388.894, "angle": 10.86, "q": 0.0}
{"time": 312.0, "velocity": 2945.285, "altitude": 208.894, "velocity_y": 550.125, "velocity_x": 2894.451, "acceleration": 13.301, "downrange_distance": 391.782, "angle": 10.751, "q": 0.0}
{"time": 313.0, "velocity": 2957.785, "altitude": 209.463, "velocity_y": 547.427, "velocity_x": 2906.934, "acceleration": 13.465, "downrange_distance": 394.683, "angle": 10.634, "q": 0.0}
{"time": 314.0, "velocity": 2969.73, "altitude": 210.014, "velocity_y": 543.796, "velocity_x": 2919.492, "acceleration": 13.569, "downrange_distance": 397.596, "angle": 10.522, "q": 0.0}
{"time": 315.0, "velocity": 2981.674, "altitude": 210.555, "velocity_y": 539.906, "velocity_x": 2932.131, "acceleration": 13.613, "downrange_distance": 400.522, "angle": 10.419, "q": 0.0}
{"time": 316.0, "velocity": 2993.619, "altitude": 211.095, "velocity_y": 535.85, "velocity_x": 2944.862, "acceleration": 13.597, "downrange_distance": 403.46, "angle": 10.323, "q": 0.0}
{"time": 317.0, "velocity": 3005.572, "altitude": 211.62, "velocity_y": 531.859, "velocity_x": 2957.678, "acceleration": 13.582, "downrange_distance": 406.412, "angle": 10.226, "q": 0.0}
{"time": 318.0, "velocity": 3017.239, "altitude": 212.126, "velocity_y": 527.825, "velocity_x": 2970.568, "acceleration": 13.597, "downrange_distance": 409.376, "angle": 10.121, "q": 0.0}
{"time": 319.0, "velocity": 3028.913, "altitude": 212.641, "velocity_y": 524.569, "velocity_x": 2983.494, "acceleration": 13.671, "downrange_distance": 412.353, "angle": 10.004, "q": 0.0}
{"time": 320.0, "velocity": 3041.405, "altitude": 213.178, "velocity_y": 521.794, "velocity_x": 2996.485, "acceleration": 13.803, "downrange_distance": 415.343, "angle": 9.879, "q": 0.0}
{"time": 321.0, "velocity": 3053.628, "altitude": 213.711, "velocity_y": 518.987, "velocity_x": 3009.564, "acceleration": 13.934, "downrange_distance": 418.346, "angle": 9.758, "q": 0.0}
{"time": 322.0, "velocity": 3066.119, "altitude": 214.228, "velocity_y": 515.449, "velocity_x": 3022.789, "acceleration": 14.008, "downrange_distance": 421.362, "angle": 9.647, "q": 0.0}
{"time": 323.0, "velocity": 3078.628, "altitude": 214.739, "velocity_y": 511.271, "velocity_x": 3036.126, "acceleration": 14.053, "downrange_distance": 424.392, "angle": 9.543, "q": 0.0}
{"time": 324.0, "velocity": 3091.396, "altitude": 215.249, "velocity_y": 506.315, "velocity_x": 3049.57, "acceleration": 14.1, "downrange_distance": 427.434, "angle": 9.439, "q": 0.0}
{"time": 325.0, "velocity": 3104.174, "altitude": 215.749, "velocity_y": 501.276, "velocity_x": 3063.086, "acceleration": 14.174, "downrange_distance": 430.491, "angle": 9.331, "q": 0.0}
{"time": 326.0, "velocity": 3116.405, "altitude": 216.24, "velocity_y": 496.784, "velocity_x": 3076.651, "acceleration": 14.217, "downrange_distance": 433.561, "angle": 9.218, "q": 0.0}
{"time": 327.0, "velocity": 3129.73, "altitude": 216.73, "velocity_y": 493.105, "velocity_x": 3090.244, "acceleration": 14.231, "downrange_distance": 436.644, "angle": 9.101, "q": 0.0}
{"time": 328.0, "velocity": 3142.508, "altitude": 217.222, "velocity_y": 489.695, "velocity_x": 3103.844, "acceleration": 14.214, "downrange_distance": 439.741, "angle": 8.986, "q": 0.0}
{"time": 329.0, "velocity": 3155.017, "altitude": 217.713, "velocity_y": 486.329, "velocity_x": 3117.469, "acceleration": 14.198, "downrange_distance": 442.852, "angle": 8.877, "q": 0.0}
{"time": 330.0, "velocity": 3167.794, "altitude": 218.198, "velocity_y": 482.845, "velocity_x": 3131.107, "acceleration": 14.214, "downrange_distance": 445.976, "angle": 8.776, "q": 0.0}
{"time": 331.0, "velocity": 3181.128, "altitude": 218.674, "velocity_y": 479.318, "velocity_x": 3144.794, "acceleration": 14.291, "downrange_distance": 449.114, "angle": 8.678, "q": 0.0}
{"time": 332.0, "velocity": 3193.896, "altitude": 219.141, "velocity_y": 476.044, "velocity_x": 3158.524, "acceleration": 14.431, "downrange_distance": 452.266, "angle": 8.581, "q": 0.0}
{"time": 333.0, "velocity": 3207.508, "altitude": 219.611, "velocity_y": 473.291, "velocity_x": 3172.28, "acceleration": 14.568, "downrange_distance": 455.431, "angle": 8.484, "q": 0.0}
{"time": 334.0, "velocity": 3220.841, "altitude": 220.088, "velocity_y": 470.614, "velocity_x": 3186.082, "acceleration": 14.644, "downrange_distance": 458.61, "angle": 8.391, "q": 0.0}
{"time": 335.0, "velocity": 3233.905, "altitude": 220.563, "velocity_y": 467.658, "velocity_x": 3199.945, "acceleration": 14.658, "downrange_distance": 461.803, "angle": 8.304, "q": 0.0}
{"time": 336.0, "velocity": 3247.794, "altitude": 221.03, "velocity_y": 464.372, "velocity_x": 3213.915, "acceleration": 14.677, "downrange_distance": 465.01, "angle": 8.22, "q": 0.0}
{"time": 337.0, "velocity": 3260.85, "altitude": 221.486, "velocity_y": 461.113, "velocity_x": 3228.044, "acceleration": 14.757, "downrange_distance": 468.231, "angle": 8.138, "q": 0.0}
{"time": 338.0, "velocity": 3274.174, "altitude": 221.932, "velocity_y": 457.94, "velocity_x": 3242.365, "acceleration": 14.929, "downrange_distance": 471.466, "angle": 8.05, "q": 0.0}
{"time": 339.0, "velocity": 3287.785, "altitude": 222.379, "velocity_y": 455.341, "velocity_x": 3256.848, "acceleration": 15.161, "downrange_distance": 474.716, "angle": 7.956, "q": 0.0}
{"time": 340.0, "velocity": 3301.952, "altitude": 222.838, "velocity_y": 452.99, "velocity_x": 3271.424, "acceleration": 15.392, "downrange_distance": 477.98, "angle": 7.856, "q": 0.0}
{"time": 341.0, "velocity": 3316.396, "altitude": 223.302, "velocity_y": 450.069, "velocity_x": 3286.06, "acceleration": 15.561, "downrange_distance": 481.259, "angle": 7.758, "q": 0.0}
{"time": 342.0, "velocity": 3330.841, "altitude": 223.757, "velocity_y": 445.564, "velocity_x": 3300.759, "acceleration": 15.639, "downrange_distance": 484.552, "angle": 7.664, "q": 0.0}
{"time": 343.0, "velocity": 3345.563, "altitude": 224.199, "velocity_y": 440.52, "velocity_x": 3315.515, "acceleration": 15.655, "downrange_distance": 487.86, "angle": 7.576, "q": 0.0}
{"time": 344.0, "velocity": 3360.008, "altitude": 224.628, "velocity_y": 435.41, "velocity_x": 3330.307, "acceleration": 15.641, "downrange_distance": 491.183, "angle": 7.49, "q": 0.0}
{"time": 345.0, "velocity": 3372.794, "altitude": 225.05, "velocity_y": 430.831, "velocity_x": 3345.137, "acceleration": 15.627, "downrange_distance": 494.521, "angle": 7.401, "q": 0.0}
{"time": 346.0, "velocity": 3386.413, "altitude": 225.472, "velocity_y": 427.272, "velocity_x": 3359.974, "acceleration": 15.612, "downrange_distance": 497.874, "angle": 7.305, "q": 0.0}
{"time": 347.0, "velocity": 3400.85, "altitude": 225.9, "velocity_y": 425.026, "velocity_x": 3374.825, "acceleration": 15.597, "downrange_distance": 501.241, "angle": 7.205, "q": 0.0}
{"time": 348.0, "velocity": 3415.841, "altitude": 226.33, "velocity_y": 422.911, "velocity_x": 3389.711, "acceleration": 15.583, "downrange_distance": 504.623, "angle": 7.105, "q": 0.0}
{"time": 349.0, "velocity": 3430.294, "altitude": 226.754, "velocity_y": 420.162, "velocity_x": 3404.69, "acceleration": 15.6, "downrange_distance": 508.02, "angle": 7.01, "q": 0.0}
{"time": 350.0, "velocity": 3444.739, "altitude": 227.171, "velocity_y": 416.686, "velocity_x": 3419.797, "acceleration": 15.647, "downrange_distance": 511.433, "angle": 6.921, "q": 0.0}
{"time": 351.0, "velocity": 3460.017, "altitude": 227.582, "velocity_y": 412.527, "velocity_x": 3435.071, "acceleration": 15.724, "downrange_distance": 514.86, "angle": 6.836, "q": 0.0}
{"time": 352.0, "velocity": 3474.739, "altitude": 227.99, "velocity_y": 407.995, "velocity_x": 3450.449, "acceleration": 15.803, "downrange_distance": 518.303, "angle": 6.753, "q": 0.0}
{"time": 353.0, "velocity": 3489.174, "altitude": 228.394, "velocity_y": 403.532, "velocity_x": 3465.874, "acceleration": 15.883, "downrange_distance": 521.761, "angle": 6.669, "q": 0.0}
{"time": 354.0, "velocity": 3504.452, "altitude": 228.792, "velocity_y": 399.582, "velocity_x": 3481.281, "acceleration": 15.965, "downrange_distance": 525.235, "angle": 6.585, "q": 0.0}
{"time": 355.0, "velocity": 3519.461, "altitude": 229.187, "velocity_y": 396.174, "velocity_x": 3496.731, "acceleration": 16.015, "downrange_distance": 528.724, "angle": 6.501, "q": 0.0}
{"time": 356.0, "velocity": 3534.183, "altitude": 229.579, "velocity_y": 393.29, "velocity_x": 3512.254, "acceleration": 16.034, "downrange_distance": 532.228, "angle": 6.419, "q": 0.0}
{"time": 357.0, "velocity": 3549.191, "altitude": 229.969, "velocity_y": 390.869, "velocity_x": 3527.857, "acceleration": 16.081, "downrange_distance": 535.748, "angle": 6.339, "q": 0.0}
{"time": 358.0, "velocity": 3564.739, "altitude": 230.358, "velocity_y": 388.751, "velocity_x": 3543.565, "acceleration": 16.219, "downrange_distance": 539.284, "angle": 6.26, "q": 0.0}
{"time": 359.0, "velocity": 3579.73, "altitude": 230.745, "velocity_y": 386.653, "velocity_x": 3559.415, "acceleration": 16.448, "downrange_distance": 542.835, "angle": 6.18, "q": 0.0}
{"time": 360.0, "velocity": 3595.841, "altitude": 231.13, "velocity_y": 384.216, "velocity_x": 3575.415, "acceleration": 16.65, "downrange_distance": 546.403, "angle": 6.098, "q": 0.0}
{"time": 361.0, "velocity": 3611.683, "altitude": 231.513, "velocity_y": 381.08, "velocity_x": 3591.558, "acceleration": 16.763, "downrange_distance": 549.986, "angle": 6.017, "q": 0.0}
{"time": 362.0, "velocity": 3627.508, "altitude": 231.893, "velocity_y": 377.049, "velocity_x": 3607.83, "acceleration": 16.785, "downrange_distance": 553.586, "angle": 5.936, "q": 0.0}
{"time": 363.0, "velocity": 3643.35, "altitude": 232.267, "velocity_y": 372.244, "velocity_x": 3624.222, "acceleration": 16.775, "downrange_distance": 557.202, "angle": 5.855, "q": 0.0}
{"time": 364.0, "velocity": 3659.183, "altitude": 232.634, "velocity_y": 367.125, "velocity_x": 3640.687, "acceleration": 16.793, "downrange_distance": 560.834, "angle": 5.775, "q": 0.0}
{"time": 365.0, "velocity": 3675.294, "altitude": 232.993, "velocity_y": 362.302, "velocity_x": 3657.202, "acceleration": 16.841, "downrange_distance": 564.483, "angle": 5.695, "q": 0.0}
{"time": 366.0, "velocity": 3691.405, "altitude": 233.347, "velocity_y": 358.266, "velocity_x": 3673.751, "acceleration": 16.946, "downrange_distance": 568.149, "angle": 5.614, "q": 0.0}
{"time": 367.0, "velocity": 3707.247, "altitude": 233.701, "velocity_y": 355.164, "velocity_x": 3690.329, "acceleration": 17.053, "downrange_distance": 571.831, "angle": 5.534, "q": 0.0}
{"time": 368.0, "velocity": 3723.636, "altitude": 234.055, "velocity_y": 352.756, "velocity_x": 3706.935, "acceleration": 17.161, "downrange_distance": 575.53, "angle": 5.454, "q": 0.0}
{"time": 369.0, "velocity": 3740.025, "altitude": 234.407, "velocity_y": 350.548, "velocity_x": 3723.588, "acceleration": 17.212, "downrange_distance": 579.245, "angle": 5.376, "q": 0.0}
{"time": 370.0, "velocity": 3756.396, "altitude": 234.756, "velocity_y": 348.073, "velocity_x": 3740.315, "acceleration": 17.234, "downrange_distance": 582.977, "angle": 5.301, "q": 0.0}
{"time": 371.0, "velocity": 3772.794, "altitude": 235.102, "velocity_y": 345.094, "velocity_x": 3757.105, "acceleration": 17.256, "downrange_distance": 586.725, "angle": 5.229, "q": 0.0}
{"time": 372.0, "velocity": 3789.461, "altitude": 235.444, "velocity_y": 341.63, "velocity_x": 3773.95, "acceleration": 17.308, "downrange_distance": 590.491, "angle": 5.16, "q": 0.0}
{"time": 373.0, "velocity": 3806.128, "altitude": 235.782, "velocity_y": 337.846, "velocity_x": 3790.893, "acceleration": 17.419, "downrange_distance": 594.273, "angle": 5.093, "q": 0.0}
{"time": 374.0, "velocity": 3822.247, "altitude": 236.116, "velocity_y": 333.97, "velocity_x": 3807.943, "acceleration": 17.529, "downrange_distance": 598.073, "angle": 5.026, "q": 0.0}
{"time": 375.0, "velocity": 3839.469, "altitude": 236.446, "velocity_y": 330.292, "velocity_x": 3825.144, "acceleration": 17.638, "downrange_distance": 601.889, "angle": 4.96, "q": 0.0}
{"time": 376.0, "velocity": 3856.413, "altitude": 236.771, "velocity_y": 327.102, "velocity_x": 3842.465, "acceleration": 17.689, "downrange_distance": 605.723, "angle": 4.893, "q": 0.0}
{"time": 377.0, "velocity": 3873.35, "altitude": 237.093, "velocity_y": 324.547, "velocity_x": 3859.927, "acceleration": 17.711, "downrange_distance": 609.574, "angle": 4.824, "q": 0.0}
{"time": 378.0, "velocity": 3890.285, "altitude": 237.414, "velocity_y": 322.457, "velocity_x": 3877.53, "acceleration": 17.734, "downrange_distance": 613.443, "angle": 4.756, "q": 0.0}
{"time": 379.0, "velocity": 3908.072, "altitude": 237.736, "velocity_y": 320.388, "velocity_x": 3895.215, "acceleration": 17.85, "downrange_distance": 617.329, "angle": 4.689, "q": 0.0}
{"time": 380.0, "velocity": 3926.405, "altitude": 238.058, "velocity_y": 317.838, "velocity_x": 3912.978, "acceleration": 18.058, "downrange_distance": 621.234, "angle": 4.624, "q": 0.0}
{"time": 381.0, "velocity": 3943.35, "altitude": 238.375, "velocity_y": 314.58, "velocity_x": 3930.759, "acceleration": 18.294, "downrange_distance": 625.155, "angle": 4.561, "q": 0.0}
{"time": 382.0, "velocity": 3961.396, "altitude": 238.686, "velocity_y": 310.802, "velocity_x": 3948.642, "acceleration": 18.436, "downrange_distance": 629.095, "angle": 4.498, "q": 0.0}
{"time": 383.0, "velocity": 3978.628, "altitude": 238.99, "velocity_y": 306.999, "velocity_x": 3966.617, "acceleration": 18.483, "downrange_distance": 633.053, "angle": 4.433, "q": 0.0}
{"time": 384.0, "velocity": 3996.413, "altitude": 239.29, "velocity_y": 303.603, "velocity_x": 3984.745, "acceleration": 18.472, "downrange_distance": 637.028, "angle": 4.366, "q": 0.0}
{"time": 385.0, "velocity": 4014.183, "altitude": 239.59, "velocity_y": 300.651, "velocity_x": 4002.963, "acceleration": 18.495, "downrange_distance": 641.022, "angle": 4.294, "q": 0.0}
{"time": 386.0, "velocity": 4030.867, "altitude": 239.891, "velocity_y": 297.757, "velocity_x": 4021.276, "acceleration": 18.577, "downrange_distance": 645.034, "angle": 4.222, "q": 0.0}
{"time": 387.0, "velocity": 4050.302, "altitude": 240.188, "velocity_y": 294.385, "velocity_x": 4039.718, "acceleration": 18.717, "downrange_distance": 649.065, "angle": 4.15, "q": 0.0}
{"time": 388.0, "velocity": 4068.628, "altitude": 240.481, "velocity_y": 290.277, "velocity_x": 4058.296, "acceleration": 18.919, "downrange_distance": 653.114, "angle": 4.081, "q": 0.0}
{"time": 389.0, "velocity": 4087.517, "altitude": 240.766, "velocity_y": 285.634, "velocity_x": 4077.035, "acceleration": 19.123, "downrange_distance": 657.182, "angle": 4.016, "q": 0.0}
{"time": 390.0, "velocity": 4105.572, "altitude": 241.044, "velocity_y": 281.028, "velocity_x": 4095.905, "acceleration": 19.331, "downrange_distance": 661.268, "angle": 3.953, "q": 0.0}
{"time": 391.0, "velocity": 4124.738, "altitude": 241.319, "velocity_y": 277.049, "velocity_x": 4114.874, "acceleration": 19.478, "downrange_distance": 665.373, "angle": 3.893, "q": 0.0}
{"time": 392.0, "velocity": 4142.517, "altitude": 241.591, "velocity_y": 274.014, "velocity_x": 4133.884, "acceleration": 19.592, "downrange_distance": 669.498, "angle": 3.833, "q": 0.0}
{"time": 393.0, "velocity": 4161.683, "altitude": 241.862, "velocity_y": 271.85, "velocity_x": 4152.852, "acceleration": 19.675, "downrange_distance": 673.641, "angle": 3.774, "q": 0.0}
{"time": 394.0, "velocity": 4181.128, "altitude": 242.133, "velocity_y": 270.209, "velocity_x": 4171.886, "acceleration": 19.758, "downrange_distance": 677.804, "angle": 3.717, "q": 0.0}
{"time": 395.0, "velocity": 4199.469, "altitude": 242.402, "velocity_y": 268.66, "velocity_x": 4191.065, "acceleration": 19.842, "downrange_distance": 681.985, "angle": 3.662, "q": 0.0}
{"time": 396.0, "velocity": 4218.913, "altitude": 242.67, "velocity_y": 266.845, "velocity_x": 4210.436, "acceleration": 19.926, "downrange_distance": 686.186, "angle": 3.608, "q": 0.0}
{"time": 397.0, "velocity": 4238.358, "altitude": 242.935, "velocity_y": 264.554, "velocity_x": 4229.945, "acceleration": 19.98, "downrange_distance": 690.406, "angle": 3.555, "q": 0.0}
{"time": 398.0, "velocity": 4256.119, "altitude": 243.198, "velocity_y": 261.714, "velocity_x": 4249.616, "acceleration": 20.003, "downrange_distance": 694.646, "angle": 3.502, "q": 0.0}
{"time": 399.0, "velocity": 4276.683, "altitude": 243.457, "velocity_y": 258.375, "velocity_x": 4269.428, "acceleration": 20.056, "downrange_distance": 698.905, "angle": 3.447, "q": 0.0}
{"time": 400.0, "velocity": 4297.517, "altitude": 243.712, "velocity_y": 254.679, "velocity_x": 4289.355, "acceleration": 20.201, "downrange_distance": 703.185, "angle": 3.391, "q": 0.0}
{"time": 401.0, "velocity": 4317.517, "altitude": 243.963, "velocity_y": 250.822, "velocity_x": 4309.355, "acceleration": 20.408, "downrange_distance": 707.484, "angle": 3.334, "q": 0.0}
{"time": 402.0, "velocity": 4336.961, "altitude": 244.209, "velocity_y": 247.002, "velocity_x": 4329.433, "acceleration": 20.553, "downrange_distance": 711.803, "angle": 3.276, "q": 0.0}
{"time": 403.0, "velocity": 4355.858, "altitude": 244.452, "velocity_y": 243.371, "velocity_x": 4349.601, "acceleration": 20.575, "downrange_distance": 716.143, "angle": 3.218, "q": 0.0}
{"time": 404.0, "velocity": 4376.691, "altitude": 244.692, "velocity_y": 240.012, "velocity_x": 4369.867, "acceleration": 20.567, "downrange_distance": 720.503, "angle": 3.161, "q": 0.0}
{"time": 405.0, "velocity": 4396.969, "altitude": 244.928, "velocity_y": 236.944, "velocity_x": 4390.197, "acceleration": 20.652, "downrange_distance": 724.883, "angle": 3.106, "q": 0.0}
{"time": 406.0, "velocity": 4416.396, "altitude": 245.162, "velocity_y": 234.144, "velocity_x": 4410.628, "acceleration": 20.858, "downrange_distance": 729.283, "angle": 3.052, "q": 0.0}
{"time": 407.0, "velocity": 4436.405, "altitude": 245.393, "velocity_y": 231.557, "velocity_x": 4431.195, "acceleration": 21.096, "downrange_distance": 733.704, "angle": 3.001, "q": 0.0}
{"time": 408.0, "velocity": 4457.794, "altitude": 245.622, "velocity_y": 229.109, "velocity_x": 4451.972, "acceleration": 21.273, "downrange_distance": 738.146, "angle": 2.951, "q": 0.0}
{"time": 409.0, "velocity": 4478.628, "altitude": 245.849, "velocity_y": 226.713, "velocity_x": 4472.992, "acceleration": 21.39, "downrange_distance": 742.608, "angle": 2.903, "q": 0.0}
{"time": 410.0, "velocity": 4499.461, "altitude": 246.073, "velocity_y": 224.288, "velocity_x": 4494.172, "acceleration": 21.479, "downrange_distance": 747.092, "angle": 2.856, "q": 0.0}
{"time": 411.0, "velocity": 4521.405, "altitude": 246.295, "velocity_y": 221.773, "velocity_x": 4515.529, "acceleration": 21.569, "downrange_distance": 751.597, "angle": 2.809, "q": 0.0}
{"time": 412.0, "velocity": 4542.517, "altitude": 246.515, "velocity_y": 219.138, "velocity_x": 4537.009, "acceleration": 21.655, "downrange_distance": 756.123, "angle": 2.762, "q": 0.0}
{"time": 413.0, "velocity": 4563.645, "altitude": 246.731, "velocity_y": 216.384, "velocity_x": 4558.626, "acceleration": 21.74, "downrange_distance": 760.671, "angle": 2.714, "q": 0.0}
{"time": 414.0, "velocity": 4585.302, "altitude": 246.945, "velocity_y": 213.53, "velocity_x": 4580.314, "acceleration": 21.821, "downrange_distance": 765.24, "angle": 2.667, "q": 0.0}
{"time": 415.0, "velocity": 4606.7, "altitude": 247.156, "velocity_y": 210.595, "velocity_x": 4602.103, "acceleration": 21.933, "downrange_distance": 769.831, "angle": 2.618, "q": 0.0}
{"time": 416.0, "velocity": 4629.183, "altitude": 247.363, "velocity_y": 207.596, "velocity_x": 4624.006, "acceleration": 22.076, "downrange_distance": 774.444, "angle": 2.57, "q": 0.0}
{"time": 417.0, "velocity": 4650.294, "altitude": 247.568, "velocity_y": 204.547, "velocity_x": 4646.044, "acceleration": 22.254, "downrange_distance": 779.079, "angle": 2.521, "q": 0.0}
{"time": 418.0, "velocity": 4672.239, "altitude": 247.77, "velocity_y": 201.453, "velocity_x": 4668.207, "acceleration": 22.401, "downrange_distance": 783.736, "angle": 2.472, "q": 0.0}
{"time": 419.0, "velocity": 4694.191, "altitude": 247.968, "velocity_y": 198.324, "velocity_x": 4690.512, "acceleration": 22.549, "downrange_distance": 788.416, "angle": 2.422, "q": 0.0}
{"time": 420.0, "velocity": 4717.239, "altitude": 248.163, "velocity_y": 195.168, "velocity_x": 4712.944, "acceleration": 22.695, "downrange_distance": 793.118, "angle": 2.374, "q": 0.0}
{"time": 421.0, "velocity": 4739.461, "altitude": 248.355, "velocity_y": 192.004, "velocity_x": 4735.522, "acceleration": 22.873, "downrange_distance": 797.842, "angle": 2.326, "q": 0.0}
{"time": 422.0, "velocity": 4762.239, "altitude": 248.544, "velocity_y": 188.859, "velocity_x": 4758.222, "acceleration": 23.019, "downrange_distance": 802.589, "angle": 2.278, "q": 0.0}
{"time": 423.0, "velocity": 4784.747, "altitude": 248.729, "velocity_y": 185.764, "velocity_x": 4781.087, "acceleration": 23.104, "downrange_distance": 807.358, "angle": 2.231, "q": 0.0}
{"time": 424.0, "velocity": 4807.525, "altitude": 248.912, "velocity_y": 182.754, "velocity_x": 4804.082, "acceleration": 23.158, "downrange_distance": 812.151, "angle": 2.186, "q": 0.0}
{"time": 425.0, "velocity": 4830.311, "altitude": 249.092, "velocity_y": 179.853, "velocity_x": 4827.287, "acceleration": 23.244, "downrange_distance": 816.967, "angle": 2.141, "q": 0.0}
{"time": 426.0, "velocity": 4853.913, "altitude": 249.268, "velocity_y": 177.067, "velocity_x": 4850.674, "acceleration": 23.421, "downrange_distance": 821.806, "angle": 2.097, "q": 0.0}
{"time": 427.0, "velocity": 4876.969, "altitude": 249.443, "velocity_y": 174.373, "velocity_x": 4874.278, "acceleration": 23.689, "downrange_distance": 826.668, "angle": 2.053, "q": 0.0}
{"time": 428.0, "velocity": 4901.128, "altitude": 249.614, "velocity_y": 171.73, "velocity_x": 4898.075, "acceleration": 23.987, "downrange_distance": 831.554, "angle": 2.01, "q": 0.0}
{"time": 429.0, "velocity": 4924.461, "altitude": 249.784, "velocity_y": 169.084, "velocity_x": 4922.083, "acceleration": 24.258, "downrange_distance": 836.464, "angle": 1.967, "q": 0.0}
{"time": 430.0, "velocity": 4948.636, "altitude": 249.95, "velocity_y": 166.381, "velocity_x": 4946.265, "acceleration": 24.469, "downrange_distance": 841.398, "angle": 1.925, "q": 0.0}
{"time": 431.0, "velocity": 4973.636, "altitude": 250.114, "velocity_y": 163.583, "velocity_x": 4970.574, "acceleration": 24.651, "downrange_distance": 846.357, "angle": 1.883, "q": 0.0}
{"time": 432.0, "velocity": 4998.636, "altitude": 250.275, "velocity_y": 160.675, "velocity_x": 4994.989, "acceleration": 24.862, "downrange_distance": 851.34, "angle": 1.841, "q": 0.0}
{"time": 433.0, "velocity": 5021.7, "altitude": 250.433, "velocity_y": 157.669, "velocity_x": 5019.528, "acceleration": 25.04, "downrange_distance": 856.347, "angle": 1.798, "q": 0.0}
{"time": 434.0, "velocity": 5046.422, "altitude": 250.587, "velocity_y": 154.597, "velocity_x": 5044.175, "acceleration": 25.187, "downrange_distance": 861.379, "angle": 1.756, "q": 0.0}
{"time": 435.0, "velocity": 5071.691, "altitude": 250.739, "velocity_y": 151.499, "velocity_x": 5068.992, "acceleration": 25.272, "downrange_distance": 866.435, "angle": 1.714, "q": 0.0}
{"time": 436.0, "velocity": 5095.572, "altitude": 250.887, "velocity_y": 148.417, "velocity_x": 5093.947, "acceleration": 25.388, "downrange_distance": 871.517, "angle": 1.673, "q": 0.0}
{"time": 437.0, "velocity": 5120.572, "altitude": 251.032, "velocity_y": 145.384, "velocity_x": 5119.049, "acceleration": 25.535, "downrange_distance": 876.623, "angle": 1.632, "q": 0.0}
{"time": 438.0, "velocity": 5146.136, "altitude": 251.175, "velocity_y": 142.419, "velocity_x": 5144.29, "acceleration": 25.686, "downrange_distance": 881.755, "angle": 1.591, "q": 0.0}
{"time": 439.0, "velocity": 5171.7, "altitude": 251.314, "velocity_y": 139.528, "velocity_x": 5169.782, "acceleration": 25.776, "downrange_distance": 886.912, "angle": 1.551, "q": 0.0}
{"time": 440.0, "velocity": 5197.256, "altitude": 251.451, "velocity_y": 136.705, "velocity_x": 5195.515, "acceleration": 25.864, "downrange_distance": 892.095, "angle": 1.512, "q": 0.0}
{"time": 441.0, "velocity": 5223.367, "altitude": 251.585, "velocity_y": 133.941, "velocity_x": 5221.47, "acceleration": 26.012, "downrange_distance": 897.303, "angle": 1.474, "q": 0.0}
{"time": 442.0, "velocity": 5249.764, "altitude": 251.716, "velocity_y": 131.222, "velocity_x": 5247.654, "acceleration": 26.282, "downrange_distance": 902.538, "angle": 1.436, "q": 0.0}
{"time": 443.0, "velocity": 5275.025, "altitude": 251.844, "velocity_y": 128.535, "velocity_x": 5274.097, "acceleration": 26.554, "downrange_distance": 907.799, "angle": 1.399, "q": 0.0}
{"time": 444.0, "velocity": 5301.691, "altitude": 251.97, "velocity_y": 125.871, "velocity_x": 5300.756, "acceleration": 26.824, "downrange_distance": 913.086, "angle": 1.363, "q": 0.0}
{"time": 445.0, "velocity": 5328.905, "altitude": 252.093, "velocity_y": 123.222, "velocity_x": 5327.54, "acceleration": 27.033, "downrange_distance": 918.4, "angle": 1.328, "q": 0.0}
{"time": 446.0, "velocity": 5356.128, "altitude": 252.214, "velocity_y": 120.587, "velocity_x": 5354.491, "acceleration": 27.239, "downrange_distance": 923.741, "angle": 1.293, "q": 0.0}
{"time": 447.0, "velocity": 5382.802, "altitude": 252.332, "velocity_y": 117.964, "velocity_x": 5381.67, "acceleration": 27.358, "downrange_distance": 929.109, "angle": 1.258, "q": 0.0}
{"time": 448.0, "velocity": 5410.572, "altitude": 252.447, "velocity_y": 115.357, "velocity_x": 5409.129, "acceleration": 27.477, "downrange_distance": 934.505, "angle": 1.224, "q": 0.0}
{"time": 449.0, "velocity": 5438.636, "altitude": 252.56, "velocity_y": 112.767, "velocity_x": 5436.855, "acceleration": 27.629, "downrange_distance": 939.928, "angle": 1.191, "q": 0.0}
{"time": 450.0, "velocity": 5465.589, "altitude": 252.67, "velocity_y": 110.196, "velocity_x": 5464.796, "acceleration": 27.931, "downrange_distance": 945.379, "angle": 1.158, "q": 0.0}
{"time": 451.0, "velocity": 5492.819, "altitude": 252.778, "velocity_y": 107.647, "velocity_x": 5492.819, "acceleration": 28.266, "downrange_distance": 950.857, "angle": 1.126, "q": 0.0}
{"time": 452.0, "velocity": 5521.7, "altitude": 252.883, "velocity_y": 105.123, "velocity_x": 5521.252, "acceleration": 28.597, "downrange_distance": 956.364, "angle": 1.094, "q": 0.0}
{"time": 453.0, "velocity": 5551.422, "altitude": 252.985, "velocity_y": 102.624, "velocity_x": 5549.826, "acceleration": 28.808, "downrange_distance": 961.9, "angle": 1.062, "q": 0.0}
{"time": 454.0, "velocity": 5580.025, "altitude": 253.085, "velocity_y": 100.151, "velocity_x": 5578.662, "acceleration": 29.049, "downrange_distance": 967.464, "angle": 1.031, "q": 0.0}
{"time": 455.0, "velocity": 5608.636, "altitude": 253.183, "velocity_y": 97.705, "velocity_x": 5607.762, "acceleration": 29.293, "downrange_distance": 973.057, "angle": 1.001, "q": 0.0}
{"time": 456.0, "velocity": 5637.525, "altitude": 253.278, "velocity_y": 95.285, "velocity_x": 5637.132, "acceleration": 29.598, "downrange_distance": 978.68, "angle": 0.971, "q": 0.0}
{"time": 457.0, "velocity": 5667.247, "altitude": 253.371, "velocity_y": 92.885, "velocity_x": 5666.752, "acceleration": 29.81, "downrange_distance": 984.332, "angle": 0.941, "q": 0.0}
{"time": 458.0, "velocity": 5696.969, "altitude": 253.462, "velocity_y": 90.498, "velocity_x": 5696.544, "acceleration": 29.99, "downrange_distance": 990.013, "angle": 0.912, "q": 0.0}
{"time": 459.0, "velocity": 5727.247, "altitude": 253.55, "velocity_y": 88.11, "velocity_x": 5726.479, "acceleration": 30.14, "downrange_distance": 995.725, "angle": 0.882, "q": 0.0}
{"time": 460.0, "velocity": 5757.247, "altitude": 253.636, "velocity_y": 85.706, "velocity_x": 5756.613, "acceleration": 30.322, "downrange_distance": 1001.466, "angle": 0.853, "q": 0.0}
{"time": 461.0, "velocity": 5788.089, "altitude": 253.719, "velocity_y": 83.269, "velocity_x": 5787.088, "acceleration": 30.504, "downrange_distance": 1007.238, "angle": 0.824, "q": 0.0}
{"time": 462.0, "velocity": 5818.367, "altitude": 253.8, "velocity_y": 80.788, "velocity_x": 5817.869, "acceleration": 30.715, "downrange_distance": 1013.041, "angle": 0.795, "q": 0.0}
{"time": 463.0, "velocity": 5848.93, "altitude": 253.878, "velocity_y": 78.255, "velocity_x": 5848.865, "acceleration": 30.956, "downrange_distance": 1018.874, "angle": 0.766, "q": 0.0}
{"time": 464.0, "velocity": 5880.319, "altitude": 253.954, "velocity_y": 75.665, "velocity_x": 5880.003, "acceleration": 31.194, "downrange_distance": 1024.739, "angle": 0.736, "q": 0.0}
{"time": 465.0, "velocity": 5911.413, "altitude": 254.027, "velocity_y": 73.018, "velocity_x": 5911.379, "acceleration": 31.437, "downrange_distance": 1030.634, "angle": 0.707, "q": 0.0}
{"time": 466.0, "velocity": 5943.358, "altitude": 254.097, "velocity_y": 70.314, "velocity_x": 5943.05, "acceleration": 31.711, "downrange_distance": 1036.561, "angle": 0.677, "q": 0.0}
{"time": 467.0, "velocity": 5975.858, "altitude": 254.165, "velocity_y": 67.553, "velocity_x": 5975.01, "acceleration": 32.079, "downrange_distance": 1042.521, "angle": 0.647, "q": 0.0}
{"time": 468.0, "velocity": 6008.645, "altitude": 254.23, "velocity_y": 64.734, "velocity_x": 6007.238, "acceleration": 32.447, "downrange_distance": 1048.512, "angle": 0.617, "q": 0.0}
{"time": 469.0, "velocity": 6038.645, "altitude": 254.292, "velocity_y": 61.859, "velocity_x": 6038.645, "acceleration": 32.785, "downrange_distance": 1054.535, "angle": 0.586, "q": 0.0}
{"time": 470.0, "velocity": 6071.995, "altitude": 254.351, "velocity_y": 58.926, "velocity_x": 6071.995, "acceleration": 33.058, "downrange_distance": 1060.59, "angle": 0.556, "q": 0.0}
{"time": 471.0, "velocity": 6106.153, "altitude": 254.407, "velocity_y": 55.941, "velocity_x": 6105.501, "acceleration": 33.389, "downrange_distance": 1066.679, "angle": 0.525, "q": 0.0}
{"time": 472.0, "velocity": 6139.747, "altitude": 254.46, "velocity_y": 52.909, "velocity_x": 6138.802, "acceleration": 33.717, "downrange_distance": 1072.801, "angle": 0.494, "q": 0.0}
{"time": 473.0, "velocity": 6172.256, "altitude": 254.51, "velocity_y": 49.845, "velocity_x": 6172.256, "acceleration": 34.019, "downrange_distance": 1078.956, "angle": 0.464, "q": 0.0}
{"time": 474.0, "velocity": 6206.413, "altitude": 254.557, "velocity_y": 46.764, "velocity_x": 6206.386, "acceleration": 34.23, "downrange_distance": 1085.146, "angle": 0.434, "q": 0.0}
{"time": 475.0, "velocity": 6240.589, "altitude": 254.6, "velocity_y": 43.685, "velocity_x": 6240.589, "acceleration": 34.417, "downrange_distance": 1091.369, "angle": 0.403, "q": 0.0}
{"time": 476.0, "velocity": 6275.302, "altitude": 254.641, "velocity_y": 40.622, "velocity_x": 6275.302, "acceleration": 34.632, "downrange_distance": 1097.627, "angle": 0.374, "q": 0.0}
{"time": 477.0, "velocity": 6310.311, "altitude": 254.678, "velocity_y": 37.587, "velocity_x": 6310.311, "acceleration": 34.848, "downrange_distance": 1103.92, "angle": 0.344, "q": 0.0}
{"time": 478.0, "velocity": 6345.589, "altitude": 254.713, "velocity_y": 34.585, "velocity_x": 6345.589, "acceleration": 35.15, "downrange_distance": 1110.248, "angle": 0.315, "q": 0.0}
{"time": 479.0, "velocity": 6382.525, "altitude": 254.744, "velocity_y": 31.618, "velocity_x": 6381.487, "acceleration": 35.542, "downrange_distance": 1116.611, "angle": 0.287, "q": 0.0}
{"time": 480.0, "velocity": 6417.272, "altitude": 254.773, "velocity_y": 28.687, "velocity_x": 6417.272, "acceleration": 36.026, "downrange_distance": 1123.011, "angle": 0.259, "q": 0.0}
{"time": 481.0, "velocity": 6454.495, "altitude": 254.799, "velocity_y": 25.79, "velocity_x": 6453.67, "acceleration": 36.42, "downrange_distance": 1129.446, "angle": 0.232, "q": 0.0}
{"time": 482.0, "velocity": 6491.145, "altitude": 254.822, "velocity_y": 22.929, "velocity_x": 6490.459, "acceleration": 36.695, "downrange_distance": 1135.918, "angle": 0.206, "q": 0.0}
{"time": 483.0, "velocity": 6527.256, "altitude": 254.842, "velocity_y": 20.103, "velocity_x": 6527.256, "acceleration": 37.001, "downrange_distance": 1142.427, "angle": 0.18, "q": 0.0}
{"time": 484.0, "velocity": 6563.922, "altitude": 254.859, "velocity_y": 17.312, "velocity_x": 6563.922, "acceleration": 37.555, "downrange_distance": 1148.973, "angle": 0.154, "q": 0.0}
{"time": 485.0, "velocity": 6602.247, "altitude": 254.873, "velocity_y": 14.557, "velocity_x": 6602.247, "acceleration": 38.326, "downrange_distance": 1155.556, "angle": 0.129, "q": 0.0}
{"time": 486.0, "velocity": 6641.708, "altitude": 254.885, "velocity_y": 11.836, "velocity_x": 6641.708, "acceleration": 39.098, "downrange_distance": 1162.178, "angle": 0.105, "q": 0.0}
{"time": 487.0, "velocity": 6683.089, "altitude": 254.894, "velocity_y": 9.151, "velocity_x": 6682.188, "acceleration": 39.62, "downrange_distance": 1168.84, "angle": 0.081, "q": 0.0}
{"time": 488.0, "velocity": 6723.089, "altitude": 254.901, "velocity_y": 6.5, "velocity_x": 6722.102, "acceleration": 40.014, "downrange_distance": 1175.542, "angle": 0.058, "q": 0.0}
{"time": 489.0, "velocity": 6763.089, "altitude": 254.905, "velocity_y": 3.886, "velocity_x": 6762.449, "acceleration": 40.345, "downrange_distance": 1182.284, "angle": 0.036, "q": 0.0}
{"time": 490.0, "velocity": 6802.828, "altitude": 254.906, "velocity_y": 1.306, "velocity_x": 6802.828, "acceleration": 40.771, "downrange_distance": 1189.067, "angle": 0.014, "q": 0.0}
{"time": 491.0, "velocity": 6843.934, "altitude": 254.904, "velocity_y": -1.239, "velocity_x": 6843.934, "acceleration": 41.077, "downrange_distance": 1195.89, "angle": -0.007, "q": 0.0}
{"time": 492.0, "velocity": 6885.328, "altitude": 254.901, "velocity_y": -3.748, "velocity_x": 6885.197, "acceleration": 41.32, "downrange_distance": 1202.755, "angle": -0.028, "q": 0.0}
{"time": 493.0, "velocity": 6926.978, "altitude": 254.894, "velocity_y": -6.223, "velocity_x": 6926.515, "acceleration": 41.472, "downrange_distance": 1209.661, "angle": -0.049, "q": 0.0}
{"time": 494.0, "velocity": 6968.367, "altitude": 254.886, "velocity_y": -8.662, "velocity_x": 6968.367, "acceleration": 41.746, "downrange_distance": 1216.608, "angle": -0.068, "q": 0.0}
{"time": 495.0, "velocity": 7010.319, "altitude": 254.875, "velocity_y": -11.066, "velocity_x": 7010.319, "acceleration": 42.115, "downrange_distance": 1223.597, "angle": -0.088, "q": 0.0}
{"time": 496.0, "velocity": 7053.375, "altitude": 254.861, "velocity_y": -13.434, "velocity_x": 7053.375, "acceleration": 42.638, "downrange_distance": 1230.629, "angle": -0.106, "q": 0.0}
{"time": 497.0, "velocity": 7096.153, "altitude": 254.845, "velocity_y": -15.768, "velocity_x": 7096.153, "acceleration": 43.132, "downrange_distance": 1237.704, "angle": -0.125, "q": 0.0}
{"time": 498.0, "velocity": 7140.05, "altitude": 254.827, "velocity_y": -18.066, "velocity_x": 7140.05, "acceleration": 43.563, "downrange_distance": 1244.822, "angle": -0.143, "q": 0.0}
